VHDL Files/src/ALU/three_bit_ALU.vhd
-- VHDL 8 bit processor project
-- Three Bit ALU
-- James Hicks Oct 8 2023

library ieee;
use ieee.std_logic_1164.all;
use ieee.numeric_std.all;

entity three_bit_ALU is
    port (
            num1, num2      : in std_logic_vector (2 downto 0);
            s_u             : in std_logic;
            add             : in std_logic;
            subtract        : in std_logic;
            multiply        : in std_logic;
            result          : out std_logic_vector (5 downto 0)
         );
end three_bit_ALU;

architecture my_arch of three_bit_ALU is

    signal control : std_logic_vector (3 downto 0);

begin
    control <= s_u & add & subtract & multiply;
    with control select result <=
        "00" & std_logic_vector(unsigned('0' & num1) + unsigned('0' & num2)) when "0100",
        "00" & std_logic_vector(unsigned('0' & num1) + unsigned('0' & num2)) when "0101",
        "00" & std_logic_vector(unsigned('0' & num1) + unsigned('0' & num2)) when "0110",
        "00" & std_logic_vector(unsigned('0' & num1) + unsigned('0' & num2)) when "0111",
        "00" & std_logic_vector(unsigned('0' & num1) - unsigned('0' & num2)) when "0010",
        "00" & std_logic_vector(unsigned('0' & num1) - unsigned('0' & num2)) when "0011",
        std_logic_vector(unsigned(num1) * unsigned(num2)) when "0001",
        std_logic_vector(signed(num1) + signed(num2)) when "1100",
        std_logic_vector(signed(num1) + signed(num2)) when "1101",
        std_logic_vector(signed(num1) + signed(num2)) when "1110",
        std_logic_vector(signed(num1) + signed(num2)) when "1111",
        std_logic_vector(signed(num1) - signed(num2)) when "1010",
        std_logic_vector(signed(num1) - signed(num2)) when "1011",
        std_logic_vector(signed(num1) * signed(num2)) when "1001",
        "000000" when others;
end my_arch;

VHDL Files/src/ALU/three_bit_ALU_tb.vhd
-- VHDL 8 bit processor project
-- Three Bit ALU Test Bench
-- James Hicks Oct 9 2023

library ieee;
use ieee.std_logic_1164.all;
use ieee.numeric_std.all;

entity three_bit_ALU_tb is
end three_bit_ALU_tb;

architecture tb_arch of three_bit_ALU_tb is

    signal num1, num2 : std_logic_vector(2 downto 0);
    signal control    : std_logic_vector(3 downto 0);
    signal result     : std_logic_vector(5 downto 0);

begin

    DUT : entity work.three_bit_ALU(my_arch)
        port map (
                    num1 => num1,
                    num2 => num2,
                    s_u => control(3),
                    add => control(2),
                    subtract => control(1),
                    multiply => control(0),
                    result => result
                 );

    process begin
        for I in 0 to 15 loop
            num1 <= "111";
            num2 <= "001";
            control <= std_logic_vector(to_unsigned(I,4));
            wait for 1 ns;
        end loop;

        assert false report "end of test";
        wait;

    end process;

end tb_arch;

VHDL Files/src/ALU/sim.vcd
$date
  Mon Oct 09 10:31:52 2023
$end
$version
  GHDL v0
$end
$timescale
  1 fs
$end
$scope module standard $end
$upscope $end
$scope module std_logic_1164 $end
$upscope $end
$scope module numeric_std $end
$upscope $end
$scope module three_bit_alu_tb $end
$var reg 3 ! num1[2:0] $end
$var reg 3 " num2[2:0] $end
$var reg 4 # control[3:0] $end
$var reg 6 $ result[5:0] $end
$scope module dut $end
$var reg 3 % num1[2:0] $end
$var reg 3 & num2[2:0] $end
$var reg 1 ' s_u $end
$var reg 1 ( add $end
$var reg 1 ) subtract $end
$var reg 1 * multiply $end
$var reg 6 + result[5:0] $end
$var reg 4 , control[3:0] $end
$upscope $end
$upscope $end
$enddefinitions $end
#0
b111 !
b001 "
b0000 #
b000000 $
b111 %
b001 &
0'
0(
0)
0*
b000000 +
b0000 ,
#1000000
b0001 #
b000111 $
1*
b000111 +
b0001 ,
#2000000
b0010 #
b000110 $
1)
0*
b000110 +
b0010 ,
#3000000
b0011 #
1*
b0011 ,
#4000000
b0100 #
b001000 $
1(
0)
0*
b001000 +
b0100 ,
#5000000
b0101 #
1*
b0101 ,
#6000000
b0110 #
1)
0*
b0110 ,
#7000000
b0111 #
1*
b0111 ,
#8000000
b1000 #
b000000 $
1'
0(
0)
0*
b000000 +
b1000 ,
#9000000
b1001 #
b111111 $
1*
b111111 +
b1001 ,
