VHDL Files/src/incrementer/half_adder.vhd
-- VHDL 8 bit processor Project
-- Half Adder
-- James Hicks Sept 21 2023

library ieee;
use ieee.std_logic_1164.all;

entity half_adder is
port (i1, i0 : in std_logic;
      sum, carry : out std_logic);
end half_adder;

architecture my_arch of half_adder is
begin
    sum <= i1 xor i0;
    carry <= i1 and i0;
end my_arch;

VHDL Files/src/incrementer/full_adder.vhd
-- VHDL 8 bit processor Project
-- Full Adder (not composed of half adders)
-- James Hicks Sept 21 2023

library ieee;
use ieee.std_logic_1164.all;

entity full_adder is
    port(carry_in, i1, i0 : in std_logic;
         carry_out, sum : out std_logic);
end full_adder;

architecture my_arch of full_adder is
    signal p2, p1, p0 : std_logic;
begin
    sum <= carry_in xor i1 xor i0;
    p2 <= carry_in and i1;
    p1 <= carry_in and i0;
    p0 <= i1 and i0;
    carry_out <= p2 or p1 or p0;
end my_arch;

-- decomposed architecture --
architecture decomposed_arch of full_adder is
    signal p0, p1, p2 : std_logic;
begin
    -- instantiate two half adders --
    half_adder_xin_yin : entity work.half_adder(my_arch)
        port map(i1=>i1, i0=>i0, sum=>p0, carry=>p1);
    half_adder_cin_sout : entity work.half_adder(my_arch)
        port map(i1=>carry_in, i0=>p0, sum=>sum, carry=>p2);
    carry_out <= p1 or p2;
end decomposed_arch;

VHDL Files/src/8 Bit Adder/2 Bit Adder/two_bit_adder.vhd
-- VHDL 8 bit processor Project
-- 2 Bit Ripple Carry Adder
-- James Hicks Sept 22 2023

-- edited sept 23 to allow for carry in and carry out

library ieee;
use ieee.std_logic_1164.all;

entity two_bit_adder is
    port (
            carry_in : in std_logic;
            a, b : in std_logic_vector (1 downto 0);
            carry_out : out std_logic;
            sum : out std_logic_vector (1 downto 0)
         );
end two_bit_adder;

architecture ripple_carry of two_bit_adder is

    signal carry_through : std_logic;

begin
    lsb : entity work.full_adder(decomposed_arch)
        port map (
                    carry_in => carry_in,
                    i1 => a(0),
                    i0 => b(0),
                    carry_out => carry_through,
                    sum => sum(0)
                );
    msb : entity work.full_adder(decomposed_arch)
        port map (
                    carry_in => carry_through,
                    i1 => a(1),
                    i0 => b(1),
                    carry_out => carry_out,
                    sum => sum(1)
                 );

end ripple_carry;

VHDL Files/src/8 Bit Adder/4 bit adder/four_bit_adder.vhd
-- VHDL 8 bit processor Project
-- Four Bit Adder
-- James Hicks Sept 23 2023

library ieee;
use ieee.std_logic_1164.all;

entity four_bit_adder is
    port (
            carry_in : in std_logic;
            a, b : in std_logic_vector (3 downto 0);
            carry_out : out std_logic
            sum : out std_logic_vector (3 downto 0);
         );
end four_bit_adder;

architecture ripple_carry of four_bit_adder is

signal carry_through : std_logic;

begin
    first_two_bits : entity work.two_bit_adder(ripple_carry)
        port map (
                    carry_in => carry_in,
                    a => a (1 downto 0),
                    b => b (1 downto 0),
                    carry_out => carry_through,
                    sum => sum (1 downto 0)
                 );
    last_two_bits : entity work.two_bit_adder(ripple_carry)
        port map (
                    carry_in => carry_through,
                    a => a (3 downto 2),
                    b => b (3 downto 2),
                    carry_out => carry_out,
                    sum => sum (3 downto 2)
                 );

end ripple_carry;

VHDL Files/src/8 Bit Adder/4 bit Adder/four_bit_adder_subtractor.vhd
-- VHDL 8 bit processor Project
-- Four Bit Binary Adder Subtractor
-- James Hicks Sept 29 2023

library ieee;
use ieee.std_logic_1164.all;

entity four_bit_adder_subtractor is
    port (
            control            : in std_logic;
            a, b               : in std_logic_vector (3 downto 0);
            carry_out          : out std_logic;
            sum_diff           : out std_logic_vector (3 downto 0)
         );
end four_bit_adder_subtractor;

-- The control is essentially a carry in
-- With the added caviet that in addition to being added
-- to the other inputs, it also decides which output to take

architecture my_arch of four_bit_adder_subtractor is

    signal add_carry, sub_carry : std_logic;
    signal sum, diff : std_logic_vector (3 downto 0);
    signal b_flipped : std_logic_vector (3 downto 0);

begin

    b_flipped <= (not b(3)) & (not b(2)) & (not b(1)) & (not b(0));

    add : entity work.four_bit_adder(ripple_carry)
        port map (
                    carry_in => control,
                    a => a,
                    b => b,
                    carry_out => add_carry,
                    sum => sum
                 );
    subtract : entity work.four_bit_adder(ripple_carry)
        port map (
                    carry_in => control,
                    a => a,
                    b => b_flipped,
                    carry_out => sub_carry,
                    sum => diff
                 );

with control select sum_diff <=
    sum when '0',
    diff when '1',
    "XXXX" when others;

with control select carry_out <=
    add_carry when '0',
    sub_carry when '1',
    'X' when others;

--with control select sum_diff <=
--    sum when '0',
--    diff when '1',
--    "XXXX" when others;
--
--with control select carry_out <=
--    add_carry when '0',
--    '0' when '1',
--    'X' when others;

end my_arch;

VHDL Files/src/8 Bit Adder/4 bit Adder/four_bit_adder_subtractor_tb.vhd
-- VHDL 8 bit processor Project
-- Four Bit Binary Adder Subtractor Test Bench
-- James Hicks Sept 29 2023

-- The bit structure is as follows
-- (control bit) & (a input) & (b input)
-- Test bits out simply represents the sum or difference of inputs

library ieee;
use ieee.std_logic_1164.all;
use ieee.numeric_std.all;

entity four_bit_adder_subtractor_tb is
end four_bit_adder_subtractor_tb;

architecture tb_architecture of four_bit_adder_subtractor_tb is

-- 9 inputs (2 4-bit numbers + control) 5 outputs (a 4 bit number + carry)
    signal test_bits_in : std_logic_vector (8 downto 0);
    signal test_bits_out : std_logic_vector (4 downto 0);

begin
    DUT : entity work.four_bit_adder_subtractor(my_arch)
        port map (
                    control => test_bits_in (8),
                    a => test_bits_in (7 downto 4),
                    b => test_bits_in (3 downto 0),
                    carry_out => test_bits_out (4),
                    sum_diff => test_bits_out (3 downto 0)
                 );
    process begin
        for I in 0 to 512 loop
            test_bits_in <= std_logic_vector(to_unsigned(I,9));
            wait for 1 ns;
        end loop;

        assert false report "End of Test";
        wait;

    end process;

end tb_architecture;

VHDL Files/src/8 Bit Adder/4 bit Adder/four_bit_adder_subtractor_simulation.vcd
$date
  Tue Oct 03 11:38:35 2023
$end
$version
  GHDL v0
$end
$timescale
  1 fs
$end
$scope module standard $end
$upscope $end
$scope module std_logic_1164 $end
$upscope $end
$scope module numeric_std $end
$upscope $end
$scope module four_bit_adder_subtractor_tb $end
$var reg 9 ! test_bits_in[8:0] $end
$var reg 5 " test_bits_out[4:0] $end
$scope module dut $end
$var reg 1 # control $end
$var reg 4 $ a[3:0] $end
$var reg 4 % b[3:0] $end
$var reg 1 & carry_out $end
$var reg 4 ' sum_diff[3:0] $end
$var reg 1 ( add_carry $end
$var reg 1 ) sub_carry $end
$var reg 4 * sum[3:0] $end
$var reg 4 + diff[3:0] $end
$var reg 4 , b_flipped[3:0] $end
$scope module add $end
$var reg 1 - carry_in $end
$var reg 4 . a[3:0] $end
$var reg 4 / b[3:0] $end
$var reg 1 0 carry_out $end
$var reg 4 1 sum[3:0] $end
$var reg 1 2 carry_through $end
$scope module first_two_bits $end
$var reg 1 3 carry_in $end
$var reg 2 4 a[1:0] $end
$var reg 2 5 b[1:0] $end
$var reg 1 6 carry_out $end
$var reg 2 7 sum[1:0] $end
$var reg 1 8 carry_through $end
$scope module lsb $end
$var reg 1 9 carry_in $end
$var reg 1 : i1 $end
$var reg 1 ; i0 $end
$var reg 1 < carry_out $end
$var reg 1 = sum $end
$var reg 1 > p0 $end
$var reg 1 ? p1 $end
$var reg 1 @ p2 $end
$scope module half_adder_xin_yin $end
$var reg 1 A i1 $end
$var reg 1 B i0 $end
$var reg 1 C sum $end
$var reg 1 D carry $end
$upscope $end
$scope module half_adder_cin_sout $end
$var reg 1 E i1 $end
$var reg 1 F i0 $end
$var reg 1 G sum $end
$var reg 1 H carry $end
$upscope $end
$upscope $end
$scope module msb $end
$var reg 1 I carry_in $end
$var reg 1 J i1 $end
$var reg 1 K i0 $end
$var reg 1 L carry_out $end
$var reg 1 M sum $end
$var reg 1 N p0 $end
$var reg 1 O p1 $end
$var reg 1 P p2 $end
$scope module half_adder_xin_yin $end
$var reg 1 Q i1 $end
$var reg 1 R i0 $end
$var reg 1 S sum $end
$var reg 1 T carry $end
$upscope $end
$scope module half_adder_cin_sout $end
$var reg 1 U i1 $end
$var reg 1 V i0 $end
$var reg 1 W sum $end
$var reg 1 X carry $end
$upscope $end
$upscope $end
$upscope $end
$scope module last_two_bits $end
$var reg 1 Y carry_in $end
$var reg 2 Z a[1:0] $end
$var reg 2 [ b[1:0] $end
$var reg 1 \ carry_out $end
$var reg 2 ] sum[1:0] $end
$var reg 1 ^ carry_through $end
$scope module lsb $end
$var reg 1 _ carry_in $end
$var reg 1 ` i1 $end
$var reg 1 a i0 $end
$var reg 1 b carry_out $end
$var reg 1 c sum $end
$var reg 1 d p0 $end
$var reg 1 e p1 $end
$var reg 1 f p2 $end
$scope module half_adder_xin_yin $end
$var reg 1 g i1 $end
$var reg 1 h i0 $end
$var reg 1 i sum $end
$var reg 1 j carry $end
$upscope $end
$scope module half_adder_cin_sout $end
$var reg 1 k i1 $end
$var reg 1 l i0 $end
$var reg 1 m sum $end
$var reg 1 n carry $end
$upscope $end
$upscope $end
$scope module msb $end
$var reg 1 o carry_in $end
$var reg 1 p i1 $end
$var reg 1 q i0 $end
$var reg 1 r carry_out $end
$var reg 1 s sum $end
$var reg 1 t p0 $end
$var reg 1 u p1 $end
$var reg 1 v p2 $end
$scope module half_adder_xin_yin $end
$var reg 1 w i1 $end
$var reg 1 x i0 $end
$var reg 1 y sum $end
$var reg 1 z carry $end
$upscope $end
$scope module half_adder_cin_sout $end
$var reg 1 { i1 $end
$var reg 1 | i0 $end
$var reg 1 } sum $end
$var reg 1 !" carry $end
$upscope $end
$upscope $end
$upscope $end
$upscope $end
$scope module subtract $end
$var reg 1 "" carry_in $end
$var reg 4 #" a[3:0] $end
$var reg 4 $" b[3:0] $end
$var reg 1 %" carry_out $end
$var reg 4 &" sum[3:0] $end
$var reg 1 '" carry_through $end
$scope module first_two_bits $end
$var reg 1 (" carry_in $end
$var reg 2 )" a[1:0] $end
$var reg 2 *" b[1:0] $end
$var reg 1 +" carry_out $end
$var reg 2 ," sum[1:0] $end
$var reg 1 -" carry_through $end
$scope module lsb $end
$var reg 1 ." carry_in $end
$var reg 1 /" i1 $end
$var reg 1 0" i0 $end
$var reg 1 1" carry_out $end
$var reg 1 2" sum $end
$var reg 1 3" p0 $end
$var reg 1 4" p1 $end
$var reg 1 5" p2 $end
$scope module half_adder_xin_yin $end
$var reg 1 6" i1 $end
$var reg 1 7" i0 $end
$var reg 1 8" sum $end
$var reg 1 9" carry $end
$upscope $end
$scope module half_adder_cin_sout $end
$var reg 1 :" i1 $end
$var reg 1 ;" i0 $end
$var reg 1 <" sum $end
$var reg 1 =" carry $end
$upscope $end
$upscope $end
$scope module msb $end
$var reg 1 >" carry_in $end
$var reg 1 ?" i1 $end
$var reg 1 @" i0 $end
$var reg 1 A" carry_out $end
$var reg 1 B" sum $end
$var reg 1 C" p0 $end
$var reg 1 D" p1 $end
$var reg 1 E" p2 $end
$scope module half_adder_xin_yin $end
$var reg 1 F" i1 $end
$var reg 1 G" i0 $end
$var reg 1 H" sum $end
$var reg 1 I" carry $end
$upscope $end
$scope module half_adder_cin_sout $end
$var reg 1 J" i1 $end
$var reg 1 K" i0 $end
$var reg 1 L" sum $end
$var reg 1 M" carry $end
$upscope $end
$upscope $end
$upscope $end
$scope module last_two_bits $end
$var reg 1 N" carry_in $end
$var reg 2 O" a[1:0] $end
$var reg 2 P" b[1:0] $end
$var reg 1 Q" carry_out $end
$var reg 2 R" sum[1:0] $end
$var reg 1 S" carry_through $end
$scope module lsb $end
$var reg 1 T" carry_in $end
$var reg 1 U" i1 $end
$var reg 1 V" i0 $end
$var reg 1 W" carry_out $end
$var reg 1 X" sum $end
$var reg 1 Y" p0 $end
$var reg 1 Z" p1 $end
$var reg 1 [" p2 $end
$scope module half_adder_xin_yin $end
$var reg 1 \" i1 $end
$var reg 1 ]" i0 $end
$var reg 1 ^" sum $end
$var reg 1 _" carry $end
$upscope $end
$scope module half_adder_cin_sout $end
$var reg 1 `" i1 $end
$var reg 1 a" i0 $end
$var reg 1 b" sum $end
$var reg 1 c" carry $end
$upscope $end
$upscope $end
$scope module msb $end
$var reg 1 d" carry_in $end
$var reg 1 e" i1 $end
$var reg 1 f" i0 $end
$var reg 1 g" carry_out $end
$var reg 1 h" sum $end
$var reg 1 i" p0 $end
$var reg 1 j" p1 $end
$var reg 1 k" p2 $end
$scope module half_adder_xin_yin $end
$var reg 1 l" i1 $end
$var reg 1 m" i0 $end
$var reg 1 n" sum $end
$var reg 1 o" carry $end
$upscope $end
$scope module half_adder_cin_sout $end
$var reg 1 p" i1 $end
$var reg 1 q" i0 $end
$var reg 1 r" sum $end
$var reg 1 s" carry $end
$upscope $end
$upscope $end
$upscope $end
$upscope $end
$upscope $end
$upscope $end
$enddefinitions $end
#0
b000000000 !
b00000 "
0#
b0000 $
b0000 %
0&
b0000 '
0(
0)
b0000 *
b1111 +
b1111 ,
0-
b0000 .
b0000 /
00
b0000 1
02
03
b00 4
b00 5
06
b00 7
08
09
0:
0;
0<
0=
0>
0?
0@
0A
0B
0C
0D
0E
0F
0G
0H
0I
0J
0K
0L
0M
0N
0O
0P
0Q
0R
0S
0T
0U
0V
0W
0X
0Y
b00 Z
b00 [
0\
b00 ]
0^
0_
0`
0a
0b
0c
0d
0e
0f
0g
0h
0i
0j
0k
0l
0m
0n
0o
0p
0q
0r
0s
0t
0u
0v
0w
0x
0y
0z
0{
0|
0}
0!"
0""
b0000 #"
b1111 $"
0%"
b1111 &"
0'"
0("
b00 )"
b11 *"
0+"
b11 ,"
0-"
0."
0/"
10"
01"
12"
13"
04"
05"
06"
17"
18"
09"
0:"
1;"
1<"
0="
0>"
0?"
1@"
0A"
1B"
1C"
0D"
0E"
0F"
1G"
1H"
0I"
0J"
1K"
1L"
0M"
0N"
b00 O"
b11 P"
0Q"
b11 R"
0S"
0T"
0U"
1V"
0W"
1X"
1Y"
0Z"
0["
0\"
1]"
1^"
0_"
0`"
1a"
1b"
0c"
0d"
0e"
1f"
0g"
1h"
1i"
0j"
0k"
0l"
1m"
1n"
0o"
0p"
1q"
1r"
0s"
#1000000
b000000001 !
b00001 "
b0001 %
b0001 '
b0001 *
b1110 +
b1110 ,
b0001 /
b0001 1
b01 5
b01 7
1;
1=
1>
1B
1C
1F
1G
b1110 $"
b1110 &"
b10 *"
b10 ,"
00"
02"
03"
07"
08"
0;"
0<"
#2000000
b000000010 !
b00010 "
b0010 %
b0010 '
b0010 *
b1101 +
b1101 ,
b0010 /
b0010 1
b10 5
b10 7
0;
0=
0>
0B
0C
0F
0G
1K
1M
1N
1R
1S
1V
1W
b1101 $"
b1101 &"
b01 *"
b01 ,"
10"
12"
13"
17"
18"
1;"
1<"
0@"
0B"
0C"
0G"
0H"
0K"
0L"
#3000000
b000000011 !
b00011 "
b0011 %
b0011 '
b0011 *
b1100 +
b1100 ,
b0011 /
b0011 1
b11 5
b11 7
1;
1=
1>
1B
1C
1F
1G
b1100 $"
b1100 &"
b00 *"
b00 ,"
00"
02"
03"
07"
08"
0;"
0<"
#4000000
b000000100 !
b00100 "
b0100 %
b0100 '
b0100 *
b1011 +
b1011 ,
b0100 /
b0100 1
b00 5
b00 7
0;
0=
0>
0B
0C
0F
0G
0K
0M
0N
0R
0S
0V
0W
b01 [
b01 ]
1a
1c
1d
1h
1i
1l
1m
b1011 $"
b1011 &"
b11 *"
b11 ,"
10"
12"
13"
17"
18"
1;"
1<"
1@"
1B"
1C"
1G"
1H"
1K"
1L"
b10 P"
b10 R"
0V"
0X"
0Y"
0]"
0^"
0a"
0b"
#5000000
b000000101 !
b00101 "
b0101 %
b0101 '
b0101 *
b1010 +
b1010 ,
b0101 /
b0101 1
b01 5
b01 7
1;
1=
1>
1B
1C
1F
1G
b1010 $"
b1010 &"
b10 *"
b10 ,"
00"
02"
03"
07"
08"
0;"
0<"
#6000000
b000000110 !
b00110 "
b0110 %
b0110 '
b0110 *
b1001 +
b1001 ,
b0110 /
b0110 1
b10 5
b10 7
0;
0=
0>
0B
0C
0F
0G
1K
1M
1N
1R
1S
1V
1W
b1001 $"
b1001 &"
b01 *"
b01 ,"
10"
12"
13"
17"
18"
1;"
1<"
0@"
0B"
0C"
0G"
0H"
0K"
0L"
#7000000
b000000111 !
b00111 "
b0111 %
b0111 '
b0111 *
b1000 +
b1000 ,
b0111 /
b0111 1
b11 5
b11 7
1;
1=
1>
1B
1C
1F
1G
b1000 $"
b1000 &"
b00 *"
b00 ,"
00"
02"
03"
07"
08"
0;"
0<"
#8000000
b000001000 !
b01000 "
b1000 %
b1000 '
b1000 *
b0111 +
b0111 ,
b1000 /
b1000 1
b00 5
b00 7
0;
0=
0>
0B
0C
0F
0G
0K
0M
0N
0R
0S
0V
0W
b10 [
b10 ]
0a
0c
0d
0h
0i
0l
0m
1q
1s
1t
1x
1y
1|
1}
b0111 $"
b0111 &"
b11 *"
b11 ,"
10"
12"
13"
17"
18"
1;"
1<"
1@"
1B"
1C"
1G"
1H"
1K"
1L"
b01 P"
b01 R"
1V"
1X"
1Y"
1]"
1^"
1a"
1b"
0f"
0h"
0i"
0m"
0n"
0q"
0r"
#9000000
b000001001 !
b01001 "
b1001 %
b1001 '
b1001 *
b0110 +
b0110 ,
b1001 /
b1001 1
b01 5
b01 7
1;
1=
1>
1B
1C
1F
1G
b0110 $"
b0110 &"
b10 *"
b10 ,"
00"
02"
03"
07"
08"
0;"
0<"
#10000000
b000001010 !
b01010 "
b1010 %
b1010 '
b1010 *
b0101 +
b0101 ,
b1010 /
b1010 1
b10 5
b10 7
0;
0=
0>
0B
0C
0F
0G
1K
1M
1N
1R
1S
1V
1W
b0101 $"
b0101 &"
b01 *"
b01 ,"
10"
12"
13"
17"
18"
1;"
1<"
0@"
0B"
0C"
0G"
0H"
0K"
0L"
#11000000
b000001011 !
b01011 "
b1011 %
b1011 '
b1011 *
b0100 +
b0100 ,
b1011 /
b1011 1
b11 5
b11 7
1;
1=
1>
1B
1C
1F
1G
b0100 $"
b0100 &"
b00 *"
b00 ,"
00"
02"
03"
07"
08"
0;"
0<"
#12000000
b000001100 !
b01100 "
b1100 %
b1100 '
b1100 *
b0011 +
b0011 ,
b1100 /
b1100 1
b00 5
b00 7
0;
0=
0>
0B
0C
0F
0G
0K
0M
0N
0R
0S
0V
0W
b11 [
b11 ]
1a
1c
1d
1h
1i
1l
1m
b0011 $"
b0011 &"
b11 *"
b11 ,"
10"
12"
13"
17"
18"
1;"
1<"
1@"
1B"
1C"
1G"
1H"
1K"
1L"
b00 P"
b00 R"
0V"
0X"
0Y"
0]"
0^"
0a"
0b"
#13000000
b000001101 !
b01101 "
b1101 %
b1101 '
b1101 *
b0010 +
b0010 ,
b1101 /
b1101 1
b01 5
b01 7
1;
1=
1>
1B
1C
1F
1G
b0010 $"
b0010 &"
b10 *"
b10 ,"
00"
02"
03"
07"
08"
0;"
0<"
#14000000
b000001110 !
b01110 "
b1110 %
b1110 '
b1110 *
b0001 +
b0001 ,
b1110 /
b1110 1
b10 5
b10 7
0;
0=
0>
0B
0C
0F
0G
1K
1M
1N
1R
1S
1V
1W
b0001 $"
b0001 &"
b01 *"
b01 ,"
10"
12"
13"
17"
18"
1;"
1<"
0@"
0B"
0C"
0G"
0H"
0K"
0L"
#15000000
b000001111 !
b01111 "
b1111 %
b1111 '
b1111 *
b0000 +
b0000 ,
b1111 /
b1111 1
b11 5
b11 7
1;
1=
1>
1B
1C
1F
1G
b0000 $"
b0000 &"
b00 *"
b00 ,"
00"
02"
03"
07"
08"
0;"
0<"
#16000000
b000010000 !
b00001 "
b0001 $
b0000 %
b0001 '
1)
b0001 *
b0000 +
b1111 ,
b0001 .
b0000 /
b0001 1
b01 4
b00 5
b01 7
1:
0;
1A
0B
0K
0M
0N
0R
0S
0V
0W
b00 [
b00 ]
0a
0c
0d
0h
0i
0l
0m
0q
0s
0t
0x
0y
0|
0}
b0001 #"
b1111 $"
1%"
b0000 &"
1'"
b01 )"
b11 *"
1+"
b00 ,"
1-"
1/"
10"
11"
02"
03"
14"
16"
17"
08"
19"
0;"
0<"
1>"
1@"
1A"
0B"
1C"
1E"
1G"
1H"
1J"
1K"
0L"
1M"
1N"
b11 P"
1Q"
b00 R"
1S"
1T"
1V"
1W"
0X"
1Y"
1["
1]"
1^"
1`"
1a"
0b"
1c"
1d"
1f"
1g"
0h"
1i"
1k"
1m"
1n"
1p"
1q"
0r"
1s"
#17000000
b000010001 !
b00010 "
b0001 %
b0010 '
0)
b0010 *
b1111 +
b1110 ,
b0001 /
b0010 1
b01 5
b10 7
18
1;
1<
0=
0>
1?
1B
0C
1D
0F
0G
1I
1M
1U
1W
b1110 $"
0%"
b1111 &"
0'"
b10 *"
0+"
b11 ,"
0-"
00"
01"
12"
13"
04"
07"
18"
09"
1;"
1<"
0>"
0A"
1B"
0E"
0J"
1L"
0M"
0N"
0Q"
b11 R"
0S"
0T"
0W"
1X"
0["
0`"
1b"
0c"
0d"
0g"
1h"
0k"
0p"
1r"
0s"
#18000000
b000010010 !
b00011 "
b0010 %
b0011 '
b0011 *
b1110 +
b1101 ,
b0010 /
b0011 1
02
b10 5
06
b11 7
08
0;
0<
1=
1>
0?
0B
1C
0D
1F
1G
0I
1K
0L
1M
1N
0P
1R
1S
0U
1V
1W
0X
0Y
b00 ]
0_
0c
0k
0m
b1101 $"
b1110 &"
b01 *"
b10 ,"
1-"
10"
11"
02"
03"
14"
17"
08"
19"
0;"
0<"
1>"
0@"
1B"
0C"
0G"
0H"
1J"
0K"
1L"
#19000000
b000010011 !
b00100 "
b0011 %
b0100 '
b0100 *
b1101 +
b1100 ,
b0011 /
b0100 1
12
b11 5
16
b00 7
18
1;
1<
0=
0>
1?
1B
0C
1D
0F
0G
1I
1L
0M
1P
1U
0W
1X
1Y
b01 ]
1_
1c
1k
1m
b1100 $"
b1101 &"
b00 *"
b01 ,"
0-"
00"
01"
12"
13"
04"
07"
18"
09"
1;"
1<"
0>"
0B"
0J"
0L"
#20000000
b000010100 !
b00101 "
b0100 %
b0101 '
b0101 *
b1100 +
b1011 ,
b0100 /
b0101 1
02
b00 5
06
b01 7
08
0;
0<
1=
1>
0?
0B
1C
0D
1F
1G
0I
0K
0L
0M
0N
0P
0R
0S
0U
0V
0W
0X
0Y
b01 [
b01 ]
0^
0_
1a
0b
1c
1d
0f
1h
1i
0k
1l
1m
0n
0o
0s
0{
0}
b1011 $"
b1100 &"
1'"
b11 *"
1+"
b00 ,"
1-"
10"
11"
02"
03"
14"
17"
08"
19"
0;"
0<"
1>"
1@"
1A"
0B"
1C"
1E"
1G"
1H"
1J"
1K"
0L"
1M"
1N"
b10 P"
b11 R"
1T"
0V"
1X"
0Y"
0]"
0^"
1`"
0a"
1b"
#21000000
b000010101 !
b00110 "
b0101 %
b0110 '
b0110 *
b1011 +
b1010 ,
b0101 /
b0110 1
b01 5
b10 7
18
1;
1<
0=
0>
1?
1B
0C
1D
0F
0G
1I
1M
1U
1W
b1010 $"
b1011 &"
0'"
b10 *"
0+"
b11 ,"
0-"
00"
01"
12"
13"
04"
07"
18"
09"
1;"
1<"
0>"
0A"
1B"
0E"
0J"
1L"
0M"
0N"
b10 R"
0T"
0X"
0`"
0b"
#22000000
b000010110 !
b00111 "
b0110 %
b0111 '
b0111 *
b1010 +
b1001 ,
b0110 /
b0111 1
02
b10 5
06
b11 7
08
0;
0<
1=
1>
0?
0B
1C
0D
1F
1G
0I
1K
0L
1M
1N
0P
1R
1S
0U
1V
1W
0X
0Y
b01 ]
0^
0_
0b
1c
0f
0k
1m
0n
0o
0s
0{
0}
b1001 $"
b1010 &"
b01 *"
b10 ,"
1-"
10"
11"
02"
03"
14"
17"
08"
19"
0;"
0<"
1>"
0@"
1B"
0C"
0G"
0H"
1J"
0K"
1L"
#23000000
b000010111 !
b01000 "
b0111 %
b1000 '
b1000 *
b1001 +
b1000 ,
b0111 /
b1000 1
12
b11 5
16
b00 7
18
1;
1<
0=
0>
1?
1B
0C
1D
0F
0G
1I
1L
0M
1P
1U
0W
1X
1Y
b10 ]
1^
1_
1b
0c
1f
1k
0m
1n
1o
1s
1{
1}
b1000 $"
b1001 &"
b00 *"
b01 ,"
0-"
00"
01"
12"
13"
04"
07"
18"
09"
1;"
1<"
0>"
0B"
0J"
0L"
#24000000
b000011000 !
b01001 "
b1000 %
0&
b1001 '
0(
b1001 *
b1000 +
b0111 ,
b1000 /
00
b1001 1
02
b00 5
06
b01 7
08
0;
0<
1=
1>
0?
0B
1C
0D
1F
1G
0I
0K
0L
0M
0N
0P
0R
0S
0U
0V
0W
0X
0Y
b10 [
0\
b10 ]
0^
0_
0a
0b
0c
0d
0f
0h
0i
0k
0l
0m
0n
0o
1q
0r
1s
1t
0v
1x
1y
0{
1|
1}
0!"
b0111 $"
b1000 &"
1'"
b11 *"
1+"
b00 ,"
1-"
10"
11"
02"
03"
14"
17"
08"
19"
0;"
0<"
1>"
1@"
1A"
0B"
1C"
1E"
1G"
1H"
1J"
1K"
0L"
1M"
1N"
b01 P"
b10 R"
1S"
1T"
1V"
1W"
0X"
1Y"
1["
1]"
1^"
1`"
1a"
0b"
1c"
1d"
0f"
1h"
0i"
0m"
0n"
1p"
0q"
1r"
#25000000
b000011001 !
b01010 "
b1001 %
b1010 '
b1010 *
b0111 +
b0110 ,
b1001 /
b1010 1
b01 5
b10 7
18
1;
1<
0=
0>
1?
1B
0C
1D
0F
0G
1I
1M
1U
1W
b0110 $"
b0111 &"
0'"
b10 *"
0+"
b11 ,"
0-"
00"
01"
12"
13"
04"
07"
18"
09"
1;"
1<"
0>"
0A"
1B"
0E"
0J"
1L"
0M"
0N"
b01 R"
0S"
0T"
0W"
1X"
0["
0`"
1b"
0c"
0d"
0h"
0p"
0r"
#26000000
b000011010 !
b01011 "
b1010 %
b1011 '
b1011 *
b0110 +
b0101 ,
b1010 /
b1011 1
02
b10 5
06
b11 7
08
0;
0<
1=
1>
0?
0B
1C
0D
1F
1G
0I
1K
0L
1M
1N
0P
1R
1S
0U
1V
1W
0X
0Y
b10 ]
0_
0c
0k
0m
b0101 $"
b0110 &"
b01 *"
b10 ,"
1-"
10"
11"
02"
03"
14"
17"
08"
19"
0;"
0<"
1>"
0@"
1B"
0C"
0G"
0H"
1J"
0K"
1L"
#27000000
b000011011 !
b01100 "
b1011 %
b1100 '
b1100 *
b0101 +
b0100 ,
b1011 /
b1100 1
12
b11 5
16
b00 7
18
1;
1<
0=
0>
1?
1B
0C
1D
0F
0G
1I
1L
0M
1P
1U
0W
1X
1Y
b11 ]
1_
1c
1k
1m
b0100 $"
b0101 &"
b00 *"
b01 ,"
0-"
00"
01"
12"
13"
04"
07"
18"
09"
1;"
1<"
0>"
0B"
0J"
0L"
#28000000
b000011100 !
b01101 "
b1100 %
0&
b1101 '
0(
b1101 *
b0100 +
b0011 ,
b1100 /
00
b1101 1
02
b00 5
06
b01 7
08
0;
0<
1=
1>
0?
0B
1C
0D
1F
1G
0I
0K
0L
0M
0N
0P
0R
0S
0U
0V
0W
0X
0Y
b11 [
0\
b11 ]
0^
0_
1a
0b
1c
1d
0f
1h
1i
0k
1l
1m
0n
0o
0r
1s
0v
0{
1}
0!"
b0011 $"
b0100 &"
1'"
b11 *"
1+"
b00 ,"
1-"
10"
11"
02"
03"
14"
17"
08"
19"
0;"
0<"
1>"
1@"
1A"
0B"
1C"
1E"
1G"
1H"
1J"
1K"
0L"
1M"
1N"
b00 P"
b01 R"
1T"
0V"
1X"
0Y"
0]"
0^"
1`"
0a"
1b"
#29000000
b000011101 !
b01110 "
b1101 %
b1110 '
b1110 *
b0011 +
b0010 ,
b1101 /
b1110 1
b01 5
b10 7
18
1;
1<
0=
0>
1?
1B
0C
1D
0F
0G
1I
1M
1U
1W
b0010 $"
b0011 &"
0'"
b10 *"
0+"
b11 ,"
0-"
00"
01"
12"
13"
04"
07"
18"
09"
1;"
1<"
0>"
0A"
1B"
0E"
0J"
1L"
0M"
0N"
b00 R"
0T"
0X"
0`"
0b"
#30000000
b000011110 !
b01111 "
b1110 %
0&
b1111 '
0(
b1111 *
b0010 +
b0001 ,
b1110 /
00
b1111 1
02
b10 5
06
b11 7
08
0;
0<
1=
1>
0?
0B
1C
0D
1F
1G
0I
1K
0L
1M
1N
0P
1R
1S
0U
1V
1W
0X
0Y
0\
b11 ]
0^
0_
0b
1c
0f
0k
1m
0n
0o
0r
1s
0v
0{
1}
0!"
b0001 $"
b0010 &"
b01 *"
b10 ,"
1-"
10"
11"
02"
03"
14"
17"
08"
19"
0;"
0<"
1>"
0@"
1B"
0C"
0G"
0H"
1J"
0K"
1L"
#31000000
b000011111 !
b10000 "
b1111 %
1&
b0000 '
1(
b0000 *
b0001 +
b0000 ,
b1111 /
10
b0000 1
12
b11 5
16
b00 7
18
1;
1<
0=
0>
1?
1B
0C
1D
0F
0G
1I
1L
0M
1P
1U
0W
1X
1Y
1\
b00 ]
1^
1_
1b
0c
1f
1k
0m
1n
1o
1r
0s
1v
1{
0}
1!"
b0000 $"
b0001 &"
b00 *"
b01 ,"
0-"
00"
01"
12"
13"
04"
07"
18"
09"
1;"
1<"
0>"
0B"
0J"
0L"
