VHDL Files/src/counters/t_ff.vhd
-- VHDL 8 bit processor project
-- T Flip Flop
-- James Hicks November 11 2023

library ieee;
use ieee.std_logic_1164.all;

entity t_ff is
    Port ( t   : in STD_LOGIC;
           en  : in STD_LOGIC;
           rst : in STD_LOGIC;
           clk : in STD_LOGIC;
           q   : out STD_LOGIC);
end t_ff;

-- two segment architecture
architecture two_seg_arch of t_ff is

signal q_pres, q_next : std_logic;

begin

  t_ff_process: process( clk, rst ) -- en is not in list
  begin
      if (rst = '1') then
          q_pres <= '0';
      elsif (clk'event and clk='1') then
        if(en = '1') then
          q_pres <= q_next;
        end if;
      end if;
  end process;

  -- next state logic
  q_next <= (t xor q_pres) when en='1' else
            (q_pres and (not en));

 -- output logic
  q <= q_pres;

end two_seg_arch;

VHDL Files/src/counters/3bit_alt.vhd
--TODO::FILE JUST FOR TESTING DELETE
--TODO::TESTINGIF DEBOUNCE IS THE ISSUE

library ieee;
use ieee.std_logic_1164.all;

entity threebitcounter_alt is
  port ( clk : in  std_logic;
         rst : in  std_logic;
         cnt : out std_logic_vector(2 downto 0)
         );
end threebitcounter_alt;

architecture my_arch of threebitcounter_alt is

signal q0_int, q1_int, q2_int : std_logic;

begin

  q2_int <= q0_int and q1_int;

  ff_1 : entity work.t_ff(two_seg_arch)
    port map ( t   => '1',
               en  => '1',
               rst => rst,
               clk => clk,
               q   => q0_int
             );

  ff_2 : entity work.t_ff(two_seg_arch)
    port map ( t   => q0_int,
               en  => '1',
               rst => rst,
               clk => clk,
               q   => q1_int);

  ff_3 : entity work.t_ff(two_seg_arch)
    port map (t    => q2_int,
              en   => '1',
              rst  => rst,
              clk  => clk,
              q    => cnt(2)
              );

  cnt(1) <= q1_int;
  cnt(0) <= q0_int;

end my_arch;

VHDL Files/src/counters/alt_tb.vhd
-- VHDL 8 bit processor project
-- 3 bit counter test bench
-- James Hicks November 11 2023

library ieee;
use ieee.std_logic_1164.all;

entity tb_alt is
end tb_alt;

architecture tb_arch of tb_alt is

  signal clk, btn, rst : std_logic := '0';
  signal cnt           : std_logic_vector(2 downto 0);
  constant clk_period  : time := 10 ns;

begin

  threebitcounter_alt : entity work.threebitcounter_alt
    port map( clk => clk,
              rst => rst,
              cnt => cnt
            );

  clk_process : process
  begin
    loop
      wait for clk_period / 2;
      clk <= not clk;
    end loop;
  end process;

  rst_process : process
  begin
    rst <= '1';
    wait until rising_edge(clk);
    rst <= '0';
    wait;
  end process;

  termination_process : process
  begin
    wait for 200000 ns;
    assert false report "end of test" severity failure;
  end process;

end tb_arch;

VHDL Files/src/counters/alt_sim.vcd
$date
  Sat Nov 11 19:13:05 2023
$end
$version
  GHDL v0
$end
$timescale
  1 fs
$end
$scope module standard $end
$upscope $end
$scope module std_logic_1164 $end
$upscope $end
$scope module tb_alt $end
$var reg 1 ! clk $end
$var reg 1 " btn $end
$var reg 1 # rst $end
$var reg 3 $ cnt[2:0] $end
$scope module threebitcounter_alt $end
$var reg 1 % clk $end
$var reg 1 & rst $end
$var reg 3 ' cnt[2:0] $end
$var reg 1 ( q0_int $end
$var reg 1 ) q1_int $end
$var reg 1 * q2_int $end
$scope module ff_1 $end
$var reg 1 + t $end
$var reg 1 , en $end
$var reg 1 - rst $end
$var reg 1 . clk $end
$var reg 1 / q $end
$var reg 1 0 q_pres $end
$var reg 1 1 q_next $end
$upscope $end
$scope module ff_2 $end
$var reg 1 2 t $end
$var reg 1 3 en $end
$var reg 1 4 rst $end
$var reg 1 5 clk $end
$var reg 1 6 q $end
$var reg 1 7 q_pres $end
$var reg 1 8 q_next $end
$upscope $end
$scope module ff_3 $end
$var reg 1 9 t $end
$var reg 1 : en $end
$var reg 1 ; rst $end
$var reg 1 < clk $end
$var reg 1 = q $end
$var reg 1 > q_pres $end
$var reg 1 ? q_next $end
$upscope $end
$upscope $end
$upscope $end
$enddefinitions $end
#0
0!
0"
1#
b000 $
0%
1&
b000 '
0(
0)
0*
1+
1,
1-
0.
0/
00
11
02
13
14
05
06
07
08
09
1:
1;
0<
0=
0>
0?
#5000000
1!
0#
1%
0&
0-
1.
04
15
0;
1<
#10000000
0!
0%
0.
05
0<
#15000000
1!
b001 $
1%
b001 '
1(
1.
1/
10
01
12
15
18
1<
#20000000
0!
0%
0.
05
0<
#25000000
1!
b010 $
1%
b010 '
0(
1)
1.
0/
00
11
02
15
16
17
18
1<
#30000000
0!
0%
0.
05
0<
#35000000
1!
b011 $
1%
b011 '
1(
1*
1.
1/
10
01
12
15
08
19
1<
1?
#40000000
0!
0%
0.
05
0<
#45000000
1!
b100 $
1%
b100 '
0(
0)
0*
1.
0/
00
11
02
15
06
07
08
09
1<
1=
1>
1?
#50000000
0!
0%
0.
05
0<
#55000000
1!
b101 $
1%
b101 '
1(
1.
1/
10
01
12
15
18
1<
#60000000
0!
0%
0.
05
0<
#65000000
1!
b110 $
1%
b110 '
0(
1)
1.
0/
00
11
02
15
16
17
18
1<
#70000000
0!
0%
0.
05
0<
#75000000
1!
b111 $
1%
b111 '
1(
1*
1.
1/
10
01
12
15
08
19
1<
0?
#80000000
0!
0%
0.
05
0<
#85000000
1!
b000 $
1%
b000 '
0(
0)
0*
1.
0/
00
11
02
15
06
07
08
09
1<
0=
0>
0?
#90000000
0!
0%
0.
05
0<
#95000000
1!
b001 $
1%
b001 '
1(
1.
1/
10
01
12
15
18
1<
#100000000
0!
0%
0.
05
0<
#105000000
1!
b010 $
1%
b010 '
0(
1)
1.
0/
00
11
02
15
16
17
18
1<
#110000000
0!
0%
0.
05
0<
#115000000
1!
b011 $
1%
b011 '
1(
1*
1.
1/
10
01
12
15
08
19
1<
1?
#120000000
0!
0%
0.
05
0<
#125000000
1!
b100 $
1%
b100 '
0(
0)
0*
1.
0/
00
11
02
15
06
07
08
09
1<
1=
1>
1?
#130000000
0!
0%
0.
05
0<
#135000000
1!
b101 $
1%
b101 '
1(
1.
1/
10
01
12
15
18
1<
#140000000
0!
0%
0.
05
0<
#145000000
1!
b110 $
1%
b110 '
0(
1)
1.
0/
00
11
02
15
16
17
18
1<
#150000000
0!
0%
0.
05
0<
#155000000
1!
b111 $
1%
b111 '
1(
1*
1.
1/
10
01
12
15
08
19
1<
0?
#160000000
0!
0%
0.
05
0<
#165000000
1!
b000 $
1%
b000 '
0(
0)
0*
1.
0/
00
11
02
15
06
07
08
09
1<
0=
0>
0?
#170000000
0!
0%
0.
05
0<
#175000000
1!
b001 $
1%
b001 '
1(
1.
1/
10
01
12
15
18
1<
#180000000
0!
0%
0.
05
0<
#185000000
1!
b010 $
1%
b010 '
0(
1)
1.
0/
00
11
02
15
16
17
18
1<
#190000000
0!
0%
0.
05
0<
#195000000
1!
b011 $
1%
b011 '
1(
1*
1.
1/
10
01
12
15
08
19
1<
1?
#200000000
0!
0%
0.
05
0<
#205000000
1!
b100 $
1%
b100 '
0(
0)
0*
1.
0/
00
11
02
15
06
07
08
09
1<
1=
1>
1?
#210000000
0!
0%
0.
05
0<
#215000000
1!
b101 $
1%
b101 '
1(
1.
1/
10
01
12
15
18
1<
#220000000
0!
0%
0.
05
0<
#225000000
1!
b110 $
1%
b110 '
0(
1)
1.
0/
00
11
02
15
16
17
18
1<
#230000000
0!
0%
0.
05
0<
#235000000
1!
b111 $
1%
b111 '
1(
1*
1.
1/
10
01
12
15
08
19
1<
0?
#240000000
0!
0%
0.
05
0<
#245000000
1!
b000 $
1%
b000 '
0(
0)
0*
1.
0/
00
11
02
15
06
07
08
09
1<
0=
0>
0?
#250000000
0!
0%
0.
05
0<
#255000000
1!
b001 $
1%
b001 '
1(
1.
1/
10
01
12
15
18
1<
#260000000
0!
0%
0.
05
0<
#265000000
1!
b010 $
1%
b010 '
0(
1)
1.
0/
00
11
02
15
16
17
18
1<
#270000000
0!
0%
0.
05
0<
#275000000
1!
b011 $
1%
b011 '
1(
1*
1.
1/
10
01
12
15
08
19
1<
1?
#280000000
0!
0%
0.
05
0<
#285000000
1!
b100 $
1%
b100 '
0(
0)
0*
1.
0/
00
11
02
15
06
07
08
09
1<
1=
1>
1?
#290000000
0!
0%
0.
05
0<
#295000000
1!
b101 $
1%
b101 '
1(
1.
1/
10
01
12
15
18
1<
#300000000
0!
0%
0.
05
0<
#305000000
1!
b110 $
1%
b110 '
0(
1)
1.
0/
00
11
02
15
16
17
18
1<
#310000000
0!
0%
0.
05
0<
#315000000
1!
b111 $
1%
b111 '
1(
1*
1.
1/
10
01
12
15
08
19
1<
0?
#320000000
0!
0%
0.
05
0<
#325000000
1!
b000 $
1%
b000 '
0(
0)
0*
1.
0/
00
11
02
15
06
07
08
09
1<
0=
0>
0?
#330000000
0!
0%
0.
05
0<
#335000000
1!
b001 $
1%
b001 '
1(
1.
1/
10
01
12
15
18
1<
#340000000
0!
0%
0.
05
0<
#345000000
1!
b010 $
1%
b010 '
0(
1)
1.
0/
00
11
02
15
16
17
18
1<
#350000000
0!
0%
0.
05
0<
#355000000
1!
b011 $
1%
b011 '
1(
1*
1.
1/
10
01
12
15
08
19
1<
1?
#360000000
0!
0%
0.
05
0<
#365000000
1!
b100 $
1%
b100 '
0(
0)
0*
1.
0/
00
11
02
15
06
07
08
09
1<
1=
1>
1?
#370000000
0!
0%
0.
05
0<
#375000000
1!
b101 $
1%
b101 '
1(
1.
1/
10
01
12
15
18
1<
#380000000
0!
0%
0.
05
0<
#385000000
1!
b110 $
1%
b110 '
0(
1)
1.
0/
00
11
02
15
16
17
18
1<
#390000000
0!
0%
0.
05
0<
#395000000
1!
b111 $
1%
b111 '
1(
1*
1.
1/
10
01
12
15
08
19
1<
0?
#400000000
0!
0%
0.
05
0<
#405000000
1!
b000 $
1%
b000 '
0(
0)
0*
1.
0/
00
11
02
15
06
07
08
09
1<
0=
0>
0?
#410000000
0!
0%
0.
05
0<
#415000000
1!
b001 $
1%
b001 '
1(
1.
1/
10
01
12
15
18
1<
#420000000
0!
0%
0.
05
0<
#425000000
1!
b010 $
1%
b010 '
0(
1)
1.
0/
00
11
02
15
16
17
18
1<
#430000000
0!
0%
0.
05
0<
#435000000
1!
b011 $
1%
b011 '
1(
1*
1.
1/
10
01
12
15
08
19
1<
1?
#440000000
0!
0%
0.
05
0<
#445000000
1!
b100 $
1%
b100 '
0(
0)
0*
1.
0/
00
11
02
15
06
07
08
09
1<
1=
1>
1?
#450000000
0!
0%
0.
05
0<
#455000000
1!
b101 $
1%
b101 '
1(
1.
1/
10
01
12
15
18
1<
#460000000
0!
0%
0.
05
0<
#465000000
1!
b110 $
1%
b110 '
0(
1)
1.
0/
00
11
02
15
16
17
18
1<
#470000000
0!
0%
0.
05
0<
#475000000
1!
b111 $
1%
b111 '
1(
1*
1.
1/
10
01
12
15
08
19
1<
0?
#480000000
0!
0%
0.
05
0<
#485000000
1!
b000 $
1%
b000 '
0(
0)
0*
1.
0/
00
11
02
15
06
07
08
09
1<
0=
0>
0?
#490000000
0!
0%
0.
05
0<
#495000000
1!
b001 $
1%
b001 '
1(
1.
1/
10
01
12
15
18
1<
#500000000
0!
0%
0.
05
0<
#505000000
1!
b010 $
1%
b010 '
0(
1)
1.
0/
00
11
02
15
16
17
18
1<
#510000000
0!
0%
0.
05
0<
#515000000
1!
b011 $
1%
b011 '
1(
1*
1.
1/
10
01
12
15
08
19
1<
1?
#520000000
0!
0%
0.
05
0<
#525000000
1!
b100 $
1%
b100 '
0(
0)
0*
1.
0/
00
11
02
15
06
07
08
09
1<
1=
1>
1?
#530000000
0!
0%
0.
05
0<
#535000000
1!
b101 $
1%
b101 '
1(
1.
1/
10
01
12
15
18
1<
#540000000
0!
0%
0.
05
0<
#545000000
1!
b110 $
1%
b110 '
0(
1)
1.
0/
00
11
02
15
16
17
18
1<
#550000000
0!
0%
0.
05
0<
#555000000
1!
b111 $
1%
b111 '
1(
1*
1.
1/
10
01
12
15
08
19
1<
0?
#560000000
0!
0%
0.
05
0<
#565000000
1!
b000 $
1%
b000 '
0(
0)
0*
1.
0/
00
11
02
15
06
07
08
09
1<
0=
0>
0?
#570000000
0!
0%
0.
05
0<
#575000000
1!
b001 $
1%
b001 '
1(
1.
1/
10
01
12
15
18
1<
#580000000
0!
0%
0.
05
0<
#585000000
1!
b010 $
1%
b010 '
0(
1)
1.
0/
00
11
02
15
16
17
18
1<
#590000000
0!
0%
0.
05
0<
#595000000
1!
b011 $
1%
b011 '
1(
1*
1.
1/
10
01
12
15
08
19
1<
1?
#600000000
0!
0%
0.
05
0<
#605000000
1!
b100 $
1%
b100 '
0(
0)
0*
1.
0/
00
11
02
15
06
07
08
09
1<
1=
1>
1?
#610000000
0!
0%
0.
05
0<
#615000000
1!
b101 $
1%
b101 '
1(
1.
1/
10
01
12
15
18
1<
#620000000
0!
0%
0.
05
0<
#625000000
1!
b110 $
1%
b110 '
0(
1)
1.
0/
00
11
02
15
16
17
18
1<
#630000000
0!
0%
0.
05
0<
#635000000
1!
b111 $
1%
b111 '
1(
1*
1.
1/
10
01
12
15
08
19
1<
0?
#640000000
0!
0%
0.
05
0<
#645000000
1!
b000 $
1%
b000 '
0(
0)
0*
1.
0/
00
11
02
15
06
07
08
09
1<
0=
0>
0?
#650000000
0!
0%
0.
05
0<
#655000000
1!
b001 $
1%
b001 '
1(
1.
1/
10
01
12
15
18
1<
#660000000
0!
0%
0.
05
0<
#665000000
1!
b010 $
1%
b010 '
0(
1)
1.
0/
00
11
02
15
16
17
18
1<
#670000000
0!
0%
0.
05
0<
#675000000
1!
b011 $
1%
b011 '
1(
1*
1.
1/
10
01
12
15
08
19
1<
1?
#680000000
0!
0%
0.
05
0<
#685000000
1!
b100 $
1%
b100 '
0(
0)
0*
1.
0/
00
11
02
15
06
07
08
09
1<
1=
1>
1?
#690000000
0!
0%
0.
05
0<
#695000000
1!
b101 $
1%
b101 '
1(
1.
1/
10
01
12
15
18
1<
#700000000
0!
0%
0.
05
0<
#705000000
1!
b110 $
1%
b110 '
0(
1)
1.
0/
00
11
02
15
16
17
18
1<
#710000000
0!
0%
0.
05
0<
#715000000
1!
b111 $
1%
b111 '
1(
1*
1.
1/
10
01
12
15
08
19
1<
0?
#720000000
0!
0%
0.
05
0<
#725000000
1!
b000 $
1%
b000 '
0(
0)
0*
1.
0/
00
11
02
15
06
07
08
09
1<
0=
0>
0?
#730000000
0!
0%
0.
05
0<
#735000000
1!
b001 $
1%
b001 '
1(
1.
1/
10
01
12
15
18
1<
#740000000
0!
0%
0.
05
0<
#745000000
1!
b010 $
1%
b010 '
0(
1)
1.
0/
00
11
02
15
16
17
18
1<
#750000000
0!
0%
0.
05
0<
#755000000
1!
b011 $
1%
b011 '
1(
1*
1.
1/
10
01
12
15
08
19
1<
1?
#760000000
0!
0%
0.
05
0<
#765000000
1!
b100 $
1%
b100 '
0(
0)
0*
1.
0/
00
11
02
15
06
07
08
09
1<
1=
1>
1?
#770000000
0!
0%
0.
05
0<
#775000000
1!
b101 $
1%
b101 '
1(
1.
1/
10
01
12
15
18
1<
#780000000
0!
0%
0.
05
0<
#785000000
1!
b110 $
1%
b110 '
0(
1)
1.
0/
00
11
02
15
16
17
18
1<
#790000000
0!
0%
0.
05
0<
#795000000
1!
b111 $
1%
b111 '
1(
1*
1.
1/
10
01
12
15
08
19
1<
0?
#800000000
0!
0%
0.
05
0<
#805000000
1!
b000 $
1%
b000 '
0(
0)
0*
1.
0/
00
11
02
15
06
07
08
09
1<
0=
0>
0?
#810000000
0!
0%
0.
05
0<
#815000000
1!
b001 $
1%
b001 '
1(
1.
1/
10
01
12
15
18
1<
#820000000
0!
0%
0.
05
0<
#825000000
1!
b010 $
1%
b010 '
0(
1)
1.
0/
00
11
02
15
16
17
18
1<
#830000000
0!
0%
0.
05
0<
#835000000
1!
b011 $
1%
b011 '
1(
1*
1.
1/
10
01
12
15
08
19
1<
1?
#840000000
0!
0%
0.
05
0<
#845000000
1!
b100 $
1%
b100 '
0(
0)
0*
1.
0/
00
11
02
15
06
07
08
09
1<
1=
1>
1?
#850000000
0!
0%
0.
05
0<
#855000000
1!
b101 $
1%
b101 '
1(
1.
1/
10
01
12
15
18
1<
#860000000
0!
0%
0.
05
0<
#865000000
1!
b110 $
1%
b110 '
0(
1)
1.
0/
00
11
02
15
16
17
18
1<
#870000000
0!
0%
0.
05
0<
#875000000
1!
b111 $
1%
b111 '
1(
1*
1.
1/
10
01
12
15
08
19
1<
0?
#880000000
0!
0%
0.
05
0<
#885000000
1!
b000 $
1%
b000 '
0(
0)
0*
1.
0/
00
11
02
15
06
07
08
09
1<
0=
0>
0?
#890000000
0!
0%
0.
05
0<
#895000000
1!
b001 $
1%
b001 '
1(
1.
1/
10
01
12
15
18
1<
#900000000
0!
0%
0.
05
0<
#905000000
1!
b010 $
1%
b010 '
0(
1)
1.
0/
00
11
02
15
16
17
18
1<
#910000000
0!
0%
0.
05
0<
#915000000
1!
b011 $
1%
b011 '
1(
1*
1.
1/
10
01
12
15
08
19
1<
1?
#920000000
0!
0%
0.
05
0<
#925000000
1!
b100 $
1%
b100 '
0(
0)
0*
1.
0/
00
11
02
15
06
07
08
09
1<
1=
1>
1?
#930000000
0!
0%
0.
05
0<
#935000000
1!
b101 $
1%
b101 '
1(
1.
1/
10
01
12
15
18
1<
#940000000
0!
0%
0.
05
0<
#945000000
1!
b110 $
1%
b110 '
0(
1)
1.
0/
00
11
02
15
16
17
18
1<
#950000000
0!
0%
0.
05
0<
#955000000
1!
b111 $
1%
b111 '
1(
1*
1.
1/
10
01
12
15
08
19
1<
0?
#960000000
0!
0%
0.
05
0<
#965000000
1!
b000 $
1%
b000 '
0(
0)
0*
1.
0/
00
11
02
15
06
07
08
09
1<
0=
0>
0?
#970000000
0!
0%
0.
05
0<
#975000000
1!
b001 $
1%
b001 '
1(
1.
1/
10
01
12
15
18
1<
#980000000
0!
0%
0.
05
0<
#985000000
1!
b010 $
1%
b010 '
0(
1)
1.
0/
00
11
02
15
16
17
18
1<
#990000000
0!
0%
0.
05
0<
#995000000
1!
b011 $
1%
b011 '
1(
1*
1.
1/
10
01
12
15
08
19
1<
1?
#1000000000
0!
0%
0.
05
0<
#1005000000
1!
b100 $
1%
b100 '
0(
0)
0*
1.
0/
00
11
02
15
06
07
08
09
1<
1=
1>
1?
#1010000000
0!
0%
0.
05
0<
#1015000000
1!
b101 $
1%
b101 '
1(
1.
1/
10
01
12
15
18
1<
#1020000000
0!
0%
0.
05
0<
#1025000000
1!
b110 $
1%
b110 '
0(
1)
1.
0/
00
11
02
15
16
17
18
1<
#1030000000
0!
0%
0.
05
0<
#1035000000
1!
b111 $
1%
b111 '
1(
1*
1.
1/
10
01
12
15
08
19
1<
0?
#1040000000
0!
0%
0.
05
0<
#1045000000
1!
b000 $
1%
b000 '
0(
0)
0*
1.
0/
00
11
02
15
06
07
08
09
1<
0=
0>
0?
#1050000000
0!
0%
0.
05
0<
#1055000000
1!
b001 $
1%
b001 '
1(
1.
1/
10
01
12
15
18
1<
#1060000000
0!
0%
0.
05
0<
#1065000000
1!
b010 $
1%
b010 '
0(
1)
1.
0/
00
11
02
15
16
17
18
1<
#1070000000
0!
0%
0.
05
0<
#1075000000
1!
b011 $
1%
b011 '
1(
1*
1.
1/
10
01
12
15
08
19
1<
1?
#1080000000
0!
0%
0.
05
0<
#1085000000
1!
b100 $
1%
b100 '
0(
0)
0*
1.
0/
00
11
02
15
06
07
08
09
1<
1=
1>
1?
#1090000000
0!
0%
0.
05
0<
#1095000000
1!
b101 $
1%
b101 '
1(
1.
1/
10
01
12
15
18
1<
#1100000000
0!
0%
0.
05
0<
#1105000000
1!
b110 $
1%
b110 '
0(
1)
1.
0/
00
11
02
15
16
17
18
1<
#1110000000
0!
0%
0.
05
0<
#1115000000
1!
b111 $
1%
b111 '
1(
1*
1.
1/
10
01
12
15
08
19
1<
0?
#1120000000
0!
0%
0.
05
0<
#1125000000
1!
b000 $
1%
b000 '
0(
0)
0*
1.
0/
00
11
02
15
06
07
08
09
1<
0=
0>
0?
#1130000000
0!
0%
0.
05
0<
#1135000000
1!
b001 $
1%
b001 '
1(
1.
1/
10
01
12
15
18
1<
#1140000000
0!
0%
0.
05
0<
#1145000000
1!
b010 $
1%
b010 '
0(
1)
1.
0/
00
11
02
15
16
17
18
1<
#1150000000
0!
0%
0.
05
0<
#1155000000
1!
b011 $
1%
b011 '
1(
1*
1.
1/
10
01
12
15
08
19
1<
1?
#1160000000
0!
0%
0.
05
0<
#1165000000
1!
b100 $
1%
b100 '
0(
0)
0*
1.
0/
00
11
02
15
06
07
08
09
1<
1=
1>
1?
#1170000000
0!
0%
0.
05
0<
#1175000000
1!
b101 $
1%
b101 '
1(
1.
1/
10
01
12
15
18
1<
#1180000000
0!
0%
0.
05
0<
#1185000000
1!
b110 $
1%
b110 '
0(
1)
1.
0/
00
11
02
15
16
17
18
1<
#1190000000
0!
0%
0.
05
0<
#1195000000
1!
b111 $
1%
b111 '
1(
1*
1.
1/
10
01
12
15
08
19
1<
0?
#1200000000
0!
0%
0.
05
0<
#1205000000
1!
b000 $
1%
b000 '
0(
0)
0*
1.
0/
00
11
02
15
06
07
08
09
1<
0=
0>
0?
#1210000000
0!
0%
0.
05
0<
#1215000000
1!
b001 $
1%
b001 '
1(
1.
1/
10
01
12
15
18
1<
#1220000000
0!
0%
0.
05
0<
#1225000000
1!
b010 $
1%
b010 '
0(
1)
1.
0/
00
11
02
15
16
17
18
1<
#1230000000
0!
0%
0.
05
0<
#1235000000
1!
b011 $
1%
b011 '
1(
1*
1.
1/
10
01
12
15
08
19
1<
1?
#1240000000
0!
0%
0.
05
0<
#1245000000
1!
b100 $
1%
b100 '
0(
0)
0*
1.
0/
00
11
02
15
06
07
08
09
1<
1=
1>
1?
#1250000000
0!
0%
0.
05
0<
#1255000000
1!
b101 $
1%
b101 '
1(
1.
1/
10
01
12
15
18
1<
#1260000000
0!
0%
0.
05
0<
#1265000000
1!
b110 $
1%
b110 '
0(
1)
1.
0/
00
11
02
15
16
17
18
1<
#1270000000
0!
0%
0.
05
0<
#1275000000
1!
b111 $
1%
b111 '
1(
1*
1.
1/
10
01
12
15
08
19
1<
0?
#1280000000
0!
0%
0.
05
0<
#1285000000
1!
b000 $
1%
b000 '
0(
0)
0*
1.
0/
00
11
02
15
06
07
08
09
1<
0=
0>
0?
#1290000000
0!
0%
0.
05
0<
#1295000000
1!
b001 $
1%
b001 '
1(
1.
1/
10
01
12
15
18
1<
#1300000000
0!
0%
0.
05
0<
#1305000000
1!
b010 $
1%
b010 '
0(
1)
1.
0/
00
11
02
15
16
17
18
1<
#1310000000
0!
0%
0.
05
0<
#1315000000
1!
b011 $
1%
b011 '
1(
1*
1.
1/
10
01
12
15
08
19
1<
1?
#1320000000
0!
0%
0.
05
0<
#1325000000
1!
b100 $
1%
b100 '
0(
0)
0*
1.
0/
00
11
02
15
06
07
08
09
1<
1=
1>
1?
#1330000000
0!
0%
0.
05
0<
#1335000000
1!
b101 $
1%
b101 '
1(
1.
1/
10
01
12
15
18
1<
#1340000000
0!
0%
0.
05
0<
#1345000000
1!
b110 $
1%
b110 '
0(
1)
1.
0/
00
11
02
15
16
17
18
1<
#1350000000
0!
0%
0.
05
0<
#1355000000
1!
b111 $
1%
b111 '
1(
1*
1.
1/
10
01
12
15
08
19
1<
0?
#1360000000
0!
0%
0.
05
0<
#1365000000
1!
b000 $
1%
b000 '
0(
0)
0*
1.
0/
00
11
02
15
06
07
08
09
1<
0=
0>
0?
#1370000000
0!
0%
0.
05
0<
#1375000000
1!
b001 $
1%
b001 '
1(
1.
1/
10
01
12
15
18
1<
#1380000000
0!
0%
0.
05
0<
#1385000000
1!
b010 $
1%
b010 '
0(
1)
1.
0/
00
11
02
15
16
17
18
1<
#1390000000
0!
0%
0.
05
0<
#1395000000
1!
b011 $
1%
b011 '
1(
1*
1.
1/
10
01
12
15
08
19
1<
1?
#1400000000
0!
0%
0.
05
0<
#1405000000
1!
b100 $
1%
b100 '
0(
0)
0*
1.
0/
00
11
02
15
06
07
08
09
1<
1=
1>
1?
#1410000000
0!
0%
0.
05
0<
#1415000000
1!
b101 $
1%
b101 '
1(
1.
1/
10
01
12
15
18
1<
#1420000000
0!
0%
0.
05
0<
#1425000000
1!
b110 $
1%
b110 '
0(
1)
1.
0/
00
11
02
15
16
17
18
1<
#1430000000
0!
0%
0.
05
0<
#1435000000
1!
b111 $
1%
b111 '
1(
1*
1.
1/
10
01
12
15
08
19
1<
0?
#1440000000
0!
0%
0.
05
0<
#1445000000
1!
b000 $
1%
b000 '
0(
0)
0*
1.
0/
00
11
02
15
06
07
08
09
1<
0=
0>
0?
#1450000000
0!
0%
0.
05
0<
#1455000000
1!
b001 $
1%
b001 '
1(
1.
1/
10
01
12
15
18
1<
#1460000000
0!
0%
0.
05
0<
#1465000000
1!
b010 $
1%
b010 '
0(
1)
1.
0/
00
11
02
15
16
17
18
1<
#1470000000
0!
0%
0.
05
0<
#1475000000
1!
b011 $
1%
b011 '
1(
1*
1.
1/
10
01
12
15
08
19
1<
1?
#1480000000
0!
0%
0.
05
0<
#1485000000
1!
b100 $
1%
b100 '
0(
0)
0*
1.
0/
00
11
02
15
06
07
08
09
1<
1=
1>
1?
#1490000000
0!
0%
0.
05
0<
#1495000000
1!
b101 $
1%
b101 '
1(
1.
1/
10
01
12
15
18
1<
#1500000000
0!
0%
0.
05
0<
#1505000000
1!
b110 $
1%
b110 '
0(
1)
1.
0/
00
11
02
15
16
17
18
1<
#1510000000
0!
0%
0.
05
0<
#1515000000
1!
b111 $
1%
b111 '
1(
1*
1.
1/
10
01
12
15
08
19
1<
0?
#1520000000
0!
0%
0.
05
0<
#1525000000
1!
b000 $
1%
b000 '
0(
0)
0*
1.
0/
00
11
02
15
06
07
08
09
1<
0=
0>
0?
#1530000000
0!
0%
0.
05
0<
#1535000000
1!
b001 $
1%
b001 '
1(
1.
1/
10
01
12
15
18
1<
#1540000000
0!
0%
0.
05
0<
#1545000000
1!
b010 $
1%
b010 '
0(
1)
1.
0/
00
11
02
15
16
17
18
1<
#1550000000
0!
0%
0.
05
0<
#1555000000
1!
b011 $
1%
b011 '
1(
1*
1.
1/
10
01
12
15
08
19
1<
1?
#1560000000
0!
0%
0.
05
0<
#1565000000
1!
b100 $
1%
b100 '
0(
0)
0*
1.
0/
00
11
02
15
06
07
08
09
1<
1=
1>
1?
#1570000000
0!
0%
0.
05
0<
#1575000000
1!
b101 $
1%
b101 '
1(
1.
1/
10
01
12
15
18
1<
#1580000000
0!
0%
0.
05
0<
#1585000000
1!
b110 $
1%
b110 '
0(
1)
1.
0/
00
11
02
15
16
17
18
1<
#1590000000
0!
0%
0.
05
0<
#1595000000
1!
b111 $
1%
b111 '
1(
1*
1.
1/
10
01
12
15
08
19
1<
0?
#1600000000
0!
0%
0.
05
0<
#1605000000
1!
b000 $
1%
b000 '
0(
0)
0*
1.
0/
00
11
02
15
06
07
08
09
1<
0=
0>
0?
#1610000000
0!
0%
0.
05
0<
#1615000000
1!
b001 $
1%
b001 '
1(
1.
1/
10
01
12
15
18
1<
#1620000000
0!
0%
0.
05
0<
#1625000000
1!
b010 $
1%
b010 '
0(
1)
1.
0/
00
11
02
15
16
17
18
1<
#1630000000
0!
0%
0.
05
0<
#1635000000
1!
b011 $
1%
b011 '
1(
1*
1.
1/
10
01
12
15
08
19
1<
1?
#1640000000
0!
0%
0.
05
0<
#1645000000
1!
b100 $
1%
b100 '
0(
0)
0*
1.
0/
00
11
02
15
06
07
08
09
1<
1=
1>
1?
#1650000000
0!
0%
0.
05
0<
#1655000000
1!
b101 $
1%
b101 '
1(
1.
1/
10
01
12
15
18
1<
#1660000000
0!
0%
0.
05
0<
#1665000000
1!
b110 $
1%
b110 '
0(
1)
1.
0/
00
11
02
15
16
17
18
1<
#1670000000
0!
0%
0.
05
0<
#1675000000
1!
b111 $
1%
b111 '
1(
1*
1.
1/
10
01
12
15
08
19
1<
0?
#1680000000
0!
0%
0.
05
0<
#1685000000
1!
b000 $
1%
b000 '
0(
0)
0*
1.
0/
00
11
02
15
06
07
08
09
1<
0=
0>
0?
#1690000000
0!
0%
0.
05
0<
#1695000000
1!
b001 $
1%
b001 '
1(
1.
1/
10
01
12
15
18
1<
#1700000000
0!
0%
0.
05
0<
#1705000000
1!
b010 $
1%
b010 '
0(
1)
1.
0/
00
11
02
15
16
17
18
1<
#1710000000
0!
0%
0.
05
0<
#1715000000
1!
b011 $
1%
b011 '
1(
1*
1.
1/
10
01
12
15
08
19
1<
1?
#1720000000
0!
0%
0.
05
0<
#1725000000
1!
b100 $
1%
b100 '
0(
0)
0*
1.
0/
00
11
02
15
06
07
08
09
1<
1=
1>
1?
#1730000000
0!
0%
0.
05
0<
#1735000000
1!
b101 $
1%
b101 '
1(
1.
1/
10
01
12
15
18
1<
#1740000000
0!
0%
0.
05
0<
#1745000000
1!
b110 $
1%
b110 '
0(
1)
1.
0/
00
11
02
15
16
17
18
1<
#1750000000
0!
0%
0.
05
0<
#1755000000
1!
b111 $
1%
b111 '
1(
1*
1.
1/
10
01
12
15
08
19
1<
0?
#1760000000
0!
0%
0.
05
0<
#1765000000
1!
b000 $
1%
b000 '
0(
0)
0*
1.
0/
00
11
02
15
06
07
08
09
1<
0=
0>
0?
#1770000000
0!
0%
0.
05
0<
#1775000000
1!
b001 $
1%
b001 '
1(
1.
1/
10
01
12
15
18
1<
#1780000000
0!
0%
0.
05
0<
#1785000000
1!
b010 $
1%
b010 '
0(
1)
1.
0/
00
11
02
15
16
17
18
1<
#1790000000
0!
0%
0.
05
0<
#1795000000
1!
b011 $
1%
b011 '
1(
1*
1.
1/
10
01
12
15
08
19
1<
1?
#1800000000
0!
0%
0.
05
0<
