VHDL Files/src/counters/t_ff.vhd
-- VHDL 8 bit processor project
-- T Flip Flop
-- James Hicks November 11 2023

library ieee;
use ieee.std_logic_1164.all;

entity t_ff is
    Port ( t   : in STD_LOGIC;
           en  : in STD_LOGIC;
           rst : in STD_LOGIC;
           clk : in STD_LOGIC;
           q   : out STD_LOGIC);
end t_ff;

-- two segment architecture
architecture two_seg_arch of t_ff is

signal q_pres, q_next : std_logic;

begin

  t_ff_process: process( clk, rst ) -- en is not in list
  begin
      if (rst = '1') then
          q_pres <= '0';
      elsif (clk'event and clk='1') then
        if(en = '1') then
          q_pres <= q_next;
        end if;
      end if;
  end process;

  -- next state logic
  q_next <= (t xor q_pres) when en='1' else
            (q_pres and (not en));

 -- output logic
  q <= q_pres;

end two_seg_arch;

VHDL Files/src/counters/debouncer.vhd
-- this code was written by Dr. Esteban Rodriguez-Marek

library IEEE;
use IEEE.STD_LOGIC_1164.ALL;
use IEEE.NUMERIC_STD.ALL;

entity debouncer is
    Generic (MAX_CNT : integer := 1000000; -- 1M 10ns counts is 10ms
             N       : integer := 20);     -- ceil(log2 1000000) = 20             
    Port ( reset : in STD_LOGIC;
           clk   : in STD_LOGIC;
           sw    : in STD_LOGIC;
           db    : out STD_LOGIC);
end debouncer;

architecture scheme1_arch of debouncer is

    -- signals for counter

    signal ctr_reg, ctr_nxt : unsigned (N-1 downto 0);
    signal m_tick : std_logic; -- 10 ms tick
    
    -- define a new enumerated state type 
    type state_type is (zero, wait1_1, wait1_2, wait1_3,
                        one,  wait0_1, wait0_2, wait0_3);
    -- need to define present state and next state signals
    signal state_reg : state_type;
    signal state_nxt : state_type;

begin

    --////////////////////////
    -- counter for 10- ms tick
    --////////////////////////

    -- counter register
    counter_process: process (reset,clk) -- no need for reset, since it is free-running
    begin
        if (reset='1') then
            ctr_reg <= (others => '0');
        elsif ( clk'event and clk='1' ) then
            ctr_reg <= ctr_nxt;
        end if;
    end process;

    -- next state logic
    ctr_nxt <= (others => '0') when (ctr_reg=MAX_CNT-1) else
               ctr_reg + 1;

    -- output tick (one-clock wide, once every 10 ms)
    m_tick <= '1' when (ctr_reg=MAX_CNT-1) else
              '0'; 

    --////////////////////////
    -- Debouncing FSM
    --////////////////////////

    -- state register
    process (clk, reset)
    begin
        if ( reset = '1' ) then
            state_reg <= zero; -- always starts at state zero
        elsif ( clk'event and clk='1' ) then
            state_reg <= state_nxt; 
        end if;
    end process;

    -- next state and output logic (Moore ckt)
    process ( state_reg, sw, m_tick )
    begin
        -- defaults for next state and output
        state_nxt <= state_reg; -- default is to stay in same state
        db <= '0';              -- default is to output zero

        -- go through each one of the 8 states
        case state_reg is
            -- sw is zero and we are debouncing a rising edge
            when zero =>
                if ( sw='1' ) then  -- advance when sw=1
                    state_nxt <= wait1_1;
                end if;
            when wait1_1 =>
                if ( sw='0' ) then -- back to state zero if sw went back to '0'
                    state_nxt <= zero;
                else -- but if still when at m_tick, go to next wait state
                    if (m_tick='1') then
                        state_nxt <= wait1_2;
                     end if;
                end if;
            when wait1_2 =>
                if ( sw='0' ) then -- back to state "zero" if sw went back to '0'
                    state_nxt <= zero;
                else -- but if still '1' when at m_tick, go to next wait state
                    if (m_tick='1') then
                        state_nxt <= wait1_3;
                     end if;
                end if;
            when wait1_3 =>
                if ( sw='0' ) then -- back to state zero if sw went back to '0'
                    state_nxt <= zero;
                else -- but if still '1' when at m_tick, go to state "one" (we are done debouncing rising  edge)
                    if (m_tick='1') then
                        state_nxt <= one;
                     end if;
                end if;
            -- sw is one and we are debouncing a falling edge
            -- In the meantime, since SW is one, output must be '1'
            when one =>
                db <= '1';
                if ( sw='0' ) then  -- advance to first wait state when sw=0
                    state_nxt <= wait0_1;
                end if; 
            when wait0_1 =>
                db <= '1';
                if ( sw='1' ) then -- back to state "one" if sw goes back to '1'
                    state_nxt <= one;
                else -- but if still '0' when at m_tick, go to next wait state
                    if (m_tick='1') then
                        state_nxt <= wait0_2;
                     end if;
                end if;
            when wait0_2 =>
                db <= '1';
                if ( sw='1' ) then -- back to state "one" if sw goes back to '1'
                    state_nxt <= one;
                else -- but if still '0' when at m_tick, go to next wait state
                    if (m_tick='1') then
                        state_nxt <= wait0_3;
                     end if;
                end if;
            when wait0_3 =>
                db <= '1';
                if ( sw='1' ) then -- back to state "one" if sw goes back to '1'
                    state_nxt <= one;
                else -- but if still '0' when at m_tick, go to state 'zero' (we are done debouncing falling edge)
                    if (m_tick='1') then
                        state_nxt <= zero;
                     end if;
                end if;            
            --when others => -- not needed because we put default values
        end case; 
    end process;

end scheme1_arch;

VHDL Files/src/counters/3bit.vhd
library ieee;
use ieee.std_logic_1164.all;

entity threebitcounter is
  port ( clk : in  std_logic;
         btn : in  std_logic;
         rst : in  std_logic;
         cnt : out std_logic_vector(2 downto 0)
         );
end threebitcounter;

architecture my_arch of threebitcounter is

signal q0_int, q1_int, q2_int, btn_db : std_logic;

begin

  debouncer : entity work.debouncer(scheme1_arch)
    port map ( reset => rst,
               clk   => clk,
               sw    => btn,
               db    => btn_db);

  q2_int <= q0_int and q1_int;

  ff_1 : entity work.t_ff(two_seg_arch)
    port map ( t   => '1',
               en  => '1',
               rst => rst,
               clk => btn_db,
               q   => q0_int
             );

  ff_2 : entity work.t_ff(two_seg_arch)
    port map ( t   => q0_int,
               en  => '1',
               rst => rst,
               clk => btn_db,
               q   => q1_int);

  ff_3 : entity work.t_ff(two_seg_arch)
    port map (t    => q2_int,
              en   => '1',
              rst  => rst,
              clk  => btn_db,
              q    => cnt(2)
              );

  cnt(1) <= q1_int;
  cnt(0) <= q0_int;

end my_arch;

VHDL Files/src/counters/3bit_tb.vhd
-- VHDL 8 bit processor project
-- 3 bit counter test bench
-- James Hicks November 11 2023

--TODO::Why isn't the debouncer working?

library ieee;
use ieee.std_logic_1164.all;

entity tb is
end tb;

architecture tb_arch of tb is

  signal clk, btn, rst : std_logic := '0';
  signal cnt           : std_logic_vector(2 downto 0);
  constant clk_period  : time := 10 ns;

begin

  threebitcounter : entity work.threebitcounter(my_arch)
    port map( clk => clk,
              btn => btn,
              rst => rst,
              cnt => cnt
            );

  clk_process : process
  begin
    loop
      wait for clk_period / 2;
      clk <= not clk;
    end loop;
  end process;

  btn_process : process
  begin
    btn <= '1';
    wait for 5 us;  -- Simulate button press for 100 ns
    btn <= '0';
    wait for 100 us;  -- Simulate button release for 100 ns
    wait for 1 ms;    -- Wait for 1 us before repeating
  end process;

  rst_process : process
  begin
    rst <= '1';
    wait until rising_edge(clk);
    rst <= '0';
    wait;
  end process;

  termination_process : process
  begin
    wait for 500 ms;
    assert false report "end of test" severity failure;
  end process;

end tb_arch;

VHDL Files/src/counters/btnhisim.vcd
$date
  Sun Nov 12 10:22:51 2023
$end
$version
  GHDL v0
$end
$timescale
  1 fs
$end
$scope module standard $end
$upscope $end
$scope module std_logic_1164 $end
$upscope $end
$scope module numeric_std $end
$upscope $end
$scope module tb $end
$var reg 1 ! clk $end
$var reg 1 " btn $end
$var reg 1 # rst $end
$var reg 3 $ cnt[2:0] $end
$scope module threebitcounter $end
$var reg 1 % clk $end
$var reg 1 & btn $end
$var reg 1 ' rst $end
$var reg 3 ( cnt[2:0] $end
$var reg 1 ) q0_int $end
$var reg 1 * q1_int $end
$var reg 1 + q2_int $end
$var reg 1 , btn_db $end
$scope module debouncer $end
$var reg 1 - reset $end
$var reg 1 . clk $end
$var reg 1 / sw $end
$var reg 1 0 db $end
$var reg 20 1 ctr_reg[19:0] $end
$var reg 20 2 ctr_nxt[19:0] $end
$var reg 1 3 m_tick $end
$comment state_reg is not handled $end
$comment state_nxt is not handled $end
$upscope $end
$scope module ff_1 $end
$var reg 1 4 t $end
$var reg 1 5 en $end
$var reg 1 6 rst $end
$var reg 1 7 clk $end
$var reg 1 8 q $end
$var reg 1 9 q_pres $end
$var reg 1 : q_next $end
$upscope $end
$scope module ff_2 $end
$var reg 1 ; t $end
$var reg 1 < en $end
$var reg 1 = rst $end
$var reg 1 > clk $end
$var reg 1 ? q $end
$var reg 1 @ q_pres $end
$var reg 1 A q_next $end
$upscope $end
$scope module ff_3 $end
$var reg 1 B t $end
$var reg 1 C en $end
$var reg 1 D rst $end
$var reg 1 E clk $end
$var reg 1 F q $end
$var reg 1 G q_pres $end
$var reg 1 H q_next $end
$upscope $end
$upscope $end
$upscope $end
$enddefinitions $end
#0
0!
1"
1#
b000 $
0%
1&
1'
b000 (
0)
0*
0+
0,
1-
0.
1/
00
b00000000000000000000 1
b00000000000000000001 2
03
14
15
16
07
08
09
1:
0;
1<
1=
0>
0?
0@
0A
0B
1C
1D
0E
0F
0G
0H
#5000000
1!
0#
1%
0'
0-
1.
06
0=
0D
#10000000
0!
0%
0.
#15000000
1!
1%
1.
b00000000000000000001 1
b00000000000000000010 2
#20000000
0!
0%
0.
#25000000
1!
1%
1.
b00000000000000000010 1
b00000000000000000011 2
#30000000
0!
0%
0.
#35000000
1!
1%
1.
b00000000000000000011 1
b00000000000000000100 2
#40000000
0!
0%
0.
#45000000
1!
1%
1.
b00000000000000000100 1
b00000000000000000101 2
#50000000
0!
0%
0.
#55000000
1!
1%
1.
b00000000000000000101 1
b00000000000000000110 2
#60000000
0!
0%
0.
#65000000
1!
1%
1.
b00000000000000000110 1
b00000000000000000111 2
#70000000
0!
0%
0.
#75000000
1!
1%
1.
b00000000000000000111 1
b00000000000000001000 2
#80000000
0!
0%
0.
#85000000
1!
1%
1.
b00000000000000001000 1
b00000000000000001001 2
#90000000
0!
0%
0.
#95000000
1!
1%
1.
b00000000000000001001 1
b00000000000000001010 2
#100000000
0!
0%
0.
#105000000
1!
1%
1.
b00000000000000001010 1
b00000000000000001011 2
#110000000
0!
0%
0.
#115000000
1!
1%
1.
b00000000000000001011 1
b00000000000000001100 2
#120000000
0!
0%
0.
#125000000
1!
1%
1.
b00000000000000001100 1
b00000000000000001101 2
#130000000
0!
0%
0.
#135000000
1!
1%
1.
b00000000000000001101 1
b00000000000000001110 2
#140000000
0!
0%
0.
#145000000
1!
1%
1.
b00000000000000001110 1
b00000000000000001111 2
#150000000
0!
0%
0.
#155000000
1!
1%
1.
b00000000000000001111 1
b00000000000000010000 2
#160000000
0!
0%
0.
#165000000
1!
1%
1.
b00000000000000010000 1
b00000000000000010001 2
#170000000
0!
0%
0.
#175000000
1!
1%
1.
b00000000000000010001 1
b00000000000000010010 2
#180000000
0!
0%
0.
#185000000
1!
1%
1.
b00000000000000010010 1
b00000000000000010011 2
#190000000
0!
0%
0.
#195000000
1!
1%
1.
b00000000000000010011 1
b00000000000000010100 2
#200000000
0!
0%
0.
#205000000
1!
1%
1.
b00000000000000010100 1
b00000000000000010101 2
#210000000
0!
0%
0.
#215000000
1!
1%
1.
b00000000000000010101 1
b00000000000000010110 2
#220000000
0!
0%
0.
#225000000
1!
1%
1.
b00000000000000010110 1
b00000000000000010111 2
#230000000
0!
0%
0.
#235000000
1!
1%
1.
b00000000000000010111 1
b00000000000000011000 2
#240000000
0!
0%
0.
#245000000
1!
1%
1.
b00000000000000011000 1
b00000000000000011001 2
#250000000
0!
0%
0.
#255000000
1!
1%
1.
b00000000000000011001 1
b00000000000000011010 2
#260000000
0!
0%
0.
#265000000
1!
1%
1.
b00000000000000011010 1
b00000000000000011011 2
#270000000
0!
0%
0.
#275000000
1!
1%
1.
b00000000000000011011 1
b00000000000000011100 2
#280000000
0!
0%
0.
#285000000
1!
1%
1.
b00000000000000011100 1
b00000000000000011101 2
#290000000
0!
0%
0.
#295000000
1!
1%
1.
b00000000000000011101 1
b00000000000000011110 2
#300000000
0!
0%
0.
#305000000
1!
1%
1.
b00000000000000011110 1
b00000000000000011111 2
#310000000
0!
0%
0.
#315000000
1!
1%
1.
b00000000000000011111 1
b00000000000000100000 2
#320000000
0!
0%
0.
#325000000
1!
1%
1.
b00000000000000100000 1
b00000000000000100001 2
#330000000
0!
0%
0.
#335000000
1!
1%
1.
b00000000000000100001 1
b00000000000000100010 2
#340000000
0!
0%
0.
#345000000
1!
1%
1.
b00000000000000100010 1
b00000000000000100011 2
#350000000
0!
0%
0.
#355000000
1!
1%
1.
b00000000000000100011 1
b00000000000000100100 2
#360000000
0!
0%
0.
#365000000
1!
1%
1.
b00000000000000100100 1
b00000000000000100101 2
#370000000
0!
0%
0.
#375000000
1!
1%
1.
b00000000000000100101 1
b00000000000000100110 2
#380000000
0!
0%
0.
#385000000
1!
1%
1.
b00000000000000100110 1
b00000000000000100111 2
#390000000
0!
0%
0.
#395000000
1!
1%
1.
b00000000000000100111 1
b00000000000000101000 2
#400000000
0!
0%
0.
#405000000
1!
1%
1.
b00000000000000101000 1
b00000000000000101001 2
#410000000
0!
0%
0.
#415000000
1!
1%
1.
b00000000000000101001 1
b00000000000000101010 2
#420000000
0!
0%
0.
#425000000
1!
1%
1.
b00000000000000101010 1
b00000000000000101011 2
#430000000
0!
0%
0.
#435000000
1!
1%
1.
b00000000000000101011 1
b00000000000000101100 2
#440000000
0!
0%
0.
#445000000
1!
1%
1.
b00000000000000101100 1
b00000000000000101101 2
#450000000
0!
0%
0.
#455000000
1!
1%
1.
b00000000000000101101 1
b00000000000000101110 2
#460000000
0!
0%
0.
#465000000
1!
1%
1.
b00000000000000101110 1
b00000000000000101111 2
#470000000
0!
0%
0.
#475000000
1!
1%
1.
b00000000000000101111 1
b00000000000000110000 2
#480000000
0!
0%
0.
#485000000
1!
1%
1.
b00000000000000110000 1
b00000000000000110001 2
#490000000
0!
0%
0.
#495000000
1!
1%
1.
b00000000000000110001 1
b00000000000000110010 2
#500000000
0!
0%
0.
#505000000
1!
1%
1.
b00000000000000110010 1
b00000000000000110011 2
#510000000
0!
0%
0.
#515000000
1!
1%
1.
b00000000000000110011 1
b00000000000000110100 2
#520000000
0!
0%
0.
#525000000
1!
1%
1.
b00000000000000110100 1
b00000000000000110101 2
#530000000
0!
0%
0.
#535000000
1!
1%
1.
b00000000000000110101 1
b00000000000000110110 2
#540000000
0!
0%
0.
#545000000
1!
1%
1.
b00000000000000110110 1
b00000000000000110111 2
#550000000
0!
0%
0.
#555000000
1!
1%
1.
b00000000000000110111 1
b00000000000000111000 2
#560000000
0!
0%
0.
#565000000
1!
1%
1.
b00000000000000111000 1
b00000000000000111001 2
#570000000
0!
0%
0.
#575000000
1!
1%
1.
b00000000000000111001 1
b00000000000000111010 2
#580000000
0!
0%
0.
#585000000
1!
1%
1.
b00000000000000111010 1
b00000000000000111011 2
#590000000
0!
0%
0.
#595000000
1!
1%
1.
b00000000000000111011 1
b00000000000000111100 2
#600000000
0!
0%
0.
#605000000
1!
1%
1.
b00000000000000111100 1
b00000000000000111101 2
#610000000
0!
0%
0.
#615000000
1!
1%
1.
b00000000000000111101 1
b00000000000000111110 2
#620000000
0!
0%
0.
#625000000
1!
1%
1.
b00000000000000111110 1
b00000000000000111111 2
#630000000
0!
0%
0.
#635000000
1!
1%
1.
b00000000000000111111 1
b00000000000001000000 2
#640000000
0!
0%
0.
#645000000
1!
1%
1.
b00000000000001000000 1
b00000000000001000001 2
#650000000
0!
0%
0.
#655000000
1!
1%
1.
b00000000000001000001 1
b00000000000001000010 2
#660000000
0!
0%
0.
#665000000
1!
1%
1.
b00000000000001000010 1
b00000000000001000011 2
#670000000
0!
0%
0.
#675000000
1!
1%
1.
b00000000000001000011 1
b00000000000001000100 2
#680000000
0!
0%
0.
#685000000
1!
1%
1.
b00000000000001000100 1
b00000000000001000101 2
#690000000
0!
0%
0.
#695000000
1!
1%
1.
b00000000000001000101 1
b00000000000001000110 2
#700000000
0!
0%
0.
#705000000
1!
1%
1.
b00000000000001000110 1
b00000000000001000111 2
#710000000
0!
0%
0.
#715000000
1!
1%
1.
b00000000000001000111 1
b00000000000001001000 2
#720000000
0!
0%
0.
#725000000
1!
1%
1.
b00000000000001001000 1
b00000000000001001001 2
#730000000
0!
0%
0.
#735000000
1!
1%
1.
b00000000000001001001 1
b00000000000001001010 2
#740000000
0!
0%
0.
#745000000
1!
1%
1.
b00000000000001001010 1
b00000000000001001011 2
#750000000
0!
0%
0.
#755000000
1!
1%
1.
b00000000000001001011 1
b00000000000001001100 2
#760000000
0!
0%
0.
#765000000
1!
1%
1.
b00000000000001001100 1
b00000000000001001101 2
#770000000
0!
0%
0.
#775000000
1!
1%
1.
b00000000000001001101 1
b00000000000001001110 2
#780000000
0!
0%
0.
#785000000
1!
1%
1.
b00000000000001001110 1
b00000000000001001111 2
#790000000
0!
0%
0.
#795000000
1!
1%
1.
b00000000000001001111 1
b00000000000001010000 2
#800000000
0!
0%
0.
#805000000
1!
1%
1.
b00000000000001010000 1
b00000000000001010001 2
#810000000
0!
0%
0.
#815000000
1!
1%
1.
b00000000000001010001 1
b00000000000001010010 2
#820000000
0!
0%
0.
#825000000
1!
1%
1.
b00000000000001010010 1
b00000000000001010011 2
#830000000
0!
0%
0.
#835000000
1!
1%
1.
b00000000000001010011 1
b00000000000001010100 2
#840000000
0!
0%
0.
#845000000
1!
1%
1.
b00000000000001010100 1
b00000000000001010101 2
#850000000
0!
0%
0.
#855000000
1!
1%
1.
b00000000000001010101 1
b00000000000001010110 2
#860000000
0!
0%
0.
#865000000
1!
1%
1.
b00000000000001010110 1
b00000000000001010111 2
#870000000
0!
0%
0.
#875000000
1!
1%
1.
b00000000000001010111 1
b00000000000001011000 2
#880000000
0!
0%
0.
#885000000
1!
1%
1.
b00000000000001011000 1
b00000000000001011001 2
#890000000
0!
0%
0.
#895000000
1!
1%
1.
b00000000000001011001 1
b00000000000001011010 2
#900000000
0!
0%
0.
#905000000
1!
1%
1.
b00000000000001011010 1
b00000000000001011011 2
#910000000
0!
0%
0.
#915000000
1!
1%
1.
b00000000000001011011 1
b00000000000001011100 2
#920000000
0!
0%
0.
#925000000
1!
1%
1.
b00000000000001011100 1
b00000000000001011101 2
#930000000
0!
0%
0.
#935000000
1!
1%
1.
b00000000000001011101 1
b00000000000001011110 2
#940000000
0!
0%
0.
#945000000
1!
1%
1.
b00000000000001011110 1
b00000000000001011111 2
#950000000
0!
0%
0.
#955000000
1!
1%
1.
b00000000000001011111 1
b00000000000001100000 2
#960000000
0!
0%
0.
#965000000
1!
1%
1.
b00000000000001100000 1
b00000000000001100001 2
#970000000
0!
0%
0.
#975000000
1!
1%
1.
b00000000000001100001 1
b00000000000001100010 2
#980000000
0!
0%
0.
#985000000
1!
1%
1.
b00000000000001100010 1
b00000000000001100011 2
#990000000
0!
0%
0.
#995000000
1!
1%
1.
b00000000000001100011 1
b00000000000001100100 2
#1000000000
0!
0%
0.
#1005000000
1!
1%
1.
b00000000000001100100 1
b00000000000001100101 2
#1010000000
0!
0%
0.
#1015000000
1!
1%
1.
b00000000000001100101 1
b00000000000001100110 2
#1020000000
0!
0%
0.
#1025000000
1!
1%
1.
b00000000000001100110 1
b00000000000001100111 2
#1030000000
0!
0%
0.
#1035000000
1!
1%
1.
b00000000000001100111 1
b00000000000001101000 2
#1040000000
0!
0%
0.
#1045000000
1!
1%
1.
b00000000000001101000 1
b00000000000001101001 2
#1050000000
0!
0%
0.
#1055000000
1!
1%
1.
b00000000000001101001 1
b00000000000001101010 2
#1060000000
0!
0%
0.
#1065000000
1!
1%
1.
b00000000000001101010 1
b00000000000001101011 2
#1070000000
0!
0%
0.
#1075000000
1!
1%
1.
b00000000000001101011 1
b00000000000001101100 2
#1080000000
0!
0%
0.
#1085000000
1!
1%
1.
b00000000000001101100 1
b00000000000001101101 2
#1090000000
0!
0%
0.
#1095000000
1!
1%
1.
b00000000000001101101 1
b00000000000001101110 2
#1100000000
0!
0%
0.
#1105000000
1!
1%
1.
b00000000000001101110 1
b00000000000001101111 2
#1110000000
0!
0%
0.
#1115000000
1!
1%
1.
b00000000000001101111 1
b00000000000001110000 2
#1120000000
0!
0%
0.
#1125000000
1!
1%
1.
b00000000000001110000 1
b00000000000001110001 2
#1130000000
0!
0%
0.
#1135000000
1!
1%
1.
b00000000000001110001 1
b00000000000001110010 2
#1140000000
0!
0%
0.
#1145000000
1!
1%
1.
b00000000000001110010 1
b00000000000001110011 2
#1150000000
0!
0%
0.
#1155000000
1!
1%
1.
b00000000000001110011 1
b00000000000001110100 2
#1160000000
0!
0%
0.
#1165000000
1!
1%
1.
b00000000000001110100 1
b00000000000001110101 2
#1170000000
0!
0%
0.
#1175000000
1!
1%
1.
b00000000000001110101 1
b00000000000001110110 2
#1180000000
0!
0%
0.
#1185000000
1!
1%
1.
b00000000000001110110 1
b00000000000001110111 2
#1190000000
0!
0%
0.
#1195000000
1!
1%
1.
b00000000000001110111 1
b00000000000001111000 2
#1200000000
0!
0%
0.
#1205000000
1!
1%
1.
b00000000000001111000 1
b00000000000001111001 2
#1210000000
0!
0%
0.
#1215000000
1!
1%
1.
b00000000000001111001 1
b00000000000001111010 2
#1220000000
0!
0%
0.
#1225000000
1!
1%
1.
b00000000000001111010 1
b00000000000001111011 2
#1230000000
0!
0%
0.
#1235000000
1!
1%
1.
b00000000000001111011 1
b00000000000001111100 2
#1240000000
0!
0%
0.
#1245000000
1!
1%
1.
b00000000000001111100 1
b00000000000001111101 2
#1250000000
0!
0%
0.
#1255000000
1!
1%
1.
b00000000000001111101 1
b00000000000001111110 2
#1260000000
0!
0%
0.
#1265000000
1!
1%
1.
b00000000000001111110 1
b00000000000001111111 2
#1270000000
0!
0%
0.
#1275000000
1!
1%
1.
b00000000000001111111 1
b00000000000010000000 2
#1280000000
0!
0%
0.
#1285000000
1!
1%
1.
b00000000000010000000 1
b00000000000010000001 2
#1290000000
0!
0%
0.
#1295000000
1!
1%
1.
b00000000000010000001 1
b00000000000010000010 2
#1300000000
0!
0%
0.
#1305000000
1!
1%
1.
b00000000000010000010 1
b00000000000010000011 2
#1310000000
0!
0%
0.
#1315000000
1!
1%
1.
b00000000000010000011 1
b00000000000010000100 2
#1320000000
0!
0%
0.
#1325000000
1!
1%
1.
b00000000000010000100 1
b00000000000010000101 2
#1330000000
0!
0%
0.
#1335000000
1!
1%
1.
b00000000000010000101 1
b00000000000010000110 2
#1340000000
0!
0%
0.
#1345000000
1!
1%
1.
b00000000000010000110 1
b00000000000010000111 2
#1350000000
0!
0%
0.
#1355000000
1!
1%
1.
b00000000000010000111 1
b00000000000010001000 2
#1360000000
0!
0%
0.
#1365000000
1!
1%
1.
b00000000000010001000 1
b00000000000010001001 2
#1370000000
0!
0%
0.
#1375000000
1!
1%
1.
b00000000000010001001 1
b00000000000010001010 2
#1380000000
0!
0%
0.
#1385000000
1!
1%
1.
b00000000000010001010 1
b00000000000010001011 2
#1390000000
0!
0%
0.
#1395000000
1!
1%
1.
b00000000000010001011 1
b00000000000010001100 2
#1400000000
0!
0%
0.
#1405000000
1!
1%
1.
b00000000000010001100 1
b00000000000010001101 2
#1410000000
0!
0%
0.
#1415000000
1!
1%
1.
b00000000000010001101 1
b00000000000010001110 2
#1420000000
0!
0%
0.
#1425000000
1!
1%
1.
b00000000000010001110 1
b00000000000010001111 2
#1430000000
0!
0%
0.
#1435000000
1!
1%
1.
b00000000000010001111 1
b00000000000010010000 2
#1440000000
0!
0%
0.
#1445000000
1!
1%
1.
b00000000000010010000 1
b00000000000010010001 2
#1450000000
0!
0%
0.
#1455000000
1!
1%
1.
b00000000000010010001 1
b00000000000010010010 2
#1460000000
0!
0%
0.
#1465000000
1!
1%
1.
b00000000000010010010 1
b00000000000010010011 2
#1470000000
0!
0%
0.
#1475000000
1!
1%
1.
b00000000000010010011 1
b00000000000010010100 2
#1480000000
0!
0%
0.
#1485000000
1!
1%
1.
b00000000000010010100 1
b00000000000010010101 2
#1490000000
0!
0%
0.
#1495000000
1!
1%
1.
b00000000000010010101 1
b00000000000010010110 2
#1500000000
0!
0%
0.
#1505000000
1!
1%
1.
b00000000000010010110 1
b00000000000010010111 2
#1510000000
0!
0%
0.
#1515000000
1!
1%
1.
b00000000000010010111 1
b00000000000010011000 2
#1520000000
0!
0%
0.
#1525000000
1!
1%
1.
b00000000000010011000 1
b00000000000010011001 2
#1530000000
0!
0%
0.
#1535000000
1!
1%
1.
b00000000000010011001 1
b00000000000010011010 2
#1540000000
0!
0%
0.
#1545000000
1!
1%
1.
b00000000000010011010 1
b00000000000010011011 2
#1550000000
0!
0%
0.
#1555000000
1!
1%
1.
b00000000000010011011 1
b00000000000010011100 2
#1560000000
0!
0%
0.
#1565000000
1!
1%
1.
b00000000000010011100 1
b00000000000010011101 2
#1570000000
0!
0%
0.
#1575000000
1!
1%
1.
b00000000000010011101 1
b00000000000010011110 2
#1580000000
0!
0%
0.
#1585000000
1!
1%
1.
b00000000000010011110 1
b00000000000010011111 2
#1590000000
0!
0%
0.
#1595000000
1!
1%
1.
b00000000000010011111 1
b00000000000010100000 2
#1600000000
0!
0%
0.
#1605000000
1!
1%
1.
b00000000000010100000 1
b00000000000010100001 2
#1610000000
0!
0%
0.
#1615000000
1!
1%
1.
b00000000000010100001 1
b00000000000010100010 2
#1620000000
0!
0%
0.
#1625000000
1!
1%
1.
b00000000000010100010 1
b00000000000010100011 2
#1630000000
0!
0%
0.
#1635000000
1!
1%
1.
b00000000000010100011 1
b00000000000010100100 2
#1640000000
0!
0%
0.
#1645000000
1!
1%
1.
b00000000000010100100 1
b00000000000010100101 2
#1650000000
0!
0%
0.
#1655000000
1!
1%
1.
b00000000000010100101 1
b00000000000010100110 2
#1660000000
0!
0%
0.
#1665000000
1!
1%
1.
b00000000000010100110 1
b00000000000010100111 2
#1670000000
0!
0%
0.
#1675000000
1!
1%
1.
b00000000000010100111 1
b00000000000010101000 2
#1680000000
0!
0%
0.
#1685000000
1!
1%
1.
b00000000000010101000 1
b00000000000010101001 2
#1690000000
0!
0%
0.
#1695000000
1!
1%
1.
b00000000000010101001 1
b00000000000010101010 2
#1700000000
0!
0%
0.
#1705000000
1!
1%
1.
b00000000000010101010 1
b00000000000010101011 2
#1710000000
0!
0%
0.
#1715000000
1!
1%
1.
b00000000000010101011 1
b00000000000010101100 2
#1720000000
0!
0%
0.
#1725000000
1!
1%
1.
b00000000000010101100 1
b00000000000010101101 2
#1730000000
0!
0%
0.
#1735000000
1!
1%
1.
b00000000000010101101 1
b00000000000010101110 2
#1740000000
0!
0%
0.
#1745000000
1!
1%
1.
b00000000000010101110 1
b00000000000010101111 2
#1750000000
0!
0%
0.
#1755000000
1!
1%
1.
b00000000000010101111 1
b00000000000010110000 2
#1760000000
0!
0%
0.
#1765000000
1!
1%
1.
b00000000000010110000 1
b00000000000010110001 2
#1770000000
0!
0%
0.
#1775000000
1!
1%
1.
b00000000000010110001 1
b00000000000010110010 2
#1780000000
0!
0%
0.
#1785000000
1!
1%
1.
b00000000000010110010 1
b00000000000010110011 2
#1790000000
0!
0%
0.
#1795000000
1!
1%
1.
b00000000000010110011 1
b00000000000010110100 2
#1800000000
0!
0%
0.
#1805000000
1!
1%
1.
b00000000000010110100 1
b00000000000010110101 2
#1810000000
0!
0%
0.
#1815000000
1!
1%
1.
b00000000000010110101 1
b00000000000010110110 2
#1820000000
0!
0%
0.
#1825000000
1!
1%
1.
b00000000000010110110 1
b00000000000010110111 2
#1830000000
0!
0%
0.
#1835000000
1!
1%
1.
b00000000000010110111 1
b00000000000010111000 2
#1840000000
0!
0%
0.
#1845000000
1!
1%
1.
b00000000000010111000 1
b00000000000010111001 2
#1850000000
0!
0%
0.
#1855000000
1!
1%
1.
b00000000000010111001 1
b00000000000010111010 2
#1860000000
0!
0%
0.
#1865000000
1!
1%
1.
b00000000000010111010 1
b00000000000010111011 2
#1870000000
0!
0%
0.
#1875000000
1!
1%
1.
b00000000000010111011 1
b00000000000010111100 2
#1880000000
0!
0%
0.
#1885000000
1!
1%
1.
b00000000000010111100 1
b00000000000010111101 2
#1890000000
0!
0%
0.
#1895000000
1!
1%
1.
b00000000000010111101 1
b00000000000010111110 2
#1900000000
0!
0%
0.
#1905000000
1!
1%
1.
b00000000000010111110 1
b00000000000010111111 2
#1910000000
0!
0%
0.
#1915000000
1!
1%
1.
b00000000000010111111 1
b00000000000011000000 2
#1920000000
0!
0%
0.
#1925000000
1!
1%
1.
b00000000000011000000 1
b00000000000011000001 2
#1930000000
0!
0%
0.
#1935000000
1!
1%
1.
b00000000000011000001 1
b00000000000011000010 2
#1940000000
0!
0%
0.
#1945000000
1!
1%
1.
b00000000000011000010 1
b00000000000011000011 2
#1950000000
0!
0%
0.
#1955000000
1!
1%
1.
b00000000000011000011 1
b00000000000011000100 2
#1960000000
0!
0%
0.
#1965000000
1!
1%
1.
b00000000000011000100 1
b00000000000011000101 2
#1970000000
0!
0%
0.
#1975000000
1!
1%
1.
b00000000000011000101 1
b00000000000011000110 2
#1980000000
0!
0%
0.
#1985000000
1!
1%
1.
b00000000000011000110 1
b00000000000011000111 2
#1990000000
0!
0%
0.
#1995000000
1!
1%
1.
b00000000000011000111 1
b00000000000011001000 2
#2000000000
0!
0%
0.
#2005000000
1!
1%
1.
b00000000000011001000 1
b00000000000011001001 2
#2010000000
0!
0%
0.
#2015000000
1!
1%
1.
b00000000000011001001 1
b00000000000011001010 2
#2020000000
0!
0%
0.
#2025000000
1!
1%
1.
b00000000000011001010 1
b00000000000011001011 2
#2030000000
0!
0%
0.
#2035000000
1!
1%
1.
b00000000000011001011 1
b00000000000011001100 2
#2040000000
0!
0%
0.
#2045000000
1!
1%
1.
b00000000000011001100 1
b00000000000011001101 2
#2050000000
0!
0%
0.
#2055000000
1!
1%
1.
b00000000000011001101 1
b00000000000011001110 2
#2060000000
0!
0%
0.
#2065000000
1!
1%
1.
b00000000000011001110 1
b00000000000011001111 2
#2070000000
0!
0%
0.
#2075000000
1!
1%
1.
b00000000000011001111 1
b00000000000011010000 2
#2080000000
0!
0%
0.
