VHDL Files/src/counters/t_ff.vhd
-- VHDL 8 bit processor project
-- T Flip Flop
-- James Hicks November 11 2023

library ieee;
use ieee.std_logic_1164.all;

entity t_ff is
    Port ( t   : in STD_LOGIC;
           en  : in STD_LOGIC;
           rst : in STD_LOGIC;
           clk : in STD_LOGIC;
           q   : out STD_LOGIC);
end t_ff;

-- two segment architecture
architecture two_seg_arch of t_ff is

signal q_pres, q_next : std_logic;

begin

  t_ff_process: process( clk, rst ) -- en is not in list
  begin
      if (rst = '1') then
          q_pres <= '0';
      elsif (clk'event and clk='1') then
        if(en = '1') then
          q_pres <= q_next;
        end if;
      end if;
  end process;

  -- next state logic
  q_next <= (t xor q_pres) when en='1' else
            (q_pres and (not en));

 -- output logic
  q <= q_pres;

end two_seg_arch;

VHDL Files/src/counters/t_ff_tb.vhd
-- VHDL 8 bit processor Project
-- T Flip Flop Test Bench
-- James Hicks November 1 2023

library ieee;
use ieee.std_logic_1164.all;
use ieee.numeric_std.all;

entity t_ff_tb is
end t_ff_tb;

architecture tb of t_ff_tb is

    signal t, en, rst, clk, q : std_logic := '0';

    constant clk_period : time := 10 ns;

begin

    DUT: entity work.t_ff(two_seg_arch)
    port map( t   => t,
              en  => en,
              rst => rst,
              clk => clk,
              q   => q
            );

    -- clock process
    clk_process : process
    begin
        loop
            wait for clk_period / 2;
            clk <= not clk;
        end loop;
    end process;

    -- data  process
    t_process : process
    begin
        wait for 20 ns;
        t <= '1';
        wait for 30 ns;
        t <= '0';
        wait for 40 ns;
        t <= '1';
        for I in 1 to 9 loop
            wait for 10 ns;
            t <= not t;
        end loop;
        wait for 20 ns;
        t <= '1';
        wait;
    end process;

    -- enable process
    en_process : process
    begin
        wait for 20 ns;
        en <= '1';
        wait for 210 ns;
        en <= '0';
        wait for 30 ns;
    end process;

    -- termination process
    termination_process : process
    begin
        wait for 260 ns;
        assert false report "end of test" severity failure;
    end process;

    -- rst process
    rst_process : process
    begin
        rst <= '1';
        wait for clk_period / 2;
        rst <= '0';
        wait;
    end process;
end tb;

VHDL Files/src/counters/tsim.vcd
$date
  Sat Nov 11 13:17:52 2023
$end
$version
  GHDL v0
$end
$timescale
  1 fs
$end
$scope module standard $end
$upscope $end
$scope module std_logic_1164 $end
$upscope $end
$scope module numeric_std $end
$upscope $end
$scope module t_ff_tb $end
$var reg 1 ! t $end
$var reg 1 " en $end
$var reg 1 # rst $end
$var reg 1 $ clk $end
$var reg 1 % q $end
$scope module dut $end
$var reg 1 & t $end
$var reg 1 ' en $end
$var reg 1 ( rst $end
$var reg 1 ) clk $end
$var reg 1 * q $end
$var reg 1 + q_pres $end
$var reg 1 , q_next $end
$upscope $end
$upscope $end
$enddefinitions $end
#0
0!
0"
1#
0$
0%
0&
0'
1(
0)
0*
0+
0,
#5000000
0#
1$
0(
1)
#10000000
0$
0)
#15000000
1$
1)
#20000000
1!
1"
0$
1&
1'
0)
1,
#25000000
1$
1%
1)
1*
1+
0,
#30000000
0$
0)
#35000000
1$
0%
1)
0*
0+
1,
#40000000
0$
0)
#45000000
1$
1%
1)
1*
1+
0,
#50000000
0!
0$
0&
0)
1,
#55000000
1$
1)
#60000000
0$
0)
#65000000
1$
1)
#70000000
0$
0)
#75000000
1$
1)
#80000000
0$
0)
#85000000
1$
1)
#90000000
1!
0$
1&
0)
0,
#95000000
1$
0%
1)
0*
0+
1,
#100000000
0!
0$
0&
0)
0,
#105000000
1$
1)
#110000000
1!
0$
1&
0)
1,
#115000000
1$
1%
1)
1*
1+
0,
#120000000
0!
0$
0&
0)
1,
#125000000
1$
1)
#130000000
1!
0$
1&
0)
0,
#135000000
1$
0%
1)
0*
0+
1,
#140000000
0!
0$
0&
0)
0,
#145000000
1$
1)
#150000000
1!
0$
1&
0)
1,
#155000000
1$
1%
1)
1*
1+
0,
#160000000
0!
0$
0&
0)
1,
#165000000
1$
1)
#170000000
1!
0$
1&
0)
0,
#175000000
1$
0%
1)
0*
0+
1,
#180000000
0!
0$
0&
0)
0,
#185000000
1$
1)
#190000000
0$
0)
#195000000
1$
1)
#200000000
1!
0$
1&
0)
1,
#205000000
1$
1%
1)
1*
1+
0,
#210000000
0$
0)
#215000000
1$
0%
1)
0*
0+
1,
#220000000
0$
0)
#225000000
1$
1%
1)
1*
1+
0,
#230000000
0"
0$
0'
0)
1,
