VHDL Files/src/ones_detector/10_ms_timer.vhd
library ieee;
use ieee.std_logic_1164.all;
use ieee.numeric_std.all;

entity ten_ms is
  generic (max   :     integer   := 1000000;
           width :     integer   := 20);
  port    (clk   : in  std_logic := '0';
           rst   : in  std_logic := '0';
           en    : in  std_logic := '0';
           tick  : out std_logic := '0');
end ten_ms;

architecture my_arch of ten_ms is
  signal r_next, r_pres : unsigned (width-1 downto 0) := (others => '0');
begin

  process (clk, rst)
  begin
    if(rst = '1') then
      r_pres <= (others => '0');
    elsif(rising_edge(clk)) then
      r_pres <= r_next;
    end if ;
  end process;

  --NEXT STATE LOGIC
  r_next <= (others => '0')when(((r_pres = max)and(en = '1')) or rst = '1') else
            r_pres + 1      when en ='1' else
            r_pres;

  tick <= '1' when r_pres = max else '0';

end my_arch;

VHDL Files/src/ones_detector/debouncer.vhd
library ieee;
use ieee.std_logic_1164.all;
use ieee.numeric_std.all;

entity debouncer is
  port ( sw        : in  std_logic;
         rst       : in  std_logic;
         clk       : in  std_logic;
         db        : out std_logic );
end debouncer;

architecture my_arch of debouncer is

  type state_type is ( zero, one,
                       w1_0, w1_1,
                       w0_0, w0_1 );
  signal r_pres, r_next : state_type;
  signal tick           : std_logic;

begin

  tick_generator : entity work.ten_ms(my_arch)
    generic map (max   => 3,
                 width => 2)
    port map ( clk => clk,
               rst => rst,
               en  => '1',
               tick => tick);

  process(clk, rst)
  begin
    if(rst = '1') then
      r_pres <= zero;
    elsif(rising_edge(clk)) then
      r_pres <= r_next;
    end if;
  end process;

  process(r_pres, sw, tick)
  begin
  -- DEFAULTS
    r_next <= r_pres;
    db     <= '0';

    case r_pres is

      when zero =>
        if(sw = '1') then
          r_next <= w1_0;
        else
          r_next <= zero;
        end if;

      when w1_0 =>
        if(sw = '1' and tick = '1') then
          r_next <= w1_1;
        else
          r_next <= zero;
        end if;

      when w1_1 =>
        if(sw = '1' and tick = '1') then
          r_next <= one;
        else
          r_next <= zero;
        end if;

      when one  =>
        if(sw = '0') then
          r_next <= w0_0;
        else
          r_next <= one;
        end if;
        db <= '1';

      when w0_0 =>
        if(sw = '0' and tick = '1') then
          r_next <= w0_1;
        else
          r_next <= one;
        end if;
        db <= '1';

      when w0_1 =>
        if(sw = '0' and tick = '1') then
          r_next <= zero;
        else
          r_next <= one;
        end if;
        db <= '1';

    end case;
  end process;

end my_arch;

VHDL Files/src/ones_detector/debouncer_tb.vhd
library ieee;
use ieee.std_logic_1164.all;
use ieee.numeric_std.all;

entity tb is
end tb;

architecture my_arch of tb is
  signal   test_sw    : std_logic := '1';
  signal   test_rst   : std_logic := '0';
  signal   test_clk   : std_logic := '0';
  signal   test_db    : std_logic := '0';
  constant clk_period : time := 10 ns;
begin

  DUT : entity work.debouncer(my_arch)
    port map ( sw  => test_sw,
               rst => test_rst,
               clk => test_clk,
               db  => test_db );

  sw_process : process
  begin
    for i in 0 to 21 loop
      wait for 1 ns;
      test_sw <= not test_sw;
    end loop;
    wait for 20 ms;
  end process;

  rst_process : process
  begin
    wait;
  end process;

  clk_process : process
  begin
    wait for clk_period / 2;
    test_clk <= not test_clk;
  end process;

  kill_process : process
  begin
    wait for 100000 ns;
    assert false report "end of test" severity failure;
  end process;

end my_arch;

VHDL Files/src/ones_detector/db_sim.vcd
$date
  Sat Nov 25 11:34:22 2023
$end
$version
  GHDL v0
$end
$timescale
  1 fs
$end
$scope module standard $end
$upscope $end
$scope module std_logic_1164 $end
$upscope $end
$scope module numeric_std $end
$upscope $end
$scope module tb $end
$var reg 1 ! test_sw $end
$var reg 1 " test_rst $end
$var reg 1 # test_clk $end
$var reg 1 $ test_db $end
$scope module dut $end
$var reg 1 % sw $end
$var reg 1 & rst $end
$var reg 1 ' clk $end
$var reg 1 ( db $end
$comment r_pres is not handled $end
$comment r_next is not handled $end
$var reg 1 ) tick $end
$scope module tick_generator $end
$var reg 1 * clk $end
$var reg 1 + rst $end
$var reg 1 , en $end
$var reg 1 - tick $end
$var reg 2 . r_next[1:0] $end
$var reg 2 / r_pres[1:0] $end
$upscope $end
$upscope $end
$upscope $end
$enddefinitions $end
#0
1!
0"
0#
0$
1%
0&
0'
0(
0)
0*
0+
1,
0-
b01 .
b00 /
#1000000
0!
0%
#2000000
1!
1%
#3000000
0!
0%
#4000000
1!
1%
#5000000
0!
1#
0%
1'
1*
b10 .
b01 /
#6000000
1!
1%
#7000000
0!
0%
#8000000
1!
1%
#9000000
0!
0%
#10000000
1!
0#
1%
0'
0*
#11000000
0!
0%
#12000000
1!
1%
#13000000
0!
0%
#14000000
1!
1%
#15000000
0!
1#
0%
1'
1*
b11 .
b10 /
#16000000
1!
1%
#17000000
0!
0%
#18000000
1!
1%
#19000000
0!
0%
#20000000
1!
0#
1%
0'
0*
#21000000
0!
0%
#22000000
1!
1%
#25000000
1#
1'
1)
1*
1-
b00 .
b11 /
#30000000
0#
0'
0*
#35000000
1#
1'
0)
1*
0-
b01 .
b00 /
#40000000
0#
0'
0*
#45000000
1#
1'
1*
b10 .
b01 /
#50000000
0#
0'
0*
#55000000
1#
1'
1*
b11 .
b10 /
#60000000
0#
0'
0*
#65000000
1#
1'
1)
1*
1-
b00 .
b11 /
#70000000
0#
0'
0*
#75000000
1#
1'
0)
1*
0-
b01 .
b00 /
#80000000
0#
0'
0*
#85000000
1#
1'
1*
b10 .
b01 /
#90000000
0#
0'
0*
#95000000
1#
1'
1*
b11 .
b10 /
#100000000
0#
0'
0*
#105000000
1#
1'
1)
1*
1-
b00 .
b11 /
#110000000
0#
0'
0*
#115000000
1#
1'
0)
1*
0-
b01 .
b00 /
#120000000
0#
0'
0*
#125000000
1#
1'
1*
b10 .
b01 /
#130000000
0#
0'
0*
#135000000
1#
1'
1*
b11 .
b10 /
#140000000
0#
0'
0*
#145000000
1#
1'
1)
1*
1-
b00 .
b11 /
#150000000
0#
0'
0*
#155000000
1#
1'
0)
1*
0-
b01 .
b00 /
#160000000
0#
0'
0*
#165000000
1#
1'
1*
b10 .
b01 /
#170000000
0#
0'
0*
#175000000
1#
1'
1*
b11 .
b10 /
#180000000
0#
0'
0*
#185000000
1#
1'
1)
1*
1-
b00 .
b11 /
#190000000
0#
0'
0*
#195000000
1#
1'
0)
1*
0-
b01 .
b00 /
#200000000
0#
0'
0*
#205000000
1#
1'
1*
b10 .
b01 /
#210000000
0#
0'
0*
#215000000
1#
1'
1*
b11 .
b10 /
#220000000
0#
0'
0*
#225000000
1#
1'
1)
1*
1-
b00 .
b11 /
#230000000
0#
0'
0*
#235000000
1#
1'
0)
1*
0-
b01 .
b00 /
#240000000
0#
0'
0*
#245000000
1#
1'
1*
b10 .
b01 /
#250000000
0#
0'
0*
#255000000
1#
1'
1*
b11 .
b10 /
#260000000
0#
0'
0*
#265000000
1#
1'
1)
1*
1-
b00 .
b11 /
#270000000
0#
0'
0*
#275000000
1#
1'
0)
1*
0-
b01 .
b00 /
#280000000
0#
0'
0*
#285000000
1#
1'
1*
b10 .
b01 /
#290000000
0#
0'
0*
#295000000
1#
1'
1*
b11 .
b10 /
#300000000
0#
0'
0*
#305000000
1#
1'
1)
1*
1-
b00 .
b11 /
#310000000
0#
0'
0*
#315000000
1#
1'
0)
1*
0-
b01 .
b00 /
#320000000
0#
0'
0*
#325000000
1#
1'
1*
b10 .
b01 /
#330000000
0#
0'
0*
#335000000
1#
1'
1*
b11 .
b10 /
#340000000
0#
0'
0*
#345000000
1#
1'
1)
1*
1-
b00 .
b11 /
#350000000
0#
0'
0*
#355000000
1#
1'
0)
1*
0-
b01 .
b00 /
#360000000
0#
0'
0*
#365000000
1#
1'
1*
b10 .
b01 /
#370000000
0#
0'
0*
#375000000
1#
1'
1*
b11 .
b10 /
#380000000
0#
0'
0*
#385000000
1#
1'
1)
1*
1-
b00 .
b11 /
#390000000
0#
0'
0*
#395000000
1#
1'
0)
1*
0-
b01 .
b00 /
#400000000
0#
0'
0*
#405000000
1#
1'
1*
b10 .
b01 /
#410000000
0#
0'
0*
#415000000
1#
1'
1*
b11 .
b10 /
#420000000
0#
0'
0*
#425000000
1#
1'
1)
1*
1-
b00 .
b11 /
#430000000
0#
0'
0*
#435000000
1#
1'
0)
1*
0-
b01 .
b00 /
#440000000
0#
0'
0*
#445000000
1#
1'
1*
b10 .
b01 /
#450000000
0#
0'
0*
#455000000
1#
1'
1*
b11 .
b10 /
#460000000
0#
0'
0*
#465000000
1#
1'
1)
1*
1-
b00 .
b11 /
#470000000
0#
0'
0*
#475000000
1#
1'
0)
1*
0-
b01 .
b00 /
#480000000
0#
0'
0*
#485000000
1#
1'
1*
b10 .
b01 /
#490000000
0#
0'
0*
#495000000
1#
1'
1*
b11 .
b10 /
#500000000
0#
0'
0*
#505000000
1#
1'
1)
1*
1-
b00 .
b11 /
#510000000
0#
0'
0*
#515000000
1#
1'
0)
1*
0-
b01 .
b00 /
#520000000
0#
0'
0*
#525000000
1#
1'
1*
b10 .
b01 /
#530000000
0#
0'
0*
#535000000
1#
1'
1*
b11 .
b10 /
#540000000
0#
0'
0*
#545000000
1#
1'
1)
1*
1-
b00 .
b11 /
#550000000
0#
0'
0*
#555000000
1#
1'
0)
1*
0-
b01 .
b00 /
#560000000
0#
0'
0*
#565000000
1#
1'
1*
b10 .
b01 /
#570000000
0#
0'
0*
#575000000
1#
1'
1*
b11 .
b10 /
#580000000
0#
0'
0*
#585000000
1#
1'
1)
1*
1-
b00 .
b11 /
#590000000
0#
0'
0*
#595000000
1#
1'
0)
1*
0-
b01 .
b00 /
#600000000
0#
0'
0*
#605000000
1#
1'
1*
b10 .
b01 /
#610000000
0#
0'
0*
#615000000
1#
1'
1*
b11 .
b10 /
#620000000
0#
0'
0*
#625000000
1#
1'
1)
1*
1-
b00 .
b11 /
#630000000
0#
0'
0*
#635000000
1#
1'
0)
1*
0-
b01 .
b00 /
#640000000
0#
0'
0*
#645000000
1#
1'
1*
b10 .
b01 /
#650000000
0#
0'
0*
#655000000
1#
1'
1*
b11 .
b10 /
#660000000
0#
0'
0*
#665000000
1#
1'
1)
1*
1-
b00 .
b11 /
#670000000
0#
0'
0*
#675000000
1#
1'
0)
1*
0-
b01 .
b00 /
#680000000
0#
0'
0*
#685000000
1#
1'
1*
b10 .
b01 /
#690000000
0#
0'
0*
#695000000
1#
1'
1*
b11 .
b10 /
#700000000
0#
0'
0*
#705000000
1#
1'
1)
1*
1-
b00 .
b11 /
#710000000
0#
0'
0*
#715000000
1#
1'
0)
1*
0-
b01 .
b00 /
#720000000
0#
0'
0*
#725000000
1#
1'
1*
b10 .
b01 /
#730000000
0#
0'
0*
#735000000
1#
1'
1*
b11 .
b10 /
#740000000
0#
0'
0*
#745000000
1#
1'
1)
1*
1-
b00 .
b11 /
#750000000
0#
0'
0*
#755000000
1#
1'
0)
1*
0-
b01 .
b00 /
#760000000
0#
0'
0*
#765000000
1#
1'
1*
b10 .
b01 /
#770000000
0#
0'
0*
#775000000
1#
1'
1*
b11 .
b10 /
#780000000
0#
0'
0*
#785000000
1#
1'
1)
1*
1-
b00 .
b11 /
#790000000
0#
0'
0*
#795000000
1#
1'
0)
1*
0-
b01 .
b00 /
#800000000
0#
0'
0*
#805000000
1#
1'
1*
b10 .
b01 /
#810000000
0#
0'
0*
#815000000
1#
1'
1*
b11 .
b10 /
#820000000
0#
0'
0*
#825000000
1#
1'
1)
1*
1-
b00 .
b11 /
#830000000
0#
0'
0*
#835000000
1#
1'
0)
1*
0-
b01 .
b00 /
#840000000
0#
0'
0*
#845000000
1#
1'
1*
b10 .
b01 /
#850000000
0#
0'
0*
#855000000
1#
1'
1*
b11 .
b10 /
#860000000
0#
0'
0*
#865000000
1#
1'
1)
1*
1-
b00 .
b11 /
#870000000
0#
0'
0*
#875000000
1#
1'
0)
1*
0-
b01 .
b00 /
#880000000
0#
0'
0*
#885000000
1#
1'
1*
b10 .
b01 /
#890000000
0#
0'
0*
#895000000
1#
1'
1*
b11 .
b10 /
#900000000
0#
0'
0*
#905000000
1#
1'
1)
1*
1-
b00 .
b11 /
#910000000
0#
0'
0*
#915000000
1#
1'
0)
1*
0-
b01 .
b00 /
#920000000
0#
0'
0*
#925000000
1#
1'
1*
b10 .
b01 /
#930000000
0#
0'
0*
#935000000
1#
1'
1*
b11 .
b10 /
#940000000
0#
0'
0*
#945000000
1#
1'
1)
1*
1-
b00 .
b11 /
#950000000
0#
0'
0*
#955000000
1#
1'
0)
1*
0-
b01 .
b00 /
#960000000
0#
0'
0*
#965000000
1#
1'
1*
b10 .
b01 /
#970000000
0#
0'
0*
#975000000
1#
1'
1*
b11 .
b10 /
#980000000
0#
0'
0*
#985000000
1#
1'
1)
1*
1-
b00 .
b11 /
#990000000
0#
0'
0*
#995000000
1#
1'
0)
1*
0-
b01 .
b00 /
