VHDL Files/src/ones_detector/10_ms_timer.vhd
library ieee;
use ieee.std_logic_1164.all;
use ieee.numeric_std.all;

entity ten_ms is
  generic (max   :     integer   := 1000000;
           width :     integer   := 20);
  port    (clk   : in  std_logic := '0';
           rst   : in  std_logic := '0';
           en    : in  std_logic := '0';
           tick  : out std_logic := '0');
end ten_ms;

architecture my_arch of ten_ms is
  signal r_next, r_pres : unsigned (width-1 downto 0) := (others => '0');
begin

  process (clk, rst)
  begin
    if(rst = '1') then
      r_pres <= (others => '0');
    elsif(rising_edge(clk)) then
      r_pres <= r_next;
    end if ;
  end process;

  --NEXT STATE LOGIC
  r_next <= (others => '0')when(((r_pres = max)and(en = '1')) or rst = '1') else
            r_pres + 1      when en ='1' else
            r_pres;

  tick <= '1' when r_pres = max else '0';

end my_arch;

VHDL Files/src/ones_detector/debouncer.vhd
library ieee;
use ieee.std_logic_1164.all;
use ieee.numeric_std.all;

entity debouncer is
  port ( sw        : in  std_logic;
         rst       : in  std_logic;
         clk       : in  std_logic;
         db        : out std_logic );
end debouncer;

architecture my_arch of debouncer is

  type state_type is ( zero, one,
                       w1_0, w1_1,
                       w0_0, w0_1 );
  signal r_pres, r_next : state_type;
  signal tick           : std_logic;

begin

  tick_generator : entity work.ten_ms(my_arch)
    generic map (max   => 3,
                 width => 2)
    port map ( clk => clk,
               rst => rst,
               en  => '1',
               tick => tick);

  process(clk, rst)
  begin
    if(rst = '1') then
      r_pres <= zero;
    elsif(rising_edge(clk)) then
      r_pres <= r_next;
    end if;
  end process;

  process(r_pres, sw, tick)
  begin
  -- DEFAULTS
    r_next <= r_pres;
    db     <= '0';

    case r_pres is

      when zero =>
        if(sw = '1') then
          r_next <= w1_0;
        end if;

      when w1_0 =>
        if(sw = '1' and tick = '1') then
          r_next <= w1_1;
        elsif(sw = '0') then
          r_next <= zero;
        end if;

      when w1_1 =>
        if(sw = '1' and tick = '1') then
          r_next <= one;
        elsif(sw = '0') then
          r_next <= zero;
        end if;

      when one  =>
        if(sw = '0') then
          r_next <= w0_0;
        end if;
        db <= '1';

      when w0_0 =>
        if(sw = '0' and tick = '1') then
          r_next <= w0_1;
        elsif(sw = '1') then
          r_next <= one;
        end if;
        db <= '1';

      when w0_1 =>
        if(sw = '0' and tick = '1') then
          r_next <= zero;
        elsif(sw = '1') then
          r_next <= one;
        end if;
        db <= '1';

    end case;
  end process;

end my_arch;

VHDL Files/src/ones_detector/debouncer_tb.vhd
library ieee;
use ieee.std_logic_1164.all;
use ieee.numeric_std.all;

entity tb is
end tb;

architecture my_arch of tb is
  signal   test_sw    : std_logic := '1';
  signal   test_rst   : std_logic := '0';
  signal   test_clk   : std_logic := '0';
  signal   test_db    : std_logic := '0';
  constant clk_period : time := 10 ns;
begin

  DUT : entity work.debouncer(my_arch)
    port map ( sw  => test_sw,
               rst => test_rst,
               clk => test_clk,
               db  => test_db );

  sw_process : process
  begin
    for i in 0 to 20 loop
      wait for 1 ns;
      test_sw <= not test_sw;
    end loop;
    wait for 100 ns;
  end process;

  rst_process : process
  begin
    wait;
  end process;

  clk_process : process
  begin
    wait for clk_period / 2;
    test_clk <= not test_clk;
  end process;

  kill_process : process
  begin
    wait for 10000 ns;
    assert false report "end of test" severity failure;
  end process;

end my_arch;

VHDL Files/src/ones_detector/db_sim.vcd
$date
  Sat Nov 25 15:07:39 2023
$end
$version
  GHDL v0
$end
$timescale
  1 fs
$end
$scope module standard $end
$upscope $end
$scope module std_logic_1164 $end
$upscope $end
$scope module numeric_std $end
$upscope $end
$scope module tb $end
$var reg 1 ! test_sw $end
$var reg 1 " test_rst $end
$var reg 1 # test_clk $end
$var reg 1 $ test_db $end
$scope module dut $end
$var reg 1 % sw $end
$var reg 1 & rst $end
$var reg 1 ' clk $end
$var reg 1 ( db $end
$comment r_pres is not handled $end
$comment r_next is not handled $end
$var reg 1 ) tick $end
$scope module tick_generator $end
$var reg 1 * clk $end
$var reg 1 + rst $end
$var reg 1 , en $end
$var reg 1 - tick $end
$var reg 2 . r_next[1:0] $end
$var reg 2 / r_pres[1:0] $end
$upscope $end
$upscope $end
$upscope $end
$enddefinitions $end
#0
1!
0"
0#
0$
1%
0&
0'
0(
0)
0*
0+
1,
0-
b01 .
b00 /
#1000000
0!
0%
#2000000
1!
1%
#3000000
0!
0%
#4000000
1!
1%
#5000000
0!
1#
0%
1'
1*
b10 .
b01 /
#6000000
1!
1%
#7000000
0!
0%
#8000000
1!
1%
#9000000
0!
0%
#10000000
1!
0#
1%
0'
0*
#11000000
0!
0%
#12000000
1!
1%
#13000000
0!
0%
#14000000
1!
1%
#15000000
0!
1#
0%
1'
1*
b11 .
b10 /
#16000000
1!
1%
#17000000
0!
0%
#18000000
1!
1%
#19000000
0!
0%
#20000000
1!
0#
1%
0'
0*
#21000000
0!
0%
#25000000
1#
1'
1)
1*
1-
b00 .
b11 /
#30000000
0#
0'
0*
#35000000
1#
1'
0)
1*
0-
b01 .
b00 /
#40000000
0#
0'
0*
#45000000
1#
1'
1*
b10 .
b01 /
#50000000
0#
0'
0*
#55000000
1#
1'
1*
b11 .
b10 /
#60000000
0#
0'
0*
#65000000
1#
1'
1)
1*
1-
b00 .
b11 /
#70000000
0#
0'
0*
#75000000
1#
1'
0)
1*
0-
b01 .
b00 /
#80000000
0#
0'
0*
#85000000
1#
1'
1*
b10 .
b01 /
#90000000
0#
0'
0*
#95000000
1#
1'
1*
b11 .
b10 /
#100000000
0#
0'
0*
#105000000
1#
1'
1)
1*
1-
b00 .
b11 /
#110000000
0#
0'
0*
#115000000
1#
1'
0)
1*
0-
b01 .
b00 /
#120000000
0#
0'
0*
#121000000
#122000000
1!
1%
#123000000
0!
0%
#124000000
1!
1%
#125000000
0!
1#
0%
1'
1*
b10 .
b01 /
#126000000
1!
1%
#127000000
0!
0%
#128000000
1!
1%
#129000000
0!
0%
#130000000
1!
0#
1%
0'
0*
#131000000
0!
0%
#132000000
1!
1%
#133000000
0!
0%
#134000000
1!
1%
#135000000
0!
1#
0%
1'
1*
b11 .
b10 /
#136000000
1!
1%
#137000000
0!
0%
#138000000
1!
1%
#139000000
0!
0%
#140000000
1!
0#
1%
0'
0*
#141000000
0!
0%
#142000000
1!
1%
#145000000
1#
1'
1)
1*
1-
b00 .
b11 /
#150000000
0#
0'
0*
#155000000
1#
1'
0)
1*
0-
b01 .
b00 /
#160000000
0#
0'
0*
#165000000
1#
1'
1*
b10 .
b01 /
#170000000
0#
0'
0*
#175000000
1#
1'
1*
b11 .
b10 /
#180000000
0#
0'
0*
#185000000
1#
1'
1)
1*
1-
b00 .
b11 /
#190000000
0#
0'
0*
#195000000
1#
1$
1'
1(
0)
1*
0-
b01 .
b00 /
#200000000
0#
0'
0*
#205000000
1#
1'
1*
b10 .
b01 /
#210000000
0#
0'
0*
#215000000
1#
1'
1*
b11 .
b10 /
#220000000
0#
0'
0*
#225000000
1#
1'
1(
1)
1*
1-
b00 .
b11 /
#230000000
0#
0'
0*
#235000000
1#
1'
1(
0)
1*
0-
b01 .
b00 /
#240000000
0#
0'
0*
#242000000
#243000000
0!
0%
1(
#244000000
1!
1%
1(
#245000000
0!
1#
0%
1'
1(
1*
b10 .
b01 /
#246000000
1!
1%
1(
#247000000
0!
0%
1(
#248000000
1!
1%
1(
#249000000
0!
0%
1(
#250000000
1!
0#
1%
0'
1(
0*
#251000000
0!
0%
1(
#252000000
1!
1%
1(
#253000000
0!
0%
1(
#254000000
1!
1%
1(
#255000000
0!
1#
0%
1'
1(
1*
b11 .
b10 /
#256000000
1!
1%
1(
#257000000
0!
0%
1(
#258000000
1!
1%
1(
#259000000
0!
0%
1(
#260000000
1!
0#
1%
0'
1(
0*
#261000000
0!
0%
1(
#262000000
1!
1%
1(
#263000000
0!
0%
1(
#265000000
1#
1'
1(
1)
1*
1-
b00 .
b11 /
#270000000
0#
0'
0*
#275000000
1#
1'
1(
0)
1*
0-
b01 .
b00 /
#280000000
0#
0'
0*
#285000000
1#
1'
1*
b10 .
b01 /
#290000000
0#
0'
0*
#295000000
1#
1'
1*
b11 .
b10 /
#300000000
0#
0'
0*
#305000000
1#
1'
1(
1)
1*
1-
b00 .
b11 /
#310000000
0#
0'
0*
#315000000
1#
0$
1'
0(
0)
1*
0-
b01 .
b00 /
#320000000
0#
0'
0*
#325000000
1#
1'
1*
b10 .
b01 /
#330000000
0#
0'
0*
#335000000
1#
1'
1*
b11 .
b10 /
#340000000
0#
0'
0*
#345000000
1#
1'
1)
1*
1-
b00 .
b11 /
#350000000
0#
0'
0*
#355000000
1#
1'
0)
1*
0-
b01 .
b00 /
#360000000
0#
0'
0*
#363000000
#364000000
1!
1%
#365000000
0!
1#
0%
1'
1*
b10 .
b01 /
#366000000
1!
1%
#367000000
0!
0%
#368000000
1!
1%
#369000000
0!
0%
#370000000
1!
0#
1%
0'
0*
#371000000
0!
0%
#372000000
1!
1%
#373000000
0!
0%
#374000000
1!
1%
#375000000
0!
1#
0%
1'
1*
b11 .
b10 /
#376000000
1!
1%
#377000000
0!
0%
#378000000
1!
1%
#379000000
0!
0%
#380000000
1!
0#
1%
0'
0*
#381000000
0!
0%
#382000000
1!
1%
#383000000
0!
0%
#384000000
1!
1%
#385000000
1#
1'
1)
1*
1-
b00 .
b11 /
#390000000
0#
0'
0*
#395000000
1#
1'
0)
1*
0-
b01 .
b00 /
#400000000
0#
0'
0*
#405000000
1#
1'
1*
b10 .
b01 /
#410000000
0#
0'
0*
#415000000
1#
1'
1*
b11 .
b10 /
#420000000
0#
0'
0*
#425000000
1#
1'
1)
1*
1-
b00 .
b11 /
#430000000
0#
0'
0*
#435000000
1#
1$
1'
1(
0)
1*
0-
b01 .
b00 /
#440000000
0#
0'
0*
#445000000
1#
1'
1*
b10 .
b01 /
#450000000
0#
0'
0*
#455000000
1#
1'
1*
b11 .
b10 /
#460000000
0#
0'
0*
#465000000
1#
1'
1(
1)
1*
1-
b00 .
b11 /
#470000000
0#
0'
0*
#475000000
1#
1'
1(
0)
1*
0-
b01 .
b00 /
#480000000
0#
0'
0*
#484000000
#485000000
0!
1#
0%
1'
1(
1*
b10 .
b01 /
#486000000
1!
1%
1(
#487000000
0!
0%
1(
#488000000
1!
1%
1(
#489000000
0!
0%
1(
#490000000
1!
0#
1%
0'
1(
0*
#491000000
0!
0%
1(
#492000000
1!
1%
1(
#493000000
0!
0%
1(
#494000000
1!
1%
1(
#495000000
0!
1#
0%
1'
1(
1*
b11 .
b10 /
#496000000
1!
1%
1(
#497000000
0!
0%
1(
#498000000
1!
1%
1(
#499000000
0!
0%
1(
#500000000
1!
0#
1%
0'
1(
0*
#501000000
0!
0%
1(
#502000000
1!
1%
1(
#503000000
0!
0%
1(
#504000000
1!
1%
1(
#505000000
0!
1#
0%
1'
1(
1)
1*
1-
b00 .
b11 /
#510000000
0#
0'
0*
#515000000
1#
1'
1(
0)
1*
0-
b01 .
b00 /
#520000000
0#
0'
0*
#525000000
1#
1'
1*
b10 .
b01 /
#530000000
0#
0'
0*
#535000000
1#
1'
1*
b11 .
b10 /
#540000000
0#
0'
0*
#545000000
1#
1'
1(
1)
1*
1-
b00 .
b11 /
#550000000
0#
0'
0*
#555000000
1#
1'
1(
0)
1*
0-
b01 .
b00 /
#560000000
0#
0'
0*
#565000000
1#
1'
1*
b10 .
b01 /
#570000000
0#
0'
0*
#575000000
1#
1'
1*
b11 .
b10 /
#580000000
0#
0'
0*
#585000000
1#
1'
1(
1)
1*
1-
b00 .
b11 /
#590000000
0#
0'
0*
#595000000
1#
0$
1'
0(
0)
1*
0-
b01 .
b00 /
#600000000
0#
0'
0*
#605000000
1#
1'
1*
b10 .
b01 /
#606000000
1!
1%
#607000000
0!
0%
#608000000
1!
1%
#609000000
0!
0%
#610000000
1!
0#
1%
0'
0*
#611000000
0!
0%
#612000000
1!
1%
#613000000
0!
0%
#614000000
1!
1%
#615000000
0!
1#
0%
1'
1*
b11 .
b10 /
#616000000
1!
1%
#617000000
0!
0%
#618000000
1!
1%
#619000000
0!
0%
#620000000
1!
0#
1%
0'
0*
#621000000
0!
0%
#622000000
1!
1%
#623000000
0!
0%
#624000000
1!
1%
#625000000
0!
1#
0%
1'
1)
1*
1-
b00 .
b11 /
#626000000
1!
1%
#630000000
0#
0'
0*
#635000000
1#
1'
0)
1*
0-
b01 .
b00 /
#640000000
0#
0'
0*
#645000000
1#
1'
1*
b10 .
b01 /
#650000000
0#
0'
0*
#655000000
1#
1'
1*
b11 .
b10 /
#660000000
0#
0'
0*
#665000000
1#
1'
1)
1*
1-
b00 .
b11 /
#670000000
0#
0'
0*
#675000000
1#
1$
1'
1(
0)
1*
0-
b01 .
b00 /
#680000000
0#
0'
0*
#685000000
1#
1'
1*
b10 .
b01 /
#690000000
0#
0'
0*
#695000000
1#
1'
1*
b11 .
b10 /
#700000000
0#
0'
0*
#705000000
1#
1'
1(
1)
1*
1-
b00 .
b11 /
#710000000
0#
0'
0*
#715000000
1#
1'
1(
0)
1*
0-
b01 .
b00 /
#720000000
0#
0'
0*
#725000000
1#
1'
1*
b10 .
b01 /
#726000000
#727000000
0!
0%
1(
#728000000
1!
1%
1(
#729000000
0!
0%
1(
#730000000
1!
0#
1%
0'
1(
0*
#731000000
0!
0%
1(
#732000000
1!
1%
1(
#733000000
0!
0%
1(
#734000000
1!
1%
1(
#735000000
0!
1#
0%
1'
1(
1*
b11 .
b10 /
#736000000
1!
1%
1(
#737000000
0!
0%
1(
#738000000
1!
1%
1(
#739000000
0!
0%
1(
#740000000
1!
0#
1%
0'
1(
0*
#741000000
0!
0%
1(
#742000000
1!
1%
1(
#743000000
0!
0%
1(
#744000000
1!
1%
1(
#745000000
0!
1#
0%
1'
1(
1)
1*
1-
b00 .
b11 /
#746000000
1!
1%
1(
#747000000
0!
0%
1(
#750000000
0#
0'
0*
#755000000
1#
1'
1(
0)
1*
0-
b01 .
b00 /
#760000000
0#
0'
0*
#765000000
1#
1'
1*
b10 .
b01 /
#770000000
0#
0'
0*
#775000000
1#
1'
1*
b11 .
b10 /
#780000000
0#
0'
0*
#785000000
1#
1'
1(
1)
1*
1-
b00 .
b11 /
#790000000
0#
0'
0*
#795000000
1#
1'
1(
0)
1*
0-
b01 .
b00 /
#800000000
0#
0'
0*
#805000000
1#
1'
1*
b10 .
b01 /
#810000000
0#
0'
0*
#815000000
1#
1'
1*
b11 .
b10 /
#820000000
0#
0'
0*
#825000000
1#
1'
1(
1)
1*
1-
b00 .
b11 /
#830000000
0#
0'
0*
#835000000
1#
0$
1'
0(
0)
1*
0-
b01 .
b00 /
#840000000
0#
0'
0*
#845000000
1#
1'
1*
b10 .
b01 /
#847000000
#848000000
1!
1%
#849000000
0!
0%
#850000000
1!
0#
1%
0'
0*
#851000000
0!
0%
#852000000
1!
1%
#853000000
0!
0%
#854000000
1!
1%
#855000000
0!
1#
0%
1'
1*
b11 .
b10 /
#856000000
1!
1%
#857000000
0!
0%
#858000000
1!
1%
#859000000
0!
0%
#860000000
1!
0#
1%
0'
0*
#861000000
0!
0%
#862000000
1!
1%
#863000000
0!
0%
#864000000
1!
1%
#865000000
0!
1#
0%
1'
1)
1*
1-
b00 .
b11 /
#866000000
1!
1%
#867000000
0!
0%
#868000000
1!
1%
#870000000
0#
0'
0*
#875000000
1#
1'
0)
1*
0-
b01 .
b00 /
#880000000
0#
0'
0*
#885000000
1#
1'
1*
b10 .
b01 /
#890000000
0#
0'
0*
#895000000
1#
1'
1*
b11 .
b10 /
#900000000
0#
0'
0*
#905000000
1#
1'
1)
1*
1-
b00 .
b11 /
#910000000
0#
0'
0*
#915000000
1#
1$
1'
1(
0)
1*
0-
b01 .
b00 /
#920000000
0#
0'
0*
#925000000
1#
1'
1*
b10 .
b01 /
#930000000
0#
0'
0*
#935000000
1#
1'
1*
b11 .
b10 /
#940000000
0#
0'
0*
#945000000
1#
1'
1(
1)
1*
1-
b00 .
b11 /
#950000000
0#
0'
0*
#955000000
1#
1'
1(
0)
1*
0-
b01 .
b00 /
#960000000
0#
0'
0*
#965000000
1#
1'
1*
b10 .
b01 /
#968000000
#969000000
0!
0%
1(
#970000000
1!
0#
1%
0'
1(
0*
#971000000
0!
0%
1(
#972000000
1!
1%
1(
#973000000
0!
0%
1(
#974000000
1!
1%
1(
#975000000
0!
1#
0%
1'
1(
1*
b11 .
b10 /
#976000000
1!
1%
1(
#977000000
0!
0%
1(
#978000000
1!
1%
1(
#979000000
0!
0%
1(
#980000000
1!
0#
1%
0'
1(
0*
#981000000
0!
0%
1(
#982000000
1!
1%
1(
#983000000
0!
0%
1(
#984000000
1!
1%
1(
#985000000
0!
1#
0%
1'
1(
1)
1*
1-
b00 .
b11 /
#986000000
1!
1%
1(
#987000000
0!
0%
1(
#988000000
1!
1%
1(
#989000000
0!
0%
1(
#990000000
0#
0'
0*
#995000000
1#
1'
1(
0)
1*
0-
b01 .
b00 /
#1000000000
0#
0'
0*
#1005000000
1#
1'
1*
b10 .
b01 /
#1010000000
0#
0'
0*
#1015000000
1#
1'
1*
b11 .
b10 /
#1020000000
0#
0'
0*
#1025000000
1#
1'
1(
1)
1*
1-
b00 .
b11 /
#1030000000
0#
0'
0*
#1035000000
1#
1'
1(
0)
1*
0-
b01 .
b00 /
#1040000000
0#
0'
0*
#1045000000
1#
1'
1*
b10 .
b01 /
#1050000000
0#
0'
0*
#1055000000
1#
1'
1*
b11 .
b10 /
#1060000000
0#
0'
0*
#1065000000
1#
1'
1(
1)
1*
1-
b00 .
b11 /
#1070000000
0#
0'
0*
#1075000000
1#
0$
1'
0(
0)
1*
0-
b01 .
b00 /
#1080000000
0#
0'
0*
#1085000000
1#
1'
1*
b10 .
b01 /
#1089000000
#1090000000
1!
0#
1%
0'
0*
#1091000000
0!
0%
#1092000000
1!
1%
#1093000000
0!
0%
#1094000000
1!
1%
#1095000000
0!
1#
0%
1'
1*
b11 .
b10 /
#1096000000
1!
1%
#1097000000
0!
0%
#1098000000
1!
1%
#1099000000
0!
0%
#1100000000
1!
0#
1%
0'
0*
#1101000000
0!
0%
#1102000000
1!
1%
#1103000000
0!
0%
#1104000000
1!
1%
#1105000000
0!
1#
0%
1'
1)
1*
1-
b00 .
b11 /
#1106000000
1!
1%
#1107000000
0!
0%
#1108000000
1!
1%
#1109000000
0!
0%
#1110000000
1!
0#
1%
0'
0*
#1115000000
1#
1'
0)
1*
0-
b01 .
b00 /
#1120000000
0#
0'
0*
#1125000000
1#
1'
1*
b10 .
b01 /
#1130000000
0#
0'
0*
#1135000000
1#
1'
1*
b11 .
b10 /
#1140000000
0#
0'
0*
#1145000000
1#
1'
1)
1*
1-
b00 .
b11 /
#1150000000
0#
0'
0*
#1155000000
1#
1$
1'
1(
0)
1*
0-
b01 .
b00 /
#1160000000
0#
0'
0*
#1165000000
1#
1'
1*
b10 .
b01 /
#1170000000
0#
0'
0*
#1175000000
1#
1'
1*
b11 .
b10 /
#1180000000
0#
0'
0*
#1185000000
1#
1'
1(
1)
1*
1-
b00 .
b11 /
#1190000000
0#
0'
0*
#1195000000
1#
1'
1(
0)
1*
0-
b01 .
b00 /
#1200000000
0#
0'
0*
#1205000000
1#
1'
1*
b10 .
b01 /
#1210000000
0#
0'
0*
#1211000000
0!
0%
1(
#1212000000
1!
1%
1(
#1213000000
0!
0%
1(
#1214000000
1!
1%
1(
#1215000000
0!
1#
0%
1'
1(
1*
b11 .
b10 /
#1216000000
1!
1%
1(
#1217000000
0!
0%
1(
#1218000000
1!
1%
1(
#1219000000
0!
0%
1(
#1220000000
1!
0#
1%
0'
1(
0*
#1221000000
0!
0%
1(
#1222000000
1!
1%
1(
#1223000000
0!
0%
1(
#1224000000
1!
1%
1(
#1225000000
0!
1#
0%
1'
1(
1)
1*
1-
b00 .
b11 /
#1226000000
1!
1%
1(
#1227000000
0!
0%
1(
#1228000000
1!
1%
1(
#1229000000
0!
0%
1(
#1230000000
1!
0#
1%
0'
1(
0*
#1231000000
0!
0%
1(
#1235000000
1#
1'
1(
0)
1*
0-
b01 .
b00 /
#1240000000
0#
0'
0*
#1245000000
1#
1'
1*
b10 .
b01 /
#1250000000
0#
0'
0*
#1255000000
1#
1'
1*
b11 .
b10 /
#1260000000
0#
0'
0*
#1265000000
1#
1'
1(
1)
1*
1-
b00 .
b11 /
#1270000000
0#
0'
0*
#1275000000
1#
1'
1(
0)
1*
0-
b01 .
b00 /
#1280000000
0#
0'
0*
#1285000000
1#
1'
1*
b10 .
b01 /
#1290000000
0#
0'
0*
#1295000000
1#
1'
1*
b11 .
b10 /
#1300000000
0#
0'
0*
#1305000000
1#
1'
1(
1)
1*
1-
b00 .
b11 /
#1310000000
0#
0'
0*
#1315000000
1#
0$
1'
0(
0)
1*
0-
b01 .
b00 /
#1320000000
0#
0'
0*
#1325000000
1#
1'
1*
b10 .
b01 /
#1330000000
0#
0'
0*
#1331000000
#1332000000
1!
1%
#1333000000
0!
0%
#1334000000
1!
1%
#1335000000
0!
1#
0%
1'
1*
b11 .
b10 /
#1336000000
1!
1%
#1337000000
0!
0%
#1338000000
1!
1%
#1339000000
0!
0%
#1340000000
1!
0#
1%
0'
0*
#1341000000
0!
0%
#1342000000
1!
1%
#1343000000
0!
0%
#1344000000
1!
1%
#1345000000
0!
1#
0%
1'
1)
1*
1-
b00 .
b11 /
#1346000000
1!
1%
#1347000000
0!
0%
#1348000000
1!
1%
#1349000000
0!
0%
#1350000000
1!
0#
1%
0'
0*
#1351000000
0!
0%
#1352000000
1!
1%
#1355000000
1#
1'
0)
1*
0-
b01 .
b00 /
#1360000000
0#
0'
0*
#1365000000
1#
1'
1*
b10 .
b01 /
#1370000000
0#
0'
0*
#1375000000
1#
1'
1*
b11 .
b10 /
#1380000000
0#
0'
0*
#1385000000
1#
1'
1)
1*
1-
b00 .
b11 /
#1390000000
0#
0'
0*
#1395000000
1#
1$
1'
1(
0)
1*
0-
b01 .
b00 /
#1400000000
0#
0'
0*
#1405000000
1#
1'
1*
b10 .
b01 /
#1410000000
0#
0'
0*
#1415000000
1#
1'
1*
b11 .
b10 /
#1420000000
0#
0'
0*
#1425000000
1#
1'
1(
1)
1*
1-
b00 .
b11 /
#1430000000
0#
0'
0*
#1435000000
1#
1'
1(
0)
1*
0-
b01 .
b00 /
#1440000000
0#
0'
0*
#1445000000
1#
1'
1*
b10 .
b01 /
#1450000000
0#
0'
0*
#1452000000
#1453000000
0!
0%
1(
#1454000000
1!
1%
1(
#1455000000
0!
1#
0%
1'
1(
1*
b11 .
b10 /
#1456000000
1!
1%
1(
#1457000000
0!
0%
1(
#1458000000
1!
1%
1(
#1459000000
0!
0%
1(
#1460000000
1!
0#
1%
0'
1(
0*
#1461000000
0!
0%
1(
#1462000000
1!
1%
1(
#1463000000
0!
0%
1(
#1464000000
1!
1%
1(
#1465000000
0!
1#
0%
1'
1(
1)
1*
1-
b00 .
b11 /
#1466000000
1!
1%
1(
#1467000000
0!
0%
1(
#1468000000
1!
1%
1(
#1469000000
0!
0%
1(
#1470000000
1!
0#
1%
0'
1(
0*
#1471000000
0!
0%
1(
#1472000000
1!
1%
1(
#1473000000
0!
0%
1(
#1475000000
1#
1'
1(
0)
1*
0-
b01 .
b00 /
#1480000000
0#
0'
0*
#1485000000
1#
1'
1*
b10 .
b01 /
#1490000000
0#
0'
0*
#1495000000
1#
1'
1*
b11 .
b10 /
#1500000000
0#
0'
0*
#1505000000
1#
1'
1(
1)
1*
1-
b00 .
b11 /
#1510000000
0#
0'
0*
#1515000000
1#
1'
1(
0)
1*
0-
b01 .
b00 /
#1520000000
0#
0'
0*
#1525000000
1#
1'
1*
b10 .
b01 /
#1530000000
0#
0'
0*
#1535000000
1#
1'
1*
b11 .
b10 /
#1540000000
0#
0'
0*
#1545000000
1#
1'
1(
1)
1*
1-
b00 .
b11 /
#1550000000
0#
0'
0*
#1555000000
1#
0$
1'
0(
0)
1*
0-
b01 .
b00 /
#1560000000
0#
0'
0*
#1565000000
1#
1'
1*
b10 .
b01 /
#1570000000
0#
0'
0*
#1573000000
#1574000000
1!
1%
#1575000000
0!
1#
0%
1'
1*
b11 .
b10 /
#1576000000
1!
1%
#1577000000
0!
0%
#1578000000
1!
1%
#1579000000
0!
0%
#1580000000
1!
0#
1%
0'
0*
#1581000000
0!
0%
#1582000000
1!
1%
#1583000000
0!
0%
#1584000000
1!
1%
#1585000000
0!
1#
0%
1'
1)
1*
1-
b00 .
b11 /
#1586000000
1!
1%
#1587000000
0!
0%
#1588000000
1!
1%
#1589000000
0!
0%
#1590000000
1!
0#
1%
0'
0*
#1591000000
0!
0%
#1592000000
1!
1%
#1593000000
0!
0%
#1594000000
1!
1%
#1595000000
1#
1'
0)
1*
0-
b01 .
b00 /
#1600000000
0#
0'
0*
#1605000000
1#
1'
1*
b10 .
b01 /
#1610000000
0#
0'
0*
#1615000000
1#
1'
1*
b11 .
b10 /
#1620000000
0#
0'
0*
#1625000000
1#
1'
1)
1*
1-
b00 .
b11 /
#1630000000
0#
0'
0*
#1635000000
1#
1$
1'
1(
0)
1*
0-
b01 .
b00 /
#1640000000
0#
0'
0*
#1645000000
1#
1'
1*
b10 .
b01 /
#1650000000
0#
0'
0*
#1655000000
1#
1'
1*
b11 .
b10 /
#1660000000
0#
0'
0*
#1665000000
1#
1'
1(
1)
1*
1-
b00 .
b11 /
#1670000000
0#
0'
0*
#1675000000
1#
1'
1(
0)
1*
0-
b01 .
b00 /
#1680000000
0#
0'
0*
#1685000000
1#
1'
1*
b10 .
b01 /
#1690000000
0#
0'
0*
#1694000000
#1695000000
0!
1#
0%
1'
1(
1*
b11 .
b10 /
#1696000000
1!
1%
1(
#1697000000
0!
0%
1(
#1698000000
1!
1%
1(
#1699000000
0!
0%
1(
#1700000000
1!
0#
1%
0'
1(
0*
#1701000000
0!
0%
1(
#1702000000
1!
1%
1(
#1703000000
0!
0%
1(
#1704000000
1!
1%
1(
#1705000000
0!
1#
0%
1'
1(
1)
1*
1-
b00 .
b11 /
#1706000000
1!
1%
1(
#1707000000
0!
0%
1(
#1708000000
1!
1%
1(
#1709000000
0!
0%
1(
#1710000000
1!
0#
1%
0'
1(
0*
#1711000000
0!
0%
1(
#1712000000
1!
1%
1(
#1713000000
0!
0%
1(
#1714000000
1!
1%
1(
#1715000000
0!
1#
0%
1'
1(
0)
1*
0-
b01 .
b00 /
#1720000000
0#
0'
0*
#1725000000
1#
1'
1(
1*
b10 .
b01 /
#1730000000
0#
0'
0*
#1735000000
1#
1'
1*
b11 .
b10 /
#1740000000
0#
0'
0*
#1745000000
1#
1'
1(
1)
1*
1-
b00 .
b11 /
#1750000000
0#
0'
0*
#1755000000
1#
1'
1(
0)
1*
0-
b01 .
b00 /
#1760000000
0#
0'
0*
#1765000000
1#
1'
1*
b10 .
b01 /
#1770000000
0#
0'
0*
#1775000000
1#
1'
1*
b11 .
b10 /
#1780000000
0#
0'
0*
#1785000000
1#
1'
1(
1)
1*
1-
b00 .
b11 /
#1790000000
0#
0'
0*
#1795000000
1#
0$
1'
0(
0)
1*
0-
b01 .
b00 /
#1800000000
0#
0'
0*
#1805000000
1#
1'
1*
b10 .
b01 /
#1810000000
0#
0'
0*
#1815000000
1#
1'
1*
b11 .
b10 /
#1816000000
1!
1%
#1817000000
0!
0%
#1818000000
1!
1%
#1819000000
0!
0%
#1820000000
1!
0#
1%
0'
0*
#1821000000
0!
0%
#1822000000
1!
1%
#1823000000
0!
0%
#1824000000
1!
1%
#1825000000
0!
1#
0%
1'
1)
1*
1-
b00 .
b11 /
#1826000000
1!
1%
#1827000000
0!
0%
#1828000000
1!
1%
#1829000000
0!
0%
#1830000000
1!
0#
1%
0'
0*
#1831000000
0!
0%
#1832000000
1!
1%
#1833000000
0!
0%
#1834000000
1!
1%
#1835000000
0!
1#
0%
1'
0)
1*
0-
b01 .
b00 /
#1836000000
1!
1%
#1840000000
0#
0'
0*
#1845000000
1#
1'
1*
b10 .
b01 /
#1850000000
0#
0'
0*
#1855000000
1#
1'
1*
b11 .
b10 /
#1860000000
0#
0'
0*
#1865000000
1#
1'
1)
1*
1-
b00 .
b11 /
#1870000000
0#
0'
0*
#1875000000
1#
1$
1'
1(
0)
1*
0-
b01 .
b00 /
#1880000000
0#
0'
0*
#1885000000
1#
1'
1*
b10 .
b01 /
#1890000000
0#
0'
0*
#1895000000
1#
1'
1*
b11 .
b10 /
#1900000000
0#
0'
0*
#1905000000
1#
1'
1(
1)
1*
1-
b00 .
b11 /
#1910000000
0#
0'
0*
#1915000000
1#
1'
1(
0)
1*
0-
b01 .
b00 /
#1920000000
0#
0'
0*
#1925000000
1#
1'
1*
b10 .
b01 /
#1930000000
0#
0'
0*
#1935000000
1#
1'
1*
b11 .
b10 /
#1936000000
#1937000000
0!
0%
1(
#1938000000
1!
1%
1(
#1939000000
0!
0%
1(
#1940000000
1!
0#
1%
0'
1(
0*
#1941000000
0!
0%
1(
#1942000000
1!
1%
1(
#1943000000
0!
0%
1(
#1944000000
1!
1%
1(
#1945000000
0!
1#
0%
1'
1(
1)
1*
1-
b00 .
b11 /
#1946000000
1!
1%
1(
#1947000000
0!
0%
1(
#1948000000
1!
1%
1(
#1949000000
0!
0%
1(
#1950000000
1!
0#
1%
0'
1(
0*
#1951000000
0!
0%
1(
#1952000000
1!
1%
1(
#1953000000
0!
0%
1(
#1954000000
1!
1%
1(
#1955000000
0!
1#
0%
1'
1(
0)
1*
0-
b01 .
b00 /
#1956000000
1!
1%
1(
#1957000000
0!
0%
1(
#1960000000
0#
0'
0*
#1965000000
1#
1'
1(
1*
b10 .
b01 /
#1970000000
0#
0'
0*
#1975000000
1#
1'
1*
b11 .
b10 /
#1980000000
0#
0'
0*
#1985000000
1#
1'
1(
1)
1*
1-
b00 .
b11 /
