VHDL Files/src/stoplight/control.vhd
library ieee;
use ieee.std_logic_1164.all;
use ieee.numeric_std.all;

entity control is
  port(clk       : in  std_logic := '0';
       rst       : in  std_logic := '0';
       car       : in  std_logic := '0';
       tick_ten  : in  std_logic := '0';
       tick_four : in  std_logic := '0';
       count_en  : out std_logic := '0';
       count_clr : out std_logic := '0';
       state     : out std_logic_vector (1 downto 0) := "00";
       main      : out std_logic_vector (2 downto 0) := "100";
       side      : out std_logic_vector (2 downto 0) := "001");
end control;

architecture my_arch of control is
  type state_type is (mg_sr, my_sr, mr_sg, mr_sy);
  signal r_pres, r_next : state_type;
  constant RED    : std_logic_vector(2 downto 0) := "100";
  constant YELLOW : std_logic_vector(2 downto 0) := "010";
  constant GREEN  : std_logic_vector(2 downto 0) := "001";
begin

-- register stuff
  process(clk, rst)
  begin
    if(rst = '1') then
      r_pres <= mg_sr;
    elsif(rising_edge(clk)) then
      r_pres <= r_next;
    end if;
  end process;

  -- state machine
  process(r_pres, car, tick_ten, tick_four)
  begin
    -- DEFAULTS
    count_en  <= '1';
    count_clr <= '0';
    r_next <= r_pres; --??

    case r_pres is

      when mg_sr =>
        main <= GREEN;
        side <= RED;
        state <= "00";
        if(tick_ten = '1') then
          if(car = '1') then
            count_clr <= '1';
            r_next <= my_sr;
          else
            count_en <= '0';
          end if;
        end if;

      when my_sr =>
        main <= YELLOW;
        side <= RED;
        state <= "01";
        if(tick_four = '1') then
          count_clr <= '1';
          r_next <= mr_sg;
        end if;

      when mr_sg =>
        main <= RED;
        side <= GREEN;
        state <= "10";
        if(car = '1') then
          if(tick_ten = '1') then
            count_clr <= '1';
            r_next <= mr_sy;
          end if;
        else
          count_clr <= '1';
          r_next <= mr_sy;
        end if;

      when mr_sy =>
        main <= RED;
        side <= YELLOW;
        state <= "11";
        if(tick_four = '1') then
          count_clr <= '1';
          r_next <= mg_sr;
        end if;

    end case;
  end process;

end my_arch;

VHDL Files/src/stoplight/ctrstg.vhd
library ieee;
use ieee.std_logic_1164.all;
use ieee.numeric_std.all;

entity ctrstg is
  generic(max   : integer  := 9;
          width : integer  := 4 );
  port   (clr   : in  std_logic := '0';
          en    : in  std_logic := '0';
          clk   : in  std_logic := '0';
          tick  : out std_logic := '0';
          cnt   : out std_logic_vector(width-1 downto 0) := (others => '0'));
end ctrstg;

architecture my_arch of ctrstg is

  signal stg_reg, stg_next : unsigned(width-1 downto 0) := (others => '0');

begin

--SEQUENTIAL PORTION
  process(clr, clk)
  begin
    if clr = '1' and rising_edge(clk) then
      stg_reg <= (others => '0');
    elsif rising_edge(clk) then
      stg_reg <= stg_next;
    end if;
  end process;

--COMBINATIONAL PORTION
  stg_next <=(others=>'0')when(((stg_reg=max) and (en='1')) or clr = '1')  else
             stg_reg + 1 when en = '1' else
             stg_reg;

  tick <= '1' when stg_reg = max else '0';

  cnt <= std_logic_vector(stg_reg);

end my_arch;

VHDL Files/src/stoplight/counter.vhd
library ieee;
use ieee.STD_LOGIC_1164.all;
use ieee.numeric_std.all;

entity counter is
  port (clr        : in  std_logic := '0';
        en         : in  std_logic := '0';
        clk        : in  std_logic := '0';
        state      : in  std_logic_vector(1 downto 0) := "00";
        tick_four  : out std_logic := '0';
        tick_ten   : out std_logic := '0';
        cnt        : out std_logic_vector(3 downto 0) := "0000");
end counter;

architecture my_arch of counter is

  signal tick_sec : std_logic := '0';
  signal count_four, count_ten : std_logic_vector(3 downto 0):=(others => '0');

begin

  one_sec_counter : entity work.ctrstg(my_arch)
    generic map(max   => 10000000,  --TODO::CHANGE TO 8 FOR TESTBENCH
                width => 27)        --TODO::CHANGE TO 4 FOR TESTBENCH
    port map (clr  => clr,
              en   => en,
              clk  => clk,
              tick => tick_sec,
              cnt  => open );

  four_sec_counter : entity work.ctrstg(my_arch)
    generic map(max   => 4,
                width => 4)
    port map (clr  => clr,
              en   => tick_sec,
              clk  => clk,
              tick => tick_four,
              cnt  => count_four );

  ten_sec_counter : entity work.ctrstg(my_arch)
    generic map(max   => 10,
                width => 4)
    port map (clr  => clr,
              en   => tick_sec,
              clk  => clk,
              tick => tick_ten,
              cnt  => count_ten);

  with state select cnt <=
    count_four when "01",
    count_four when "11",
    count_ten  when others;

end my_arch;

VHDL Files/src/stoplight/counter_tb.vhd
library ieee;
use ieee.STD_LOGIC_1164.all;
use ieee.numeric_std.all;

entity stoplight_tb is
end stoplight_tb;

architecture tb of stoplight_tb is

  --COUNTER SIGNALS
  signal clk, t_4, t_10 : std_logic := '0';
  signal state : std_logic_vector(1 downto 0) := "00";
  signal cnt  : std_logic_vector(3 downto 0) := "0000";

  --CONTROL SIGNALS
  signal rst, car, count_en, count_clr : std_logic := '0';
  signal main, side : std_logic_vector( 2 downto 0 );

  constant clk_period : time := 10 ns;

begin

  counter : entity work.counter(my_arch)
    port map(clr       => count_clr,
             en        => count_en,
             clk       => clk,
             state     => state,
             tick_four => t_4,
             tick_ten  => t_10,
             cnt       => cnt);

  control : entity work.control(my_arch)
    port map(clk       => clk,
             rst       => rst,
             car       => car,
             tick_ten  => t_10,
             tick_four => t_4,
             count_en  => count_en,
             count_clr => count_clr,
             state     => state,
             main      => main,
             side      => side );

  clk_process : process
  begin
    wait for clk_period / 2;
    clk <= not clk;
  end process;

  rst_process : process
  begin
    rst <= '0';
    wait;
  end process;

  car_process : process
  begin
    wait for clk_period * 100;
    car <= not car;
  end process;

  termination : process
  begin
    wait for clk_period * 10000;
    assert false report "end of test" severity failure;
  end process;
end tb;

VHDL Files/src/stoplight/sim.vcd
$date
  Thu Nov 30 16:02:21 2023
$end
$version
  GHDL v0
$end
$timescale
  1 fs
$end
$scope module standard $end
$upscope $end
$scope module std_logic_1164 $end
$upscope $end
$scope module numeric_std $end
$upscope $end
$scope module stoplight_tb $end
$var reg 1 ! clk $end
$var reg 1 " t_4 $end
$var reg 1 # t_10 $end
$var reg 2 $ state[1:0] $end
$var reg 4 % cnt[3:0] $end
$var reg 1 & rst $end
$var reg 1 ' car $end
$var reg 1 ( count_en $end
$var reg 1 ) count_clr $end
$var reg 3 * main[2:0] $end
$var reg 3 + side[2:0] $end
$scope module counter $end
$var reg 1 , clr $end
$var reg 1 - en $end
$var reg 1 . clk $end
$var reg 2 / state[1:0] $end
$var reg 1 0 tick_four $end
$var reg 1 1 tick_ten $end
$var reg 4 2 cnt[3:0] $end
$var reg 1 3 tick_sec $end
$var reg 4 4 count_four[3:0] $end
$var reg 4 5 count_ten[3:0] $end
$scope module one_sec_counter $end
$var reg 1 6 clr $end
$var reg 1 7 en $end
$var reg 1 8 clk $end
$var reg 1 9 tick $end
$var reg 4 : cnt[3:0] $end
$var reg 4 ; stg_reg[3:0] $end
$var reg 4 < stg_next[3:0] $end
$upscope $end
$scope module four_sec_counter $end
$var reg 1 = clr $end
$var reg 1 > en $end
$var reg 1 ? clk $end
$var reg 1 @ tick $end
$var reg 4 A cnt[3:0] $end
$var reg 4 B stg_reg[3:0] $end
$var reg 4 C stg_next[3:0] $end
$upscope $end
$scope module ten_sec_counter $end
$var reg 1 D clr $end
$var reg 1 E en $end
$var reg 1 F clk $end
$var reg 1 G tick $end
$var reg 4 H cnt[3:0] $end
$var reg 4 I stg_reg[3:0] $end
$var reg 4 J stg_next[3:0] $end
$upscope $end
$upscope $end
$scope module control $end
$var reg 1 K clk $end
$var reg 1 L rst $end
$var reg 1 M car $end
$var reg 1 N tick_ten $end
$var reg 1 O tick_four $end
$var reg 1 P count_en $end
$var reg 1 Q count_clr $end
$var reg 2 R state[1:0] $end
$var reg 3 S main[2:0] $end
$var reg 3 T side[2:0] $end
$comment r_pres is not handled $end
$comment r_next is not handled $end
$upscope $end
$upscope $end
$enddefinitions $end
#0
0!
0"
0#
b00 $
b0000 %
0&
0'
1(
0)
b001 *
b100 +
0,
1-
0.
b00 /
00
01
b0000 2
03
b0000 4
b0000 5
06
17
08
09
b0000 :
b0000 ;
b0001 <
0=
0>
0?
0@
b0000 A
b0000 B
b0000 C
0D
0E
0F
0G
b0000 H
b0000 I
b0000 J
0K
0L
0M
0N
0O
1P
0Q
b00 R
b001 S
b100 T
#5000000
1!
1.
18
b0001 :
b0001 ;
b0010 <
1?
1F
1K
#10000000
0!
0.
08
0?
0F
0K
#15000000
1!
1.
18
b0010 :
b0010 ;
b0011 <
1?
1F
1K
#20000000
0!
0.
08
0?
0F
0K
#25000000
1!
1.
18
b0011 :
b0011 ;
b0100 <
1?
1F
1K
#30000000
0!
0.
08
0?
0F
0K
#35000000
1!
1.
18
b0100 :
b0100 ;
b0101 <
1?
1F
1K
#40000000
0!
0.
08
0?
0F
0K
#45000000
1!
1.
18
b0101 :
b0101 ;
b0110 <
1?
1F
1K
#50000000
0!
0.
08
0?
0F
0K
#55000000
1!
1.
18
b0110 :
b0110 ;
b0111 <
1?
1F
1K
#60000000
0!
0.
08
0?
0F
0K
#65000000
1!
1.
18
b0111 :
b0111 ;
b1000 <
1?
1F
1K
#70000000
0!
0.
08
0?
0F
0K
#75000000
1!
1.
13
18
19
b1000 :
b1000 ;
b0000 <
1>
1?
b0001 C
1E
1F
b0001 J
1K
#80000000
0!
0.
08
0?
0F
0K
#85000000
1!
b0001 %
1.
b0001 2
03
b0001 4
b0001 5
18
09
b0000 :
b0000 ;
b0001 <
0>
1?
b0001 A
b0001 B
b0001 C
0E
1F
b0001 H
b0001 I
b0001 J
1K
#90000000
0!
0.
08
0?
0F
0K
#95000000
1!
1.
18
b0001 :
b0001 ;
b0010 <
1?
1F
1K
#100000000
0!
0.
08
0?
0F
0K
#105000000
1!
1.
18
b0010 :
b0010 ;
b0011 <
1?
1F
1K
#110000000
0!
0.
08
0?
0F
0K
#115000000
1!
1.
18
b0011 :
b0011 ;
b0100 <
1?
1F
1K
#120000000
0!
0.
08
0?
0F
0K
#125000000
1!
1.
18
b0100 :
b0100 ;
b0101 <
1?
1F
1K
#130000000
0!
0.
08
0?
0F
0K
#135000000
1!
1.
18
b0101 :
b0101 ;
b0110 <
1?
1F
1K
#140000000
0!
0.
08
0?
0F
0K
#145000000
1!
1.
18
b0110 :
b0110 ;
b0111 <
1?
1F
1K
#150000000
0!
0.
08
0?
0F
0K
#155000000
1!
1.
18
b0111 :
b0111 ;
b1000 <
1?
1F
1K
#160000000
0!
0.
08
0?
0F
0K
#165000000
1!
1.
13
18
19
b1000 :
b1000 ;
b0000 <
1>
1?
b0010 C
1E
1F
b0010 J
1K
#170000000
0!
0.
08
0?
0F
0K
#175000000
1!
b0010 %
1.
b0010 2
03
b0010 4
b0010 5
18
09
b0000 :
b0000 ;
b0001 <
0>
1?
b0010 A
b0010 B
b0010 C
0E
1F
b0010 H
b0010 I
b0010 J
1K
#180000000
0!
0.
08
0?
0F
0K
#185000000
1!
1.
18
b0001 :
b0001 ;
b0010 <
1?
1F
1K
#190000000
0!
0.
08
0?
0F
0K
#195000000
1!
1.
18
b0010 :
b0010 ;
b0011 <
1?
1F
1K
#200000000
0!
0.
08
0?
0F
0K
#205000000
1!
1.
18
b0011 :
b0011 ;
b0100 <
1?
1F
1K
#210000000
0!
0.
08
0?
0F
0K
#215000000
1!
1.
18
b0100 :
b0100 ;
b0101 <
1?
1F
1K
#220000000
0!
0.
08
0?
0F
0K
#225000000
1!
1.
18
b0101 :
b0101 ;
b0110 <
1?
1F
1K
#230000000
0!
0.
08
0?
0F
0K
#235000000
1!
1.
18
b0110 :
b0110 ;
b0111 <
1?
1F
1K
#240000000
0!
0.
08
0?
0F
0K
#245000000
1!
1.
18
b0111 :
b0111 ;
b1000 <
1?
1F
1K
#250000000
0!
0.
08
0?
0F
0K
#255000000
1!
1.
13
18
19
b1000 :
b1000 ;
b0000 <
1>
1?
b0011 C
1E
1F
b0011 J
1K
#260000000
0!
0.
08
0?
0F
0K
#265000000
1!
b0011 %
1.
b0011 2
03
b0011 4
b0011 5
18
09
b0000 :
b0000 ;
b0001 <
0>
1?
b0011 A
b0011 B
b0011 C
0E
1F
b0011 H
b0011 I
b0011 J
1K
#270000000
0!
0.
08
0?
0F
0K
#275000000
1!
1.
18
b0001 :
b0001 ;
b0010 <
1?
1F
1K
#280000000
0!
0.
08
0?
0F
0K
#285000000
1!
1.
18
b0010 :
b0010 ;
b0011 <
1?
1F
1K
#290000000
0!
0.
08
0?
0F
0K
#295000000
1!
1.
18
b0011 :
b0011 ;
b0100 <
1?
1F
1K
#300000000
0!
0.
08
0?
0F
0K
#305000000
1!
1.
18
b0100 :
b0100 ;
b0101 <
1?
1F
1K
#310000000
0!
0.
08
0?
0F
0K
#315000000
1!
1.
18
b0101 :
b0101 ;
b0110 <
1?
1F
1K
#320000000
0!
0.
08
0?
0F
0K
#325000000
1!
1.
18
b0110 :
b0110 ;
b0111 <
1?
1F
1K
#330000000
0!
0.
08
0?
0F
0K
#335000000
1!
1.
18
b0111 :
b0111 ;
b1000 <
1?
1F
1K
#340000000
0!
0.
08
0?
0F
0K
#345000000
1!
1.
13
18
19
b1000 :
b1000 ;
b0000 <
1>
1?
b0100 C
1E
1F
b0100 J
1K
#350000000
0!
0.
08
0?
0F
0K
#355000000
1!
1"
b0100 %
1.
10
b0100 2
03
b0100 4
b0100 5
18
09
b0000 :
b0000 ;
b0001 <
0>
1?
1@
b0100 A
b0100 B
b0100 C
0E
1F
b0100 H
b0100 I
b0100 J
1K
1O
#360000000
0!
0.
08
0?
0F
0K
#365000000
1!
1.
18
b0001 :
b0001 ;
b0010 <
1?
1F
1K
#370000000
0!
0.
08
0?
0F
0K
#375000000
1!
1.
18
b0010 :
b0010 ;
b0011 <
1?
1F
1K
#380000000
0!
0.
08
0?
0F
0K
#385000000
1!
1.
18
b0011 :
b0011 ;
b0100 <
1?
1F
1K
#390000000
0!
0.
08
0?
0F
0K
#395000000
1!
1.
18
b0100 :
b0100 ;
b0101 <
1?
1F
1K
#400000000
0!
0.
08
0?
0F
0K
#405000000
1!
1.
18
b0101 :
b0101 ;
b0110 <
1?
1F
1K
#410000000
0!
0.
08
0?
0F
0K
#415000000
1!
1.
18
b0110 :
b0110 ;
b0111 <
1?
1F
1K
#420000000
0!
0.
08
0?
0F
0K
#425000000
1!
1.
18
b0111 :
b0111 ;
b1000 <
1?
1F
1K
#430000000
0!
0.
08
0?
0F
0K
#435000000
1!
1.
13
18
19
b1000 :
b1000 ;
b0000 <
1>
1?
b0000 C
1E
1F
b0101 J
1K
#440000000
0!
0.
08
0?
0F
0K
#445000000
1!
0"
b0101 %
1.
00
b0101 2
03
b0000 4
b0101 5
18
09
b0000 :
b0000 ;
b0001 <
0>
1?
0@
b0000 A
b0000 B
b0000 C
0E
1F
b0101 H
b0101 I
b0101 J
1K
0O
#450000000
0!
0.
08
0?
0F
0K
#455000000
1!
1.
18
b0001 :
b0001 ;
b0010 <
1?
1F
1K
#460000000
0!
0.
08
0?
0F
0K
#465000000
1!
1.
18
b0010 :
b0010 ;
b0011 <
1?
1F
1K
#470000000
0!
0.
08
0?
0F
0K
#475000000
1!
1.
18
b0011 :
b0011 ;
b0100 <
1?
1F
1K
#480000000
0!
0.
08
0?
0F
0K
#485000000
1!
1.
18
b0100 :
b0100 ;
b0101 <
1?
1F
1K
#490000000
0!
0.
08
0?
0F
0K
#495000000
1!
1.
18
b0101 :
b0101 ;
b0110 <
1?
1F
1K
#500000000
0!
0.
08
0?
0F
0K
#505000000
1!
1.
18
b0110 :
b0110 ;
b0111 <
1?
1F
1K
#510000000
0!
0.
08
0?
0F
0K
#515000000
1!
1.
18
b0111 :
b0111 ;
b1000 <
1?
1F
1K
#520000000
0!
0.
08
0?
0F
0K
#525000000
1!
1.
13
18
19
b1000 :
b1000 ;
b0000 <
1>
1?
b0001 C
1E
1F
b0110 J
1K
#530000000
0!
0.
08
0?
0F
0K
#535000000
1!
b0110 %
1.
b0110 2
03
b0001 4
b0110 5
18
09
b0000 :
b0000 ;
b0001 <
0>
1?
b0001 A
b0001 B
b0001 C
0E
1F
b0110 H
b0110 I
b0110 J
1K
#540000000
0!
0.
08
0?
0F
0K
#545000000
1!
1.
18
b0001 :
b0001 ;
b0010 <
1?
1F
1K
#550000000
0!
0.
08
0?
0F
0K
#555000000
1!
1.
18
b0010 :
b0010 ;
b0011 <
1?
1F
1K
#560000000
0!
0.
08
0?
0F
0K
#565000000
1!
1.
18
b0011 :
b0011 ;
b0100 <
1?
1F
1K
#570000000
0!
0.
08
0?
0F
0K
#575000000
1!
1.
18
b0100 :
b0100 ;
b0101 <
1?
1F
1K
#580000000
0!
0.
08
0?
0F
0K
#585000000
1!
1.
18
b0101 :
b0101 ;
b0110 <
1?
1F
1K
#590000000
0!
0.
08
0?
0F
0K
#595000000
1!
1.
18
b0110 :
b0110 ;
b0111 <
1?
1F
1K
#600000000
0!
0.
08
0?
0F
0K
#605000000
1!
1.
18
b0111 :
b0111 ;
b1000 <
1?
1F
1K
#610000000
0!
0.
08
0?
0F
0K
#615000000
1!
1.
13
18
19
b1000 :
b1000 ;
b0000 <
1>
1?
b0010 C
1E
1F
b0111 J
1K
#620000000
0!
0.
08
0?
0F
0K
#625000000
1!
b0111 %
1.
b0111 2
03
b0010 4
b0111 5
18
09
b0000 :
b0000 ;
b0001 <
0>
1?
b0010 A
b0010 B
b0010 C
0E
1F
b0111 H
b0111 I
b0111 J
1K
#630000000
0!
0.
08
0?
0F
0K
#635000000
1!
1.
18
b0001 :
b0001 ;
b0010 <
1?
1F
1K
#640000000
0!
0.
08
0?
0F
0K
#645000000
1!
1.
18
b0010 :
b0010 ;
b0011 <
1?
1F
1K
#650000000
0!
0.
08
0?
0F
0K
#655000000
1!
1.
18
b0011 :
b0011 ;
b0100 <
1?
1F
1K
#660000000
0!
0.
08
0?
0F
0K
#665000000
1!
1.
18
b0100 :
b0100 ;
b0101 <
1?
1F
1K
#670000000
0!
0.
08
0?
0F
0K
#675000000
1!
1.
18
b0101 :
b0101 ;
b0110 <
1?
1F
1K
#680000000
0!
0.
08
0?
0F
0K
#685000000
1!
1.
18
b0110 :
b0110 ;
b0111 <
1?
1F
1K
#690000000
0!
0.
08
0?
0F
0K
#695000000
1!
1.
18
b0111 :
b0111 ;
b1000 <
1?
1F
1K
#700000000
0!
0.
08
0?
0F
0K
#705000000
1!
1.
13
18
19
b1000 :
b1000 ;
b0000 <
1>
1?
b0011 C
1E
1F
b1000 J
1K
#710000000
0!
0.
08
0?
0F
0K
#715000000
1!
b1000 %
1.
b1000 2
03
b0011 4
b1000 5
18
09
b0000 :
b0000 ;
b0001 <
0>
1?
b0011 A
b0011 B
b0011 C
0E
1F
b1000 H
b1000 I
b1000 J
1K
#720000000
0!
0.
08
0?
0F
0K
#725000000
1!
1.
18
b0001 :
b0001 ;
b0010 <
1?
1F
1K
#730000000
0!
0.
08
0?
0F
0K
#735000000
1!
1.
18
b0010 :
b0010 ;
b0011 <
1?
1F
1K
#740000000
0!
0.
08
0?
0F
0K
#745000000
1!
1.
18
b0011 :
b0011 ;
b0100 <
1?
1F
1K
#750000000
0!
0.
08
0?
0F
0K
#755000000
1!
1.
18
b0100 :
b0100 ;
b0101 <
1?
1F
1K
#760000000
0!
0.
08
0?
0F
0K
#765000000
1!
1.
18
b0101 :
b0101 ;
b0110 <
1?
1F
1K
#770000000
0!
0.
08
0?
0F
0K
#775000000
1!
1.
18
b0110 :
b0110 ;
b0111 <
1?
1F
1K
#780000000
0!
0.
08
0?
0F
0K
#785000000
1!
1.
18
b0111 :
b0111 ;
b1000 <
1?
1F
1K
#790000000
0!
0.
08
0?
0F
0K
#795000000
1!
1.
13
18
19
b1000 :
b1000 ;
b0000 <
1>
1?
b0100 C
1E
1F
b1001 J
1K
#800000000
0!
0.
08
0?
0F
0K
#805000000
1!
1"
b1001 %
1.
10
b1001 2
03
b0100 4
b1001 5
18
09
b0000 :
b0000 ;
b0001 <
0>
1?
1@
b0100 A
b0100 B
b0100 C
0E
1F
b1001 H
b1001 I
b1001 J
1K
1O
#810000000
0!
0.
08
0?
0F
0K
#815000000
1!
1.
18
b0001 :
b0001 ;
b0010 <
1?
1F
1K
#820000000
0!
0.
08
0?
0F
0K
#825000000
1!
1.
18
b0010 :
b0010 ;
b0011 <
1?
1F
1K
#830000000
0!
0.
08
0?
0F
0K
#835000000
1!
1.
18
b0011 :
b0011 ;
b0100 <
1?
1F
1K
#840000000
0!
0.
08
0?
0F
0K
#845000000
1!
1.
18
b0100 :
b0100 ;
b0101 <
1?
1F
1K
#850000000
0!
0.
08
0?
0F
0K
#855000000
1!
1.
18
b0101 :
b0101 ;
b0110 <
1?
1F
1K
#860000000
0!
0.
08
0?
0F
0K
#865000000
1!
1.
18
b0110 :
b0110 ;
b0111 <
1?
1F
1K
#870000000
0!
0.
08
0?
0F
0K
#875000000
1!
1.
18
b0111 :
b0111 ;
b1000 <
1?
1F
1K
#880000000
0!
0.
08
0?
0F
0K
#885000000
1!
1.
13
18
19
b1000 :
b1000 ;
b0000 <
1>
1?
b0000 C
1E
1F
b1010 J
1K
#890000000
0!
0.
08
0?
0F
0K
#895000000
1!
0"
1#
b1010 %
0(
0-
1.
00
11
b1010 2
03
b0000 4
b1010 5
07
18
09
b0000 :
b0000 ;
b0000 <
0>
1?
0@
b0000 A
b0000 B
b0000 C
0E
1F
1G
b1010 H
b1010 I
b1010 J
1K
1N
0O
0P
#900000000
0!
0.
08
0?
0F
0K
#905000000
1!
1.
18
1?
1F
1K
#910000000
0!
0.
08
0?
0F
0K
#915000000
1!
1.
18
1?
1F
1K
#920000000
0!
0.
08
0?
0F
0K
#925000000
1!
1.
18
1?
1F
1K
#930000000
0!
0.
08
0?
0F
0K
#935000000
1!
1.
18
1?
1F
1K
#940000000
0!
0.
08
0?
0F
0K
#945000000
1!
1.
18
1?
1F
1K
#950000000
0!
0.
08
0?
0F
0K
#955000000
1!
1.
18
1?
1F
1K
#960000000
0!
0.
08
0?
0F
0K
#965000000
1!
1.
18
1?
1F
1K
#970000000
0!
0.
08
0?
0F
0K
#975000000
1!
1.
18
1?
1F
1K
#980000000
0!
0.
08
0?
0F
0K
#985000000
1!
1.
18
1?
1F
1K
#990000000
0!
0.
08
0?
0F
0K
#995000000
1!
1.
18
1?
1F
1K
#1000000000
0!
1'
1(
1)
1,
1-
0.
16
17
08
1=
0?
1D
0F
b0000 J
0K
1M
1P
1Q
#1005000000
1!
0#
b01 $
b0000 %
0)
b010 *
0,
1.
b01 /
01
b0000 2
b0000 5
06
18
b0001 <
0=
1?
0D
1F
0G
b0000 H
b0000 I
1K
0N
0Q
b01 R
b010 S
#1010000000
0!
0.
08
0?
0F
0K
#1015000000
1!
1.
18
b0001 :
b0001 ;
b0010 <
1?
1F
1K
#1020000000
0!
0.
08
0?
0F
0K
#1025000000
1!
1.
18
b0010 :
b0010 ;
b0011 <
1?
1F
1K
#1030000000
0!
0.
08
0?
0F
0K
#1035000000
1!
1.
18
b0011 :
b0011 ;
b0100 <
1?
1F
1K
#1040000000
0!
0.
08
0?
0F
0K
#1045000000
1!
1.
18
b0100 :
b0100 ;
b0101 <
1?
1F
1K
#1050000000
0!
0.
08
0?
0F
0K
#1055000000
1!
1.
18
b0101 :
b0101 ;
b0110 <
1?
1F
1K
#1060000000
0!
0.
08
0?
0F
0K
#1065000000
1!
1.
18
b0110 :
b0110 ;
b0111 <
1?
1F
1K
#1070000000
0!
0.
08
0?
0F
0K
#1075000000
1!
1.
18
b0111 :
b0111 ;
b1000 <
1?
1F
1K
#1080000000
0!
0.
08
0?
0F
0K
#1085000000
1!
1.
13
18
19
b1000 :
b1000 ;
b0000 <
1>
1?
b0001 C
1E
1F
b0001 J
1K
#1090000000
0!
0.
08
0?
0F
0K
#1095000000
1!
b0001 %
1.
b0001 2
03
b0001 4
b0001 5
18
09
b0000 :
b0000 ;
b0001 <
0>
1?
b0001 A
b0001 B
b0001 C
0E
1F
b0001 H
b0001 I
b0001 J
1K
#1100000000
0!
0.
08
0?
0F
0K
#1105000000
1!
1.
18
b0001 :
b0001 ;
b0010 <
1?
1F
1K
#1110000000
0!
0.
08
0?
0F
0K
#1115000000
1!
1.
18
b0010 :
b0010 ;
b0011 <
1?
1F
1K
#1120000000
0!
0.
08
0?
0F
0K
#1125000000
1!
1.
18
b0011 :
b0011 ;
b0100 <
1?
1F
1K
#1130000000
0!
0.
08
0?
0F
0K
#1135000000
1!
1.
18
b0100 :
b0100 ;
b0101 <
1?
1F
1K
#1140000000
0!
0.
08
0?
0F
0K
#1145000000
1!
1.
18
b0101 :
b0101 ;
b0110 <
1?
1F
1K
#1150000000
0!
0.
08
0?
0F
0K
#1155000000
1!
1.
18
b0110 :
b0110 ;
b0111 <
1?
1F
1K
#1160000000
0!
0.
08
0?
0F
0K
#1165000000
1!
1.
18
b0111 :
b0111 ;
b1000 <
1?
1F
1K
#1170000000
0!
0.
08
0?
0F
0K
#1175000000
1!
1.
13
18
19
b1000 :
b1000 ;
b0000 <
1>
1?
b0010 C
1E
1F
b0010 J
1K
#1180000000
0!
0.
08
0?
0F
0K
#1185000000
1!
b0010 %
1.
b0010 2
03
b0010 4
b0010 5
18
09
b0000 :
b0000 ;
b0001 <
0>
1?
b0010 A
b0010 B
b0010 C
0E
1F
b0010 H
b0010 I
b0010 J
1K
#1190000000
0!
0.
08
0?
0F
0K
#1195000000
1!
1.
18
b0001 :
b0001 ;
b0010 <
1?
1F
1K
#1200000000
0!
0.
08
0?
0F
0K
#1205000000
1!
1.
18
b0010 :
b0010 ;
b0011 <
1?
1F
1K
#1210000000
0!
0.
08
0?
0F
0K
#1215000000
1!
1.
18
b0011 :
b0011 ;
b0100 <
1?
1F
1K
#1220000000
0!
0.
08
0?
0F
0K
#1225000000
1!
1.
18
b0100 :
b0100 ;
b0101 <
1?
1F
1K
#1230000000
0!
0.
08
0?
0F
0K
#1235000000
1!
1.
18
b0101 :
b0101 ;
b0110 <
1?
1F
1K
#1240000000
0!
0.
08
0?
0F
0K
#1245000000
1!
1.
18
b0110 :
b0110 ;
b0111 <
1?
1F
1K
#1250000000
0!
0.
08
0?
0F
0K
#1255000000
1!
1.
18
b0111 :
b0111 ;
b1000 <
1?
1F
1K
#1260000000
0!
0.
08
0?
0F
0K
#1265000000
1!
1.
13
18
19
b1000 :
b1000 ;
b0000 <
1>
1?
b0011 C
1E
1F
b0011 J
1K
#1270000000
0!
0.
08
0?
0F
0K
#1275000000
1!
b0011 %
1.
b0011 2
03
b0011 4
b0011 5
18
09
b0000 :
b0000 ;
b0001 <
0>
1?
b0011 A
b0011 B
b0011 C
0E
1F
b0011 H
b0011 I
b0011 J
1K
#1280000000
0!
0.
08
0?
0F
0K
#1285000000
1!
1.
18
b0001 :
b0001 ;
b0010 <
1?
1F
1K
#1290000000
0!
0.
08
0?
0F
0K
#1295000000
1!
1.
18
b0010 :
b0010 ;
b0011 <
1?
1F
1K
#1300000000
0!
0.
08
0?
0F
0K
#1305000000
1!
1.
18
b0011 :
b0011 ;
b0100 <
1?
1F
1K
#1310000000
0!
0.
08
0?
0F
0K
#1315000000
1!
1.
18
b0100 :
b0100 ;
b0101 <
1?
1F
1K
#1320000000
0!
0.
08
0?
0F
0K
#1325000000
1!
1.
18
b0101 :
b0101 ;
b0110 <
1?
1F
1K
#1330000000
0!
0.
08
0?
0F
0K
#1335000000
1!
1.
18
b0110 :
b0110 ;
b0111 <
1?
1F
1K
#1340000000
0!
0.
08
0?
0F
0K
#1345000000
1!
1.
18
b0111 :
b0111 ;
b1000 <
1?
1F
1K
#1350000000
0!
0.
08
0?
0F
0K
#1355000000
1!
1.
13
18
19
b1000 :
b1000 ;
b0000 <
1>
1?
b0100 C
1E
1F
b0100 J
1K
#1360000000
0!
0.
08
0?
0F
0K
#1365000000
1!
1"
b0100 %
1)
1,
1.
10
b0100 2
03
b0100 4
b0100 5
16
18
09
b0000 :
b0000 ;
b0000 <
1=
0>
1?
1@
b0100 A
b0100 B
b0000 C
1D
0E
1F
b0100 H
b0100 I
b0000 J
1K
1O
1Q
#1370000000
0!
0.
08
0?
0F
0K
#1375000000
1!
0"
b10 $
b0000 %
0)
b100 *
b001 +
0,
1.
b10 /
00
b0000 2
b0000 4
b0000 5
06
18
b0001 <
0=
1?
0@
b0000 A
b0000 B
0D
1F
b0000 H
b0000 I
1K
0O
0Q
b10 R
b100 S
b001 T
#1380000000
0!
0.
08
0?
0F
0K
#1385000000
1!
1.
18
b0001 :
b0001 ;
b0010 <
1?
1F
1K
#1390000000
0!
0.
08
0?
0F
0K
#1395000000
1!
1.
18
b0010 :
b0010 ;
b0011 <
1?
1F
1K
#1400000000
0!
0.
08
0?
0F
0K
#1405000000
1!
1.
18
b0011 :
b0011 ;
b0100 <
1?
1F
1K
#1410000000
0!
0.
08
0?
0F
0K
#1415000000
1!
1.
18
b0100 :
b0100 ;
b0101 <
1?
1F
1K
#1420000000
0!
0.
08
0?
0F
0K
#1425000000
1!
1.
18
b0101 :
b0101 ;
b0110 <
1?
1F
1K
#1430000000
0!
0.
08
0?
0F
0K
#1435000000
1!
1.
18
b0110 :
b0110 ;
b0111 <
1?
1F
1K
#1440000000
0!
0.
08
0?
0F
0K
#1445000000
1!
1.
18
b0111 :
b0111 ;
b1000 <
1?
1F
1K
#1450000000
0!
0.
08
0?
0F
0K
#1455000000
1!
1.
13
18
19
b1000 :
b1000 ;
b0000 <
1>
1?
b0001 C
1E
1F
b0001 J
1K
#1460000000
0!
0.
08
0?
0F
0K
#1465000000
1!
b0001 %
1.
b0001 2
03
b0001 4
b0001 5
18
09
b0000 :
b0000 ;
b0001 <
0>
1?
b0001 A
b0001 B
b0001 C
0E
1F
b0001 H
b0001 I
b0001 J
1K
#1470000000
0!
0.
08
0?
0F
0K
#1475000000
1!
1.
18
b0001 :
b0001 ;
b0010 <
1?
1F
1K
