VHDL Files/src/stopwatch/ctrstg.vhd
library ieee;
use ieee.std_logic_1164.all;
use ieee.numeric_std.all;

entity ctrstg is
  generic(max   : integer  := 9;
          width : integer  := 4 );
  port   (clr   : in  std_logic;
          en    : in  std_logic;
          clk   : in  std_logic;
          tick  : out std_logic;
          cnt   : out std_logic_vector(width-1 downto 0));
end ctrstg;

architecture my_arch of ctrstg is

  signal stg_reg, stg_next : unsigned(width-1 downto 0);

begin

--SEQUENTIAL PORTION
  process(clr, clk)
  begin
    if clr = '1' then
      stg_reg <= (others => '0');
    elsif rising_edge(clk) then
      stg_reg <= stg_next;
    end if;
  end process;

--COMBINATIONAL PORTION
  stg_next <=(others=>'0')when((stg_reg=max)and en='1') else
             stg_reg + 1 when en = '1' else
             stg_reg;

  tick <= '1' when stg_reg = max else '0';

  cnt <= std_logic_vector(stg_reg);

end my_arch;

VHDL Files/src/stopwatch/ctrstg_tb.vhd
library ieee;
use ieee.std_logic_1164.all;
use ieee.numeric_std.all;

entity tb is
end tb;

architecture tb of tb is

  signal clr, en, clk, tick : std_logic := '0';
  signal cnt : std_logic_vector (9 downto 0);
  constant clk_period : time := 10 ns;

begin

  DUT : entity work.ctrstg(my_arch)
    generic map ( max  => 200,
                  width => 10 )
    port map ( clr  => clr,
               en   => en,
               clk  => clk,
               tick => tick,
               cnt  => cnt );

  clk_process : process
  begin
    loop
      wait for clk_period / 2;
      clk <= not clk;
    end loop;
  end process;

  en_process : process
  begin
    wait for clk_period;
    en <= '1';
    wait;
  end process;

  clr_process : process
  begin
    clr <= '1';
    wait for clk_period;
    clr <= '0';
    wait;
  end process;

  termination : process
  begin
    wait for 100000 ns;
    assert false report "Test Complete" severity failure;
  end process;

end tb;

VHDL Files/src/stopwatch/ctrstgsim.vcd
$date
  Fri Nov 17 21:44:08 2023
$end
$version
  GHDL v0
$end
$timescale
  1 fs
$end
$scope module standard $end
$upscope $end
$scope module std_logic_1164 $end
$upscope $end
$scope module numeric_std $end
$upscope $end
$scope module tb $end
$var reg 1 ! clr $end
$var reg 1 " en $end
$var reg 1 # clk $end
$var reg 1 $ tick $end
$var reg 10 % cnt[9:0] $end
$scope module dut $end
$var reg 1 & clr $end
$var reg 1 ' en $end
$var reg 1 ( clk $end
$var reg 1 ) tick $end
$var reg 10 * cnt[9:0] $end
$var reg 10 + stg_reg[9:0] $end
$var reg 10 , stg_next[9:0] $end
$upscope $end
$upscope $end
$enddefinitions $end
#0
1!
0"
0#
0$
b0000000000 %
1&
0'
0(
0)
b0000000000 *
b0000000000 +
b0000000000 ,
#5000000
1#
1(
#10000000
0!
1"
0#
0&
1'
0(
b0000000001 ,
#15000000
1#
b0000000001 %
1(
b0000000001 *
b0000000001 +
b0000000010 ,
#20000000
0#
0(
#25000000
1#
b0000000010 %
1(
b0000000010 *
b0000000010 +
b0000000011 ,
#30000000
0#
0(
#35000000
1#
b0000000011 %
1(
b0000000011 *
b0000000011 +
b0000000100 ,
#40000000
0#
0(
#45000000
1#
b0000000100 %
1(
b0000000100 *
b0000000100 +
b0000000101 ,
#50000000
0#
0(
#55000000
1#
b0000000101 %
1(
b0000000101 *
b0000000101 +
b0000000110 ,
#60000000
0#
0(
#65000000
1#
b0000000110 %
1(
b0000000110 *
b0000000110 +
b0000000111 ,
#70000000
0#
0(
#75000000
1#
b0000000111 %
1(
b0000000111 *
b0000000111 +
b0000001000 ,
#80000000
0#
0(
#85000000
1#
b0000001000 %
1(
b0000001000 *
b0000001000 +
b0000001001 ,
#90000000
0#
0(
#95000000
1#
b0000001001 %
1(
b0000001001 *
b0000001001 +
b0000001010 ,
#100000000
0#
0(
#105000000
1#
b0000001010 %
1(
b0000001010 *
b0000001010 +
b0000001011 ,
#110000000
0#
0(
#115000000
1#
b0000001011 %
1(
b0000001011 *
b0000001011 +
b0000001100 ,
#120000000
0#
0(
#125000000
1#
b0000001100 %
1(
b0000001100 *
b0000001100 +
b0000001101 ,
#130000000
0#
0(
#135000000
1#
b0000001101 %
1(
b0000001101 *
b0000001101 +
b0000001110 ,
#140000000
0#
0(
#145000000
1#
b0000001110 %
1(
b0000001110 *
b0000001110 +
b0000001111 ,
#150000000
0#
0(
#155000000
1#
b0000001111 %
1(
b0000001111 *
b0000001111 +
b0000010000 ,
#160000000
0#
0(
#165000000
1#
b0000010000 %
1(
b0000010000 *
b0000010000 +
b0000010001 ,
#170000000
0#
0(
#175000000
1#
b0000010001 %
1(
b0000010001 *
b0000010001 +
b0000010010 ,
#180000000
0#
0(
#185000000
1#
b0000010010 %
1(
b0000010010 *
b0000010010 +
b0000010011 ,
#190000000
0#
0(
#195000000
1#
b0000010011 %
1(
b0000010011 *
b0000010011 +
b0000010100 ,
#200000000
0#
0(
#205000000
1#
b0000010100 %
1(
b0000010100 *
b0000010100 +
b0000010101 ,
#210000000
0#
0(
#215000000
1#
b0000010101 %
1(
b0000010101 *
b0000010101 +
b0000010110 ,
#220000000
0#
0(
#225000000
1#
b0000010110 %
1(
b0000010110 *
b0000010110 +
b0000010111 ,
#230000000
0#
0(
#235000000
1#
b0000010111 %
1(
b0000010111 *
b0000010111 +
b0000011000 ,
#240000000
0#
0(
#245000000
1#
b0000011000 %
1(
b0000011000 *
b0000011000 +
b0000011001 ,
#250000000
0#
0(
#255000000
1#
b0000011001 %
1(
b0000011001 *
b0000011001 +
b0000011010 ,
#260000000
0#
0(
#265000000
1#
b0000011010 %
1(
b0000011010 *
b0000011010 +
b0000011011 ,
#270000000
0#
0(
#275000000
1#
b0000011011 %
1(
b0000011011 *
b0000011011 +
b0000011100 ,
#280000000
0#
0(
#285000000
1#
b0000011100 %
1(
b0000011100 *
b0000011100 +
b0000011101 ,
#290000000
0#
0(
#295000000
1#
b0000011101 %
1(
b0000011101 *
b0000011101 +
b0000011110 ,
#300000000
0#
0(
#305000000
1#
b0000011110 %
1(
b0000011110 *
b0000011110 +
b0000011111 ,
#310000000
0#
0(
#315000000
1#
b0000011111 %
1(
b0000011111 *
b0000011111 +
b0000100000 ,
#320000000
0#
0(
#325000000
1#
b0000100000 %
1(
b0000100000 *
b0000100000 +
b0000100001 ,
#330000000
0#
0(
#335000000
1#
b0000100001 %
1(
b0000100001 *
b0000100001 +
b0000100010 ,
#340000000
0#
0(
#345000000
1#
b0000100010 %
1(
b0000100010 *
b0000100010 +
b0000100011 ,
#350000000
0#
0(
#355000000
1#
b0000100011 %
1(
b0000100011 *
b0000100011 +
b0000100100 ,
#360000000
0#
0(
#365000000
1#
b0000100100 %
1(
b0000100100 *
b0000100100 +
b0000100101 ,
#370000000
0#
0(
#375000000
1#
b0000100101 %
1(
b0000100101 *
b0000100101 +
b0000100110 ,
#380000000
0#
0(
#385000000
1#
b0000100110 %
1(
b0000100110 *
b0000100110 +
b0000100111 ,
#390000000
0#
0(
#395000000
1#
b0000100111 %
1(
b0000100111 *
b0000100111 +
b0000101000 ,
#400000000
0#
0(
#405000000
1#
b0000101000 %
1(
b0000101000 *
b0000101000 +
b0000101001 ,
#410000000
0#
0(
#415000000
1#
b0000101001 %
1(
b0000101001 *
b0000101001 +
b0000101010 ,
#420000000
0#
0(
#425000000
1#
b0000101010 %
1(
b0000101010 *
b0000101010 +
b0000101011 ,
#430000000
0#
0(
#435000000
1#
b0000101011 %
1(
b0000101011 *
b0000101011 +
b0000101100 ,
#440000000
0#
0(
#445000000
1#
b0000101100 %
1(
b0000101100 *
b0000101100 +
b0000101101 ,
#450000000
0#
0(
#455000000
1#
b0000101101 %
1(
b0000101101 *
b0000101101 +
b0000101110 ,
#460000000
0#
0(
#465000000
1#
b0000101110 %
1(
b0000101110 *
b0000101110 +
b0000101111 ,
#470000000
0#
0(
#475000000
1#
b0000101111 %
1(
b0000101111 *
b0000101111 +
b0000110000 ,
#480000000
0#
0(
#485000000
1#
b0000110000 %
1(
b0000110000 *
b0000110000 +
b0000110001 ,
#490000000
0#
0(
#495000000
1#
b0000110001 %
1(
b0000110001 *
b0000110001 +
b0000110010 ,
#500000000
0#
0(
#505000000
1#
b0000110010 %
1(
b0000110010 *
b0000110010 +
b0000110011 ,
#510000000
0#
0(
#515000000
1#
b0000110011 %
1(
b0000110011 *
b0000110011 +
b0000110100 ,
#520000000
0#
0(
#525000000
1#
b0000110100 %
1(
b0000110100 *
b0000110100 +
b0000110101 ,
#530000000
0#
0(
#535000000
1#
b0000110101 %
1(
b0000110101 *
b0000110101 +
b0000110110 ,
#540000000
0#
0(
#545000000
1#
b0000110110 %
1(
b0000110110 *
b0000110110 +
b0000110111 ,
#550000000
0#
0(
#555000000
1#
b0000110111 %
1(
b0000110111 *
b0000110111 +
b0000111000 ,
#560000000
0#
0(
#565000000
1#
b0000111000 %
1(
b0000111000 *
b0000111000 +
b0000111001 ,
#570000000
0#
0(
#575000000
1#
b0000111001 %
1(
b0000111001 *
b0000111001 +
b0000111010 ,
#580000000
0#
0(
#585000000
1#
b0000111010 %
1(
b0000111010 *
b0000111010 +
b0000111011 ,
#590000000
0#
0(
#595000000
1#
b0000111011 %
1(
b0000111011 *
b0000111011 +
b0000111100 ,
#600000000
0#
0(
#605000000
1#
b0000111100 %
1(
b0000111100 *
b0000111100 +
b0000111101 ,
#610000000
0#
0(
#615000000
1#
b0000111101 %
1(
b0000111101 *
b0000111101 +
b0000111110 ,
#620000000
0#
0(
#625000000
1#
b0000111110 %
1(
b0000111110 *
b0000111110 +
b0000111111 ,
#630000000
0#
0(
#635000000
1#
b0000111111 %
1(
b0000111111 *
b0000111111 +
b0001000000 ,
#640000000
0#
0(
#645000000
1#
b0001000000 %
1(
b0001000000 *
b0001000000 +
b0001000001 ,
#650000000
0#
0(
#655000000
1#
b0001000001 %
1(
b0001000001 *
b0001000001 +
b0001000010 ,
#660000000
0#
0(
#665000000
1#
b0001000010 %
1(
b0001000010 *
b0001000010 +
b0001000011 ,
#670000000
0#
0(
#675000000
1#
b0001000011 %
1(
b0001000011 *
b0001000011 +
b0001000100 ,
#680000000
0#
0(
#685000000
1#
b0001000100 %
1(
b0001000100 *
b0001000100 +
b0001000101 ,
#690000000
0#
0(
#695000000
1#
b0001000101 %
1(
b0001000101 *
b0001000101 +
b0001000110 ,
#700000000
0#
0(
#705000000
1#
b0001000110 %
1(
b0001000110 *
b0001000110 +
b0001000111 ,
#710000000
0#
0(
#715000000
1#
b0001000111 %
1(
b0001000111 *
b0001000111 +
b0001001000 ,
#720000000
0#
0(
#725000000
1#
b0001001000 %
1(
b0001001000 *
b0001001000 +
b0001001001 ,
#730000000
0#
0(
#735000000
1#
b0001001001 %
1(
b0001001001 *
b0001001001 +
b0001001010 ,
#740000000
0#
0(
#745000000
1#
b0001001010 %
1(
b0001001010 *
b0001001010 +
b0001001011 ,
#750000000
0#
0(
#755000000
1#
b0001001011 %
1(
b0001001011 *
b0001001011 +
b0001001100 ,
#760000000
0#
0(
#765000000
1#
b0001001100 %
1(
b0001001100 *
b0001001100 +
b0001001101 ,
#770000000
0#
0(
#775000000
1#
b0001001101 %
1(
b0001001101 *
b0001001101 +
b0001001110 ,
#780000000
0#
0(
#785000000
1#
b0001001110 %
1(
b0001001110 *
b0001001110 +
b0001001111 ,
#790000000
0#
0(
#795000000
1#
b0001001111 %
1(
b0001001111 *
b0001001111 +
b0001010000 ,
#800000000
0#
0(
#805000000
1#
b0001010000 %
1(
b0001010000 *
b0001010000 +
b0001010001 ,
#810000000
0#
0(
#815000000
1#
b0001010001 %
1(
b0001010001 *
b0001010001 +
b0001010010 ,
#820000000
0#
0(
#825000000
1#
b0001010010 %
1(
b0001010010 *
b0001010010 +
b0001010011 ,
#830000000
0#
0(
#835000000
1#
b0001010011 %
1(
b0001010011 *
b0001010011 +
b0001010100 ,
#840000000
0#
0(
#845000000
1#
b0001010100 %
1(
b0001010100 *
b0001010100 +
b0001010101 ,
#850000000
0#
0(
#855000000
1#
b0001010101 %
1(
b0001010101 *
b0001010101 +
b0001010110 ,
#860000000
0#
0(
#865000000
1#
b0001010110 %
1(
b0001010110 *
b0001010110 +
b0001010111 ,
#870000000
0#
0(
#875000000
1#
b0001010111 %
1(
b0001010111 *
b0001010111 +
b0001011000 ,
#880000000
0#
0(
#885000000
1#
b0001011000 %
1(
b0001011000 *
b0001011000 +
b0001011001 ,
#890000000
0#
0(
#895000000
1#
b0001011001 %
1(
b0001011001 *
b0001011001 +
b0001011010 ,
#900000000
0#
0(
#905000000
1#
b0001011010 %
1(
b0001011010 *
b0001011010 +
b0001011011 ,
#910000000
0#
0(
#915000000
1#
b0001011011 %
1(
b0001011011 *
b0001011011 +
b0001011100 ,
#920000000
0#
0(
#925000000
1#
b0001011100 %
1(
b0001011100 *
b0001011100 +
b0001011101 ,
#930000000
0#
0(
#935000000
1#
b0001011101 %
1(
b0001011101 *
b0001011101 +
b0001011110 ,
#940000000
0#
0(
#945000000
1#
b0001011110 %
1(
b0001011110 *
b0001011110 +
b0001011111 ,
#950000000
0#
0(
#955000000
1#
b0001011111 %
1(
b0001011111 *
b0001011111 +
b0001100000 ,
#960000000
0#
0(
#965000000
1#
b0001100000 %
1(
b0001100000 *
b0001100000 +
b0001100001 ,
#970000000
0#
0(
#975000000
1#
b0001100001 %
1(
b0001100001 *
b0001100001 +
b0001100010 ,
#980000000
0#
0(
#985000000
1#
b0001100010 %
1(
b0001100010 *
b0001100010 +
b0001100011 ,
#990000000
0#
0(
#995000000
1#
b0001100011 %
1(
b0001100011 *
b0001100011 +
b0001100100 ,
#1000000000
0#
0(
#1005000000
1#
b0001100100 %
1(
b0001100100 *
b0001100100 +
b0001100101 ,
#1010000000
0#
0(
#1015000000
1#
b0001100101 %
1(
b0001100101 *
b0001100101 +
b0001100110 ,
#1020000000
0#
0(
#1025000000
1#
b0001100110 %
1(
b0001100110 *
b0001100110 +
b0001100111 ,
#1030000000
0#
0(
#1035000000
1#
b0001100111 %
1(
b0001100111 *
b0001100111 +
b0001101000 ,
#1040000000
0#
0(
#1045000000
1#
b0001101000 %
1(
b0001101000 *
b0001101000 +
b0001101001 ,
#1050000000
0#
0(
#1055000000
1#
b0001101001 %
1(
b0001101001 *
b0001101001 +
b0001101010 ,
#1060000000
0#
0(
#1065000000
1#
b0001101010 %
1(
b0001101010 *
b0001101010 +
b0001101011 ,
#1070000000
0#
0(
#1075000000
1#
b0001101011 %
1(
b0001101011 *
b0001101011 +
b0001101100 ,
#1080000000
0#
0(
#1085000000
1#
b0001101100 %
1(
b0001101100 *
b0001101100 +
b0001101101 ,
#1090000000
0#
0(
#1095000000
1#
b0001101101 %
1(
b0001101101 *
b0001101101 +
b0001101110 ,
#1100000000
0#
0(
#1105000000
1#
b0001101110 %
1(
b0001101110 *
b0001101110 +
b0001101111 ,
#1110000000
0#
0(
#1115000000
1#
b0001101111 %
1(
b0001101111 *
b0001101111 +
b0001110000 ,
#1120000000
0#
0(
#1125000000
1#
b0001110000 %
1(
b0001110000 *
b0001110000 +
b0001110001 ,
#1130000000
0#
0(
#1135000000
1#
b0001110001 %
1(
b0001110001 *
b0001110001 +
b0001110010 ,
#1140000000
0#
0(
#1145000000
1#
b0001110010 %
1(
b0001110010 *
b0001110010 +
b0001110011 ,
#1150000000
0#
0(
#1155000000
1#
b0001110011 %
1(
b0001110011 *
b0001110011 +
b0001110100 ,
#1160000000
0#
0(
#1165000000
1#
b0001110100 %
1(
b0001110100 *
b0001110100 +
b0001110101 ,
#1170000000
0#
0(
#1175000000
1#
b0001110101 %
1(
b0001110101 *
b0001110101 +
b0001110110 ,
#1180000000
0#
0(
#1185000000
1#
b0001110110 %
1(
b0001110110 *
b0001110110 +
b0001110111 ,
#1190000000
0#
0(
#1195000000
1#
b0001110111 %
1(
b0001110111 *
b0001110111 +
b0001111000 ,
#1200000000
0#
0(
#1205000000
1#
b0001111000 %
1(
b0001111000 *
b0001111000 +
b0001111001 ,
#1210000000
0#
0(
#1215000000
1#
b0001111001 %
1(
b0001111001 *
b0001111001 +
b0001111010 ,
#1220000000
0#
0(
#1225000000
1#
b0001111010 %
1(
b0001111010 *
b0001111010 +
b0001111011 ,
#1230000000
0#
0(
#1235000000
1#
b0001111011 %
1(
b0001111011 *
b0001111011 +
b0001111100 ,
#1240000000
0#
0(
#1245000000
1#
b0001111100 %
1(
b0001111100 *
b0001111100 +
b0001111101 ,
#1250000000
0#
0(
#1255000000
1#
b0001111101 %
1(
b0001111101 *
b0001111101 +
b0001111110 ,
#1260000000
0#
0(
#1265000000
1#
b0001111110 %
1(
b0001111110 *
b0001111110 +
b0001111111 ,
#1270000000
0#
0(
#1275000000
1#
b0001111111 %
1(
b0001111111 *
b0001111111 +
b0010000000 ,
#1280000000
0#
0(
#1285000000
1#
b0010000000 %
1(
b0010000000 *
b0010000000 +
b0010000001 ,
#1290000000
0#
0(
#1295000000
1#
b0010000001 %
1(
b0010000001 *
b0010000001 +
b0010000010 ,
#1300000000
0#
0(
#1305000000
1#
b0010000010 %
1(
b0010000010 *
b0010000010 +
b0010000011 ,
#1310000000
0#
0(
#1315000000
1#
b0010000011 %
1(
b0010000011 *
b0010000011 +
b0010000100 ,
#1320000000
0#
0(
#1325000000
1#
b0010000100 %
1(
b0010000100 *
b0010000100 +
b0010000101 ,
#1330000000
0#
0(
#1335000000
1#
b0010000101 %
1(
b0010000101 *
b0010000101 +
b0010000110 ,
#1340000000
0#
0(
#1345000000
1#
b0010000110 %
1(
b0010000110 *
b0010000110 +
b0010000111 ,
#1350000000
0#
0(
#1355000000
1#
b0010000111 %
1(
b0010000111 *
b0010000111 +
b0010001000 ,
#1360000000
0#
0(
#1365000000
1#
b0010001000 %
1(
b0010001000 *
b0010001000 +
b0010001001 ,
#1370000000
0#
0(
#1375000000
1#
b0010001001 %
1(
b0010001001 *
b0010001001 +
b0010001010 ,
#1380000000
0#
0(
#1385000000
1#
b0010001010 %
1(
b0010001010 *
b0010001010 +
b0010001011 ,
#1390000000
0#
0(
#1395000000
1#
b0010001011 %
1(
b0010001011 *
b0010001011 +
b0010001100 ,
#1400000000
0#
0(
#1405000000
1#
b0010001100 %
1(
b0010001100 *
b0010001100 +
b0010001101 ,
#1410000000
0#
0(
#1415000000
1#
b0010001101 %
1(
b0010001101 *
b0010001101 +
b0010001110 ,
#1420000000
0#
0(
#1425000000
1#
b0010001110 %
1(
b0010001110 *
b0010001110 +
b0010001111 ,
#1430000000
0#
0(
#1435000000
1#
b0010001111 %
1(
b0010001111 *
b0010001111 +
b0010010000 ,
#1440000000
0#
0(
#1445000000
1#
b0010010000 %
1(
b0010010000 *
b0010010000 +
b0010010001 ,
#1450000000
0#
0(
#1455000000
1#
b0010010001 %
1(
b0010010001 *
b0010010001 +
b0010010010 ,
#1460000000
0#
0(
#1465000000
1#
b0010010010 %
1(
b0010010010 *
b0010010010 +
b0010010011 ,
#1470000000
0#
0(
#1475000000
1#
b0010010011 %
1(
b0010010011 *
b0010010011 +
b0010010100 ,
#1480000000
0#
0(
#1485000000
1#
b0010010100 %
1(
b0010010100 *
b0010010100 +
b0010010101 ,
#1490000000
0#
0(
#1495000000
1#
b0010010101 %
1(
b0010010101 *
b0010010101 +
b0010010110 ,
#1500000000
0#
0(
#1505000000
1#
b0010010110 %
1(
b0010010110 *
b0010010110 +
b0010010111 ,
#1510000000
0#
0(
#1515000000
1#
b0010010111 %
1(
b0010010111 *
b0010010111 +
b0010011000 ,
#1520000000
0#
0(
#1525000000
1#
b0010011000 %
1(
b0010011000 *
b0010011000 +
b0010011001 ,
#1530000000
0#
0(
#1535000000
1#
b0010011001 %
1(
b0010011001 *
b0010011001 +
b0010011010 ,
#1540000000
0#
0(
#1545000000
1#
b0010011010 %
1(
b0010011010 *
b0010011010 +
b0010011011 ,
#1550000000
0#
0(
#1555000000
1#
b0010011011 %
1(
b0010011011 *
b0010011011 +
b0010011100 ,
#1560000000
0#
0(
#1565000000
1#
b0010011100 %
1(
b0010011100 *
b0010011100 +
b0010011101 ,
#1570000000
0#
0(
#1575000000
1#
b0010011101 %
1(
b0010011101 *
b0010011101 +
b0010011110 ,
#1580000000
0#
0(
#1585000000
1#
b0010011110 %
1(
b0010011110 *
b0010011110 +
b0010011111 ,
#1590000000
0#
0(
#1595000000
1#
b0010011111 %
1(
b0010011111 *
b0010011111 +
b0010100000 ,
#1600000000
0#
0(
#1605000000
1#
b0010100000 %
1(
b0010100000 *
b0010100000 +
b0010100001 ,
#1610000000
0#
0(
#1615000000
1#
b0010100001 %
1(
b0010100001 *
b0010100001 +
b0010100010 ,
#1620000000
0#
0(
#1625000000
1#
b0010100010 %
1(
b0010100010 *
b0010100010 +
b0010100011 ,
#1630000000
0#
0(
#1635000000
1#
b0010100011 %
1(
b0010100011 *
b0010100011 +
b0010100100 ,
#1640000000
0#
0(
#1645000000
1#
b0010100100 %
1(
b0010100100 *
b0010100100 +
b0010100101 ,
#1650000000
0#
0(
#1655000000
1#
b0010100101 %
1(
b0010100101 *
b0010100101 +
b0010100110 ,
#1660000000
0#
0(
#1665000000
1#
b0010100110 %
1(
b0010100110 *
b0010100110 +
b0010100111 ,
#1670000000
0#
0(
#1675000000
1#
b0010100111 %
1(
b0010100111 *
b0010100111 +
b0010101000 ,
#1680000000
0#
0(
#1685000000
1#
b0010101000 %
1(
b0010101000 *
b0010101000 +
b0010101001 ,
#1690000000
0#
0(
#1695000000
1#
b0010101001 %
1(
b0010101001 *
b0010101001 +
b0010101010 ,
#1700000000
0#
0(
#1705000000
1#
b0010101010 %
1(
b0010101010 *
b0010101010 +
b0010101011 ,
#1710000000
0#
0(
#1715000000
1#
b0010101011 %
1(
b0010101011 *
b0010101011 +
b0010101100 ,
#1720000000
0#
0(
#1725000000
1#
b0010101100 %
1(
b0010101100 *
b0010101100 +
b0010101101 ,
#1730000000
0#
0(
#1735000000
1#
b0010101101 %
1(
b0010101101 *
b0010101101 +
b0010101110 ,
#1740000000
0#
0(
#1745000000
1#
b0010101110 %
1(
b0010101110 *
b0010101110 +
b0010101111 ,
#1750000000
0#
0(
#1755000000
1#
b0010101111 %
1(
b0010101111 *
b0010101111 +
b0010110000 ,
#1760000000
0#
0(
#1765000000
1#
b0010110000 %
1(
b0010110000 *
b0010110000 +
b0010110001 ,
#1770000000
0#
0(
#1775000000
1#
b0010110001 %
1(
b0010110001 *
b0010110001 +
b0010110010 ,
#1780000000
0#
0(
#1785000000
1#
b0010110010 %
1(
b0010110010 *
b0010110010 +
b0010110011 ,
#1790000000
0#
0(
#1795000000
1#
b0010110011 %
1(
b0010110011 *
b0010110011 +
b0010110100 ,
#1800000000
0#
0(
#1805000000
1#
b0010110100 %
1(
b0010110100 *
b0010110100 +
b0010110101 ,
#1810000000
0#
0(
#1815000000
1#
b0010110101 %
1(
b0010110101 *
b0010110101 +
b0010110110 ,
#1820000000
0#
0(
#1825000000
1#
b0010110110 %
1(
b0010110110 *
b0010110110 +
b0010110111 ,
#1830000000
0#
0(
#1835000000
1#
b0010110111 %
1(
b0010110111 *
b0010110111 +
b0010111000 ,
#1840000000
0#
0(
#1845000000
1#
b0010111000 %
1(
b0010111000 *
b0010111000 +
b0010111001 ,
#1850000000
0#
0(
#1855000000
1#
b0010111001 %
1(
b0010111001 *
b0010111001 +
b0010111010 ,
#1860000000
0#
0(
#1865000000
1#
b0010111010 %
1(
b0010111010 *
b0010111010 +
b0010111011 ,
#1870000000
0#
0(
#1875000000
1#
b0010111011 %
1(
b0010111011 *
b0010111011 +
b0010111100 ,
#1880000000
0#
0(
#1885000000
1#
b0010111100 %
1(
b0010111100 *
b0010111100 +
b0010111101 ,
#1890000000
0#
0(
#1895000000
1#
b0010111101 %
1(
b0010111101 *
b0010111101 +
b0010111110 ,
#1900000000
0#
0(
#1905000000
1#
b0010111110 %
1(
b0010111110 *
b0010111110 +
b0010111111 ,
#1910000000
0#
0(
#1915000000
1#
b0010111111 %
1(
b0010111111 *
b0010111111 +
b0011000000 ,
#1920000000
0#
0(
#1925000000
1#
b0011000000 %
1(
b0011000000 *
b0011000000 +
b0011000001 ,
#1930000000
0#
0(
#1935000000
1#
b0011000001 %
1(
b0011000001 *
b0011000001 +
b0011000010 ,
#1940000000
0#
0(
#1945000000
1#
b0011000010 %
1(
b0011000010 *
b0011000010 +
b0011000011 ,
#1950000000
0#
0(
#1955000000
1#
b0011000011 %
1(
b0011000011 *
b0011000011 +
b0011000100 ,
#1960000000
0#
0(
#1965000000
1#
b0011000100 %
1(
b0011000100 *
b0011000100 +
b0011000101 ,
#1970000000
0#
0(
#1975000000
1#
b0011000101 %
1(
b0011000101 *
b0011000101 +
b0011000110 ,
#1980000000
0#
0(
#1985000000
1#
b0011000110 %
1(
b0011000110 *
b0011000110 +
b0011000111 ,
#1990000000
0#
0(
#1995000000
1#
b0011000111 %
1(
b0011000111 *
b0011000111 +
b0011001000 ,
#2000000000
0#
0(
#2005000000
1#
1$
b0011001000 %
1(
1)
b0011001000 *
b0011001000 +
b0000000000 ,
#2010000000
0#
0(
#2015000000
1#
0$
b0000000000 %
1(
0)
b0000000000 *
b0000000000 +
b0000000001 ,
#2020000000
0#
0(
#2025000000
1#
b0000000001 %
1(
b0000000001 *
b0000000001 +
b0000000010 ,
#2030000000
0#
0(
#2035000000
1#
b0000000010 %
1(
b0000000010 *
b0000000010 +
b0000000011 ,
#2040000000
0#
0(
#2045000000
1#
b0000000011 %
1(
b0000000011 *
b0000000011 +
b0000000100 ,
#2050000000
0#
0(
#2055000000
1#
b0000000100 %
1(
b0000000100 *
b0000000100 +
b0000000101 ,
#2060000000
0#
0(
#2065000000
1#
b0000000101 %
1(
b0000000101 *
b0000000101 +
b0000000110 ,
#2070000000
0#
0(
#2075000000
1#
b0000000110 %
1(
b0000000110 *
b0000000110 +
b0000000111 ,
#2080000000
0#
0(
#2085000000
1#
b0000000111 %
1(
b0000000111 *
b0000000111 +
b0000001000 ,
#2090000000
0#
0(
#2095000000
1#
b0000001000 %
1(
b0000001000 *
b0000001000 +
b0000001001 ,
#2100000000
0#
0(
#2105000000
1#
b0000001001 %
1(
b0000001001 *
b0000001001 +
b0000001010 ,
#2110000000
0#
0(
#2115000000
1#
b0000001010 %
1(
b0000001010 *
b0000001010 +
b0000001011 ,
#2120000000
0#
0(
#2125000000
1#
b0000001011 %
1(
b0000001011 *
b0000001011 +
b0000001100 ,
#2130000000
0#
0(
#2135000000
1#
b0000001100 %
1(
b0000001100 *
b0000001100 +
b0000001101 ,
#2140000000
0#
0(
#2145000000
1#
b0000001101 %
1(
b0000001101 *
b0000001101 +
b0000001110 ,
#2150000000
0#
0(
#2155000000
1#
b0000001110 %
1(
b0000001110 *
b0000001110 +
b0000001111 ,
#2160000000
0#
0(
#2165000000
1#
b0000001111 %
1(
b0000001111 *
b0000001111 +
b0000010000 ,
#2170000000
0#
0(
#2175000000
1#
b0000010000 %
1(
b0000010000 *
b0000010000 +
b0000010001 ,
#2180000000
0#
0(
#2185000000
1#
b0000010001 %
1(
b0000010001 *
b0000010001 +
b0000010010 ,
#2190000000
0#
0(
#2195000000
1#
b0000010010 %
1(
b0000010010 *
b0000010010 +
b0000010011 ,
#2200000000
0#
0(
#2205000000
1#
b0000010011 %
1(
b0000010011 *
b0000010011 +
b0000010100 ,
#2210000000
0#
0(
#2215000000
1#
b0000010100 %
1(
b0000010100 *
b0000010100 +
b0000010101 ,
#2220000000
0#
0(
#2225000000
1#
b0000010101 %
1(
b0000010101 *
b0000010101 +
b0000010110 ,
#2230000000
0#
0(
#2235000000
1#
b0000010110 %
1(
b0000010110 *
b0000010110 +
b0000010111 ,
#2240000000
0#
0(
#2245000000
1#
b0000010111 %
1(
b0000010111 *
b0000010111 +
b0000011000 ,
#2250000000
0#
0(
#2255000000
1#
b0000011000 %
1(
b0000011000 *
b0000011000 +
b0000011001 ,
#2260000000
0#
0(
#2265000000
1#
b0000011001 %
1(
b0000011001 *
b0000011001 +
b0000011010 ,
#2270000000
0#
0(
#2275000000
1#
b0000011010 %
1(
b0000011010 *
b0000011010 +
b0000011011 ,
#2280000000
0#
0(
#2285000000
1#
b0000011011 %
1(
b0000011011 *
b0000011011 +
b0000011100 ,
#2290000000
0#
0(
#2295000000
1#
b0000011100 %
1(
b0000011100 *
b0000011100 +
b0000011101 ,
#2300000000
0#
0(
#2305000000
1#
b0000011101 %
1(
b0000011101 *
b0000011101 +
b0000011110 ,
#2310000000
0#
0(
#2315000000
1#
b0000011110 %
1(
b0000011110 *
b0000011110 +
b0000011111 ,
#2320000000
0#
0(
#2325000000
1#
b0000011111 %
1(
b0000011111 *
b0000011111 +
b0000100000 ,
#2330000000
0#
0(
#2335000000
1#
b0000100000 %
1(
b0000100000 *
b0000100000 +
b0000100001 ,
#2340000000
0#
0(
#2345000000
1#
b0000100001 %
1(
b0000100001 *
b0000100001 +
b0000100010 ,
#2350000000
0#
0(
#2355000000
1#
b0000100010 %
1(
b0000100010 *
b0000100010 +
b0000100011 ,
#2360000000
0#
0(
#2365000000
1#
b0000100011 %
1(
b0000100011 *
b0000100011 +
b0000100100 ,
#2370000000
0#
0(
#2375000000
1#
b0000100100 %
1(
b0000100100 *
b0000100100 +
b0000100101 ,
#2380000000
0#
0(
#2385000000
1#
b0000100101 %
1(
b0000100101 *
b0000100101 +
b0000100110 ,
#2390000000
0#
0(
#2395000000
1#
b0000100110 %
1(
b0000100110 *
b0000100110 +
b0000100111 ,
#2400000000
0#
0(
#2405000000
1#
b0000100111 %
1(
b0000100111 *
b0000100111 +
b0000101000 ,
#2410000000
0#
0(
#2415000000
1#
b0000101000 %
1(
b0000101000 *
b0000101000 +
b0000101001 ,
#2420000000
0#
0(
#2425000000
1#
b0000101001 %
1(
b0000101001 *
b0000101001 +
b0000101010 ,
#2430000000
0#
0(
#2435000000
1#
b0000101010 %
1(
b0000101010 *
b0000101010 +
b0000101011 ,
